Workbook
Name budget: 'Budget Dashboard'!$L1
Name budget_range: 'Budget Dashboard'!$Q1
Name budget_rank: 'Budget Dashboard'!$R1
Name cc_budget: Calculations!$K1
Name cc_delta: Calculations!$L1
Name cc_in_Focus: Calculations!$G1
Name cc_month_number: Calculations!$F1
Name cc_show_remaining_rudget: Calculations!$I1
Name cc_show_type: Calculations!$H1
Name cc_tracked: Calculations!$J1
Name cc_type: Calculations!$E1
Name comb_rank: 'Budget Dashboard'!$S1
Name comb_rank_norm: 'Budget Dashboard'!$U1
Name comb_rank_norm_run_range: 'Budget Dashboard'!$V1
Name comb_rank_range: 'Budget Dashboard'!$T1
Name comb_rank_unique: 'Budget Dashboard'!$W1
Name current_date: TODAY()
Name expenses_header_row: ROW(Expenses[[#Headers],[Expenses]])
Name expenses_max_row: MAX(ROW(Expenses[]))
Name expenses_min_row: MIN(ROW(Expenses[]))
Name expenses_total_row: ROW('Budget Planning'!$C$46)
Name header_row_id: 'Budget Dashboard'!$D1
Name income_header_row: ROW(Income[[#Headers],[Income]])
Name income_max_row: MAX(ROW(Income[]))
Name income_min_row: MIN(ROW(Income[]))
Name income_total_row: ROW('Budget Planning'!$C$27)
Name is_cat: 'Budget Dashboard'!$F1
Name is_empty: 'Budget Dashboard'!$H1
Name is_header: 'Budget Dashboard'!$E1
Name is_total: 'Budget Dashboard'!$G1
Name item: 'Budget Dashboard'!$J1
Name out_budget: 'Budget Dashboard'!$AA1
Name out_percentage_completed: 'Budget Dashboard'!$AB1
Name out_tracked: 'Budget Dashboard'!$Z1
Name row_id: 'Budget Dashboard'!$C1
Name savings_header_row: ROW(Savings[[#Headers],[Savings]])
Name savings_max_row: MAX(ROW(Savings[]))
Name savings_min_row: MIN(ROW(Savings[]))
Name Savings_rate_calculation_type: Settings!$E$22
Name savings_top_row: ROW(Savings[[#Headers],[Savings]])
Name savings_total_row: ROW('Budget Planning'!$C$65)
Name selected_period: Calculations!$E$20
Name selected_period_display: Calculations!$E$21
Name selected_year: Calculations!$E$19
Name Shift_late_income_starting_date: Settings!$E$18
Name Shift_late_income_status: Settings!$E$16
Name sort_max_row: 'Budget Dashboard'!$N1
Name sort_min_row: 'Budget Dashboard'!$M1
Name Starting_Year: Settings!$E$8
Name tracked: 'Budget Dashboard'!$K1
Name tracked_range: 'Budget Dashboard'!$O1
Name tracked_rank: 'Budget Dashboard'!$P1
Name type: 'Budget Dashboard'!$I1

Sheet Budget Dashboard
B2: Budget Dashboard
AQ5: Year
AN6: Select the year to view -> | AQ6: Current Year
AQ8: Period
AN9: Select the period to view -> | AQ9: Total Year
Y11: ="Breakdown - " & IF(selected_period="Total Year", selected_year & " (Total Year)", selected_period_display & " " & selected_year) -> Breakdown - 2026 (Total Year) | AF11: ="Summary - " & IF(selected_period="Total Year", selected_year & " (Total Year)", selected_period_display & " " & selected_year) -> Summary - 2026 (Total Year)
C12: row_id | D12: header_row_id | E12: is_header | F12: is_cat | G12: is_total | H12: is_empty | I12: type | J12: item | K12: tracked | L12: budget | M12: sort_min_row | N12: sort_max_row | O12: tracked_range | P12: tracked_rank | Q12: budget_range | R12: budget_rank | S12: comb_rank | T12: comb_rank_range | U12: comb_rank_norm | V12: comb_rank_norm_run_range | W12: comb_rank_unique | X12: sorted_row_id [Lookup]
C13: {=income_header_row} -> 10 | D13: =IF(is_header,row_id, IF(NOT(is_empty),D12,-1)) -> 10 | E13: {=1*OR(row_id=income_header_row, row_id=expenses_header_row, row_id=savings_header_row)} -> 1 | F13: =1*NOT(OR(is_header, is_total, is_empty)) -> 0 | G13: {=1*OR(row_id=income_total_row, row_id=expenses_total_row, row_id=savings_total_row)} -> 0 | H13: =1*OR(row_id="/1", row_id="/2", row_id=-1) -> 0 | I13: {=IFERROR(INDEX('Budget Planning'!$C:$C, header_row_id),"")} -> Income | J13: {=IFERROR(INDEX('Budget Planning'!$C:$C, row_id), "")} -> Income | K13: {=IF( OR(is_header, is_empty, selected_period=""), "", IF( is_total, IF( selected_period="Total Year", SUMPRODUCT( Tracking[Amount] * (Tracking[Type]=type) * (YEAR(Tracking[Effective Date])=selected_year) ), SUMPRODUCT( Tracking[Amount] * (Tracking[Type]=type) * (YEAR(Tracking[Effective Date])=selected_year) * (MONTH(Tracking[Effective Date])=selected_period) ) ), IF( selected_period="Total Year", SUMPRODUCT( Tracking[Amount] * (Tracking[Type]=type) * (Tracking[Category]=item) * (YEAR(Tracking[Effective Date])=selected_year) ), SUMPRODUCT( Tracking[Amount] * (Tracking[Type]=type) * (Tracking[Category]=item) * (YEAR(Tracking[Effective Date])=selected_year) * (MONTH(Tracking[Effective Date])=selected_period) ) ) ) )} | L13: {=IF( OR(is_header, is_empty), "", INDEX( 'Budget Planning'!$E:$FA, row_id, MATCH( IF( selected_period = "Total Year", selected_year, DATE(selected_year, selected_period, 1) ), 'Budget Planning'!$E$10:$FA$10, 0 ) ) )} | M13: {=IF( is_cat, IF( header_row_id = income_header_row, MATCH(income_min_row, $C:$C, 0), IF( header_row_id = expenses_header_row, MATCH(expenses_min_row, $C:$C, 0), IF( header_row_id = savings_header_row, MATCH(savings_min_row, $C:$C, 0), "" ) ) ), "" )} | N13: {=IF( is_cat, IF( header_row_id = income_header_row, MATCH(income_max_row, $C:$C, 0), IF( header_row_id = expenses_header_row, MATCH(expenses_max_row, $C:$C, 0), IF( header_row_id = savings_header_row, MATCH(savings_max_row, $C:$C, 0), "" ) ) ), "" )} | O13: =IF(is_cat, ADDRESS(sort_min_row, COLUMN(tracked)) &":" & ADDRESS(sort_max_row, COLUMN(tracked)), "") | P13: =IF(is_cat, RANK(tracked, INDIRECT(tracked_range), 0), "") | Q13: =IF(is_cat, ADDRESS(sort_min_row, COLUMN(budget)) &":" & ADDRESS(sort_max_row, COLUMN(budget)), "") | R13: =IF(is_cat, RANK(budget, INDIRECT(budget_range), 0), "") | S13: =IF(is_cat, _xlfn.NUMBERVALUE(tracked_rank & budget_rank), "") | T13: =IF(is_cat, ADDRESS(sort_min_row, COLUMN(comb_rank)) &":" & ADDRESS(sort_max_row, COLUMN(comb_rank)), "") | U13: =IF(is_cat,RANK(comb_rank,INDIRECT(comb_rank_range),1),"") | V13: =IF(is_cat, ADDRESS(sort_min_row, COLUMN(comb_rank_norm)) &":" & ADDRESS(ROW(), COLUMN(comb_rank_norm)), "") | W13: =IF(is_cat, comb_rank_norm + COUNTIF(INDIRECT(comb_rank_norm_run_range), comb_rank_norm)-1, "") | X13: =IF(is_cat, header_row_id + comb_rank_unique, row_id) -> 10 | Y13: =IF(is_empty, "", INDEX($J:$J, MATCH(row_id, $X:$X, 0))) -> Income | Z13: =IF(is_empty, "", IF(is_header, "Tracked", INDEX($K:$K, MATCH(row_id, $X:$X, 0)))) -> Tracked | AA13: =IF(is_empty, "", IF(is_header, "Budget", INDEX($L:$L, MATCH(row_id, $X:$X, 0)))) -> Budget | AB13: =IF(is_empty, "", IF(is_header, "% Compl.", IFERROR(out_tracked / out_budget, "-"))) -> % Compl. | AC13: =IF(is_empty, "", IF(is_header, "Remaining", IF(out_budget - out_tracked > 0, out_budget - out_tracked, 0))) -> Remaining | AD13: =IF(is_empty, "", IF(is_header, "Excess", IF(out_budget - out_tracked < 0, out_tracked - out_budget, 0))) -> Excess
C14: {=IF(C13=-1,-1, IF(C13<income_max_row, C13+1, IF(C13=income_max_row, income_total_row, IF(C13=income_total_row, "/1", IF(C13="/1", expenses_header_row, IF(C13<expenses_max_row, C13+1, IF(C13=expenses_max_row, expenses_total_row, IF(C13=expenses_total_row, "/2", IF(C13="/2", savings_header_row, IF(C13<savings_max_row, C13+1, IF(C13=savings_max_row, savings_total_row, -1)))))))))))} -> 11 | D14: =IF(is_header,row_id, IF(NOT(is_empty),D13,-1)) -> 10 | E14: {=1*OR(row_id=income_header_row, row_id=expenses_header_row, row_id=savings_header_row)} -> 0 | F14: =1*NOT(OR(is_header, is_total, is_empty)) -> 1 | G14: {=1*OR(row_id=income_total_row, row_id=expenses_total_row, row_id=savings_total_row)} -> 0 | H14: =1*OR(row_id="/1", row_id="/2", row_id=-1) -> 0 | I14: {=IFERROR(INDEX('Budget Planning'!$C:$C, header_row_id),"")} -> Income | J14: {=IFERROR(INDEX('Budget Planning'!$C:$C, row_id), "")} -> JPMC Salary | K14: {=IF( OR(is_header, is_empty, selected_period=""), "", IF( is_total, IF( selected_period="Total Year", SUMPRODUCT( Tracking[Amount] * (Tracking[Type]=type) * (YEAR(Tracking[Effective Date])=selected_year) ), SUMPRODUCT( Tracking[Amount] * (Tracking[Type]=type) * (YEAR(Tracking[Effective Date])=selected_year) * (MONTH(Tracking[Effective Date])=selected_period) ) ), IF( selected_period="Total Year", SUMPRODUCT( Tracking[Amount] * (Tracking[Type]=type) * (Tracking[Category]=item) * (YEAR(Tracking[Effective Date])=selected_year) ), SUMPRODUCT( Tracking[Amount] * (Tracking[Type]=type) * (Tracking[Category]=item) * (YEAR(Tracking[Effective Date])=selected_year) * (MONTH(Tracking[Effective Date])=selected_period) ) ) ) )} -> 291488 | L14: {=IF( OR(is_header, is_empty), "", INDEX( 'Budget Planning'!$E:$FA, row_id, MATCH( IF( selected_period = "Total Year", selected_year, DATE(selected_year, selected_period, 1) ), 'Budget Planning'!$E$10:$FA$10, 0 ) ) )} -> 291488 | M14: {=IF( is_cat, IF( header_row_id = income_header_row, MATCH(income_min_row, $C:$C, 0), IF( header_row_id = expenses_header_row, MATCH(expenses_min_row, $C:$C, 0), IF( header_row_id = savings_header_row, MATCH(savings_min_row, $C:$C, 0), "" ) ) ), "" )} -> 14 | N14: {=IF( is_cat, IF( header_row_id = income_header_row, MATCH(income_max_row, $C:$C, 0), IF( header_row_id = expenses_header_row, MATCH(expenses_max_row, $C:$C, 0), IF( header_row_id = savings_header_row, MATCH(savings_max_row, $C:$C, 0), "" ) ) ), "" )} -> 18 | O14: =IF(is_cat, ADDRESS(sort_min_row, COLUMN(tracked)) &":" & ADDRESS(sort_max_row, COLUMN(tracked)), "") -> $K$14:$K$18 | P14: =IF(is_cat, RANK(tracked, INDIRECT(tracked_range), 0), "") -> 1 | Q14: =IF(is_cat, ADDRESS(sort_min_row, COLUMN(budget)) &":" & ADDRESS(sort_max_row, COLUMN(budget)), "") -> $L$14:$L$18 | R14: =IF(is_cat, RANK(budget, INDIRECT(budget_range), 0), "") -> 1 | S14: =IF(is_cat, _xlfn.NUMBERVALUE(tracked_rank & budget_rank), "") -> 11 | T14: =IF(is_cat, ADDRESS(sort_min_row, COLUMN(comb_rank)) &":" & ADDRESS(sort_max_row, COLUMN(comb_rank)), "") -> $S$14:$S$18 | U14: =IF(is_cat,RANK(comb_rank,INDIRECT(comb_rank_range),1),"") -> 1 | V14: =IF(is_cat, ADDRESS(sort_min_row, COLUMN(comb_rank_norm)) &":" & ADDRESS(ROW(), COLUMN(comb_rank_norm)), "") -> $U$14:$U$14 | W14: =IF(is_cat, comb_rank_norm + COUNTIF(INDIRECT(comb_rank_norm_run_range), comb_rank_norm)-1, "") -> 1 | X14: =IF(is_cat, header_row_id + comb_rank_unique, row_id) -> 11 | Y14: =IF(is_empty, "", INDEX($J:$J, MATCH(row_id, $X:$X, 0))) -> JPMC Salary | Z14: =IF(is_empty, "", IF(is_header, "Tracked", INDEX($K:$K, MATCH(row_id, $X:$X, 0)))) -> 291488 | AA14: =IF(is_empty, "", IF(is_header, "Budget", INDEX($L:$L, MATCH(row_id, $X:$X, 0)))) -> 291488 | AB14: =IF(is_empty, "", IF(is_header, "% Compl.", IFERROR(out_tracked / out_budget, "-"))) -> 1 | AC14: =IF(is_empty, "", IF(is_header, "Remaining", IF(out_budget - out_tracked > 0, out_budget - out_tracked, 0))) -> 0 | AD14: =IF(is_empty, "", IF(is_header, "Excess", IF(out_budget - out_tracked < 0, out_tracked - out_budget, 0))) -> 0
C15: {=IF(C14=-1,-1, IF(C14<income_max_row, C14+1, IF(C14=income_max_row, income_total_row, IF(C14=income_total_row, "/1", IF(C14="/1", expenses_header_row, IF(C14<expenses_max_row, C14+1, IF(C14=expenses_max_row, expenses_total_row, IF(C14=expenses_total_row, "/2", IF(C14="/2", savings_header_row, IF(C14<savings_max_row, C14+1, IF(C14=savings_max_row, savings_total_row, -1)))))))))))} -> 12 | D15: =IF(is_header,row_id, IF(NOT(is_empty),D14,-1)) -> 10 | E15: {=1*OR(row_id=income_header_row, row_id=expenses_header_row, row_id=savings_header_row)} -> 0 | F15: =1*NOT(OR(is_header, is_total, is_empty)) -> 1 | G15: {=1*OR(row_id=income_total_row, row_id=expenses_total_row, row_id=savings_total_row)} -> 0 | H15: =1*OR(row_id="/1", row_id="/2", row_id=-1) -> 0 | I15: {=IFERROR(INDEX('Budget Planning'!$C:$C, header_row_id),"")} -> Income | J15: {=IFERROR(INDEX('Budget Planning'!$C:$C, row_id), "")} -> JPMC Bonus | K15: {=IF( OR(is_header, is_empty, selected_period=""), "", IF( is_total, IF( selected_period="Total Year", SUMPRODUCT( Tracking[Amount] * (Tracking[Type]=type) * (YEAR(Tracking[Effective Date])=selected_year) ), SUMPRODUCT( Tracking[Amount] * (Tracking[Type]=type) * (YEAR(Tracking[Effective Date])=selected_year) * (MONTH(Tracking[Effective Date])=selected_period) ) ), IF( selected_period="Total Year", SUMPRODUCT( Tracking[Amount] * (Tracking[Type]=type) * (Tracking[Category]=item) * (YEAR(Tracking[Effective Date])=selected_year) ), SUMPRODUCT( Tracking[Amount] * (Tracking[Type]=type) * (Tracking[Category]=item) * (YEAR(Tracking[Effective Date])=selected_year) * (MONTH(Tracking[Effective Date])=selected_period) ) ) ) )} -> 0 | L15: {=IF( OR(is_header, is_empty), "", INDEX( 'Budget Planning'!$E:$FA, row_id, MATCH( IF( selected_period = "Total Year", selected_year, DATE(selected_year, selected_period, 1) ), 'Budget Planning'!$E$10:$FA$10, 0 ) ) )} -> 0 | M15: {=IF( is_cat, IF( header_row_id = income_header_row, MATCH(income_min_row, $C:$C, 0), IF( header_row_id = expenses_header_row, MATCH(expenses_min_row, $C:$C, 0), IF( header_row_id = savings_header_row, MATCH(savings_min_row, $C:$C, 0), "" ) ) ), "" )} -> 14 | N15: {=IF( is_cat, IF( header_row_id = income_header_row, MATCH(income_max_row, $C:$C, 0), IF( header_row_id = expenses_header_row, MATCH(expenses_max_row, $C:$C, 0), IF( header_row_id = savings_header_row, MATCH(savings_max_row, $C:$C, 0), "" ) ) ), "" )} -> 18 | O15: =IF(is_cat, ADDRESS(sort_min_row, COLUMN(tracked)) &":" & ADDRESS(sort_max_row, COLUMN(tracked)), "") -> $K$14:$K$18 | P15: =IF(is_cat, RANK(tracked, INDIRECT(tracked_range), 0), "") -> 2 | Q15: =IF(is_cat, ADDRESS(sort_min_row, COLUMN(budget)) &":" & ADDRESS(sort_max_row, COLUMN(budget)), "") -> $L$14:$L$18 | R15: =IF(is_cat, RANK(budget, INDIRECT(budget_range), 0), "") -> 3 | S15: =IF(is_cat, _xlfn.NUMBERVALUE(tracked_rank & budget_rank), "") -> 23 | T15: =IF(is_cat, ADDRESS(sort_min_row, COLUMN(comb_rank)) &":" & ADDRESS(sort_max_row, COLUMN(comb_rank)), "") -> $S$14:$S$18 | U15: =IF(is_cat,RANK(comb_rank,INDIRECT(comb_rank_range),1),"") -> 3 | V15: =IF(is_cat, ADDRESS(sort_min_row, COLUMN(comb_rank_norm)) &":" & ADDRESS(ROW(), COLUMN(comb_rank_norm)), "") -> $U$14:$U$15 | W15: =IF(is_cat, comb_rank_norm + COUNTIF(INDIRECT(comb_rank_norm_run_range), comb_rank_norm)-1, "") -> 3 | X15: =IF(is_cat, header_row_id + comb_rank_unique, row_id) -> 13 | Y15: =IF(is_empty, "", INDEX($J:$J, MATCH(row_id, $X:$X, 0))) -> One Time Income | Z15: =IF(is_empty, "", IF(is_header, "Tracked", INDEX($K:$K, MATCH(row_id, $X:$X, 0)))) -> 0 | AA15: =IF(is_empty, "", IF(is_header, "Budget", INDEX($L:$L, MATCH(row_id, $X:$X, 0)))) -> 2100 | AB15: =IF(is_empty, "", IF(is_header, "% Compl.", IFERROR(out_tracked / out_budget, "-"))) -> 0 | AC15: =IF(is_empty, "", IF(is_header, "Remaining", IF(out_budget - out_tracked > 0, out_budget - out_tracked, 0))) -> 2100 | AD15: =IF(is_empty, "", IF(is_header, "Excess", IF(out_budget - out_tracked < 0, out_tracked - out_budget, 0))) -> 0
C16: {=IF(C15=-1,-1, IF(C15<income_max_row, C15+1, IF(C15=income_max_row, income_total_row, IF(C15=income_total_row, "/1", IF(C15="/1", expenses_header_row, IF(C15<expenses_max_row, C15+1, IF(C15=expenses_max_row, expenses_total_row, IF(C15=expenses_total_row, "/2", IF(C15="/2", savings_header_row, IF(C15<savings_max_row, C15+1, IF(C15=savings_max_row, savings_total_row, -1)))))))))))} -> 13 | D16: =IF(is_header,row_id, IF(NOT(is_empty),D15,-1)) -> 10 | E16: {=1*OR(row_id=income_header_row, row_id=expenses_header_row, row_id=savings_header_row)} -> 0 | F16: =1*NOT(OR(is_header, is_total, is_empty)) -> 1 | G16: {=1*OR(row_id=income_total_row, row_id=expenses_total_row, row_id=savings_total_row)} -> 0 | H16: =1*OR(row_id="/1", row_id="/2", row_id=-1) -> 0 | I16: {=IFERROR(INDEX('Budget Planning'!$C:$C, header_row_id),"")} -> Income | J16: {=IFERROR(INDEX('Budget Planning'!$C:$C, row_id), "")} -> Side Hustle | K16: {=IF( OR(is_header, is_empty, selected_period=""), "", IF( is_total, IF( selected_period="Total Year", SUMPRODUCT( Tracking[Amount] * (Tracking[Type]=type) * (YEAR(Tracking[Effective Date])=selected_year) ), SUMPRODUCT( Tracking[Amount] * (Tracking[Type]=type) * (YEAR(Tracking[Effective Date])=selected_year) * (MONTH(Tracking[Effective Date])=selected_period) ) ), IF( selected_period="Total Year", SUMPRODUCT( Tracking[Amount] * (Tracking[Type]=type) * (Tracking[Category]=item) * (YEAR(Tracking[Effective Date])=selected_year) ), SUMPRODUCT( Tracking[Amount] * (Tracking[Type]=type) * (Tracking[Category]=item) * (YEAR(Tracking[Effective Date])=selected_year) * (MONTH(Tracking[Effective Date])=selected_period) ) ) ) )} -> 0 | L16: {=IF( OR(is_header, is_empty), "", INDEX( 'Budget Planning'!$E:$FA, row_id, MATCH( IF( selected_period = "Total Year", selected_year, DATE(selected_year, selected_period, 1) ), 'Budget Planning'!$E$10:$FA$10, 0 ) ) )} -> 0 | M16: {=IF( is_cat, IF( header_row_id = income_header_row, MATCH(income_min_row, $C:$C, 0), IF( header_row_id = expenses_header_row, MATCH(expenses_min_row, $C:$C, 0), IF( header_row_id = savings_header_row, MATCH(savings_min_row, $C:$C, 0), "" ) ) ), "" )} -> 14 | N16: {=IF( is_cat, IF( header_row_id = income_header_row, MATCH(income_max_row, $C:$C, 0), IF( header_row_id = expenses_header_row, MATCH(expenses_max_row, $C:$C, 0), IF( header_row_id = savings_header_row, MATCH(savings_max_row, $C:$C, 0), "" ) ) ), "" )} -> 18 | O16: =IF(is_cat, ADDRESS(sort_min_row, COLUMN(tracked)) &":" & ADDRESS(sort_max_row, COLUMN(tracked)), "") -> $K$14:$K$18 | P16: =IF(is_cat, RANK(tracked, INDIRECT(tracked_range), 0), "") -> 2 | Q16: =IF(is_cat, ADDRESS(sort_min_row, COLUMN(budget)) &":" & ADDRESS(sort_max_row, COLUMN(budget)), "") -> $L$14:$L$18 | R16: =IF(is_cat, RANK(budget, INDIRECT(budget_range), 0), "") -> 3 | S16: =IF(is_cat, _xlfn.NUMBERVALUE(tracked_rank & budget_rank), "") -> 23 | T16: =IF(is_cat, ADDRESS(sort_min_row, COLUMN(comb_rank)) &":" & ADDRESS(sort_max_row, COLUMN(comb_rank)), "") -> $S$14:$S$18 | U16: =IF(is_cat,RANK(comb_rank,INDIRECT(comb_rank_range),1),"") -> 3 | V16: =IF(is_cat, ADDRESS(sort_min_row, COLUMN(comb_rank_norm)) &":" & ADDRESS(ROW(), COLUMN(comb_rank_norm)), "") -> $U$14:$U$16 | W16: =IF(is_cat, comb_rank_norm + COUNTIF(INDIRECT(comb_rank_norm_run_range), comb_rank_norm)-1, "") -> 4 | X16: =IF(is_cat, header_row_id + comb_rank_unique, row_id) -> 14 | Y16: =IF(is_empty, "", INDEX($J:$J, MATCH(row_id, $X:$X, 0))) -> JPMC Bonus | Z16: =IF(is_empty, "", IF(is_header, "Tracked", INDEX($K:$K, MATCH(row_id, $X:$X, 0)))) -> 0 | AA16: =IF(is_empty, "", IF(is_header, "Budget", INDEX($L:$L, MATCH(row_id, $X:$X, 0)))) -> 0 | AB16: =IF(is_empty, "", IF(is_header, "% Compl.", IFERROR(out_tracked / out_budget, "-"))) -> - | AC16: =IF(is_empty, "", IF(is_header, "Remaining", IF(out_budget - out_tracked > 0, out_budget - out_tracked, 0))) -> 0 | AD16: =IF(is_empty, "", IF(is_header, "Excess", IF(out_budget - out_tracked < 0, out_tracked - out_budget, 0))) -> 0 | AI16: =Calculations!E35 -> JPMC Salary | AJ16: =Calculations!F35 -> 291488
C17: {=IF(C16=-1,-1, IF(C16<income_max_row, C16+1, IF(C16=income_max_row, income_total_row, IF(C16=income_total_row, "/1", IF(C16="/1", expenses_header_row, IF(C16<expenses_max_row, C16+1, IF(C16=expenses_max_row, expenses_total_row, IF(C16=expenses_total_row, "/2", IF(C16="/2", savings_header_row, IF(C16<savings_max_row, C16+1, IF(C16=savings_max_row, savings_total_row, -1)))))))))))} -> 14 | D17: =IF(is_header,row_id, IF(NOT(is_empty),D16,-1)) -> 10 | E17: {=1*OR(row_id=income_header_row, row_id=expenses_header_row, row_id=savings_header_row)} -> 0 | F17: =1*NOT(OR(is_header, is_total, is_empty)) -> 1 | G17: {=1*OR(row_id=income_total_row, row_id=expenses_total_row, row_id=savings_total_row)} -> 0 | H17: =1*OR(row_id="/1", row_id="/2", row_id=-1) -> 0 | I17: {=IFERROR(INDEX('Budget Planning'!$C:$C, header_row_id),"")} -> Income | J17: {=IFERROR(INDEX('Budget Planning'!$C:$C, row_id), "")} -> Bank Interest | K17: {=IF( OR(is_header, is_empty, selected_period=""), "", IF( is_total, IF( selected_period="Total Year", SUMPRODUCT( Tracking[Amount] * (Tracking[Type]=type) * (YEAR(Tracking[Effective Date])=selected_year) ), SUMPRODUCT( Tracking[Amount] * (Tracking[Type]=type) * (YEAR(Tracking[Effective Date])=selected_year) * (MONTH(Tracking[Effective Date])=selected_period) ) ), IF( selected_period="Total Year", SUMPRODUCT( Tracking[Amount] * (Tracking[Type]=type) * (Tracking[Category]=item) * (YEAR(Tracking[Effective Date])=selected_year) ), SUMPRODUCT( Tracking[Amount] * (Tracking[Type]=type) * (Tracking[Category]=item) * (YEAR(Tracking[Effective Date])=selected_year) * (MONTH(Tracking[Effective Date])=selected_period) ) ) ) )} -> 0 | L17: {=IF( OR(is_header, is_empty), "", INDEX( 'Budget Planning'!$E:$FA, row_id, MATCH( IF( selected_period = "Total Year", selected_year, DATE(selected_year, selected_period, 1) ), 'Budget Planning'!$E$10:$FA$10, 0 ) ) )} -> 0 | M17: {=IF( is_cat, IF( header_row_id = income_header_row, MATCH(income_min_row, $C:$C, 0), IF( header_row_id = expenses_header_row, MATCH(expenses_min_row, $C:$C, 0), IF( header_row_id = savings_header_row, MATCH(savings_min_row, $C:$C, 0), "" ) ) ), "" )} -> 14 | N17: {=IF( is_cat, IF( header_row_id = income_header_row, MATCH(income_max_row, $C:$C, 0), IF( header_row_id = expenses_header_row, MATCH(expenses_max_row, $C:$C, 0), IF( header_row_id = savings_header_row, MATCH(savings_max_row, $C:$C, 0), "" ) ) ), "" )} -> 18 | O17: =IF(is_cat, ADDRESS(sort_min_row, COLUMN(tracked)) &":" & ADDRESS(sort_max_row, COLUMN(tracked)), "") -> $K$14:$K$18 | P17: =IF(is_cat, RANK(tracked, INDIRECT(tracked_range), 0), "") -> 2 | Q17: =IF(is_cat, ADDRESS(sort_min_row, COLUMN(budget)) &":" & ADDRESS(sort_max_row, COLUMN(budget)), "") -> $L$14:$L$18 | R17: =IF(is_cat, RANK(budget, INDIRECT(budget_range), 0), "") -> 3 | S17: =IF(is_cat, _xlfn.NUMBERVALUE(tracked_rank & budget_rank), "") -> 23 | T17: =IF(is_cat, ADDRESS(sort_min_row, COLUMN(comb_rank)) &":" & ADDRESS(sort_max_row, COLUMN(comb_rank)), "") -> $S$14:$S$18 | U17: =IF(is_cat,RANK(comb_rank,INDIRECT(comb_rank_range),1),"") -> 3 | V17: =IF(is_cat, ADDRESS(sort_min_row, COLUMN(comb_rank_norm)) &":" & ADDRESS(ROW(), COLUMN(comb_rank_norm)), "") -> $U$14:$U$17 | W17: =IF(is_cat, comb_rank_norm + COUNTIF(INDIRECT(comb_rank_norm_run_range), comb_rank_norm)-1, "") -> 5 | X17: =IF(is_cat, header_row_id + comb_rank_unique, row_id) -> 15 | Y17: =IF(is_empty, "", INDEX($J:$J, MATCH(row_id, $X:$X, 0))) -> Side Hustle | Z17: =IF(is_empty, "", IF(is_header, "Tracked", INDEX($K:$K, MATCH(row_id, $X:$X, 0)))) -> 0 | AA17: =IF(is_empty, "", IF(is_header, "Budget", INDEX($L:$L, MATCH(row_id, $X:$X, 0)))) -> 0 | AB17: =IF(is_empty, "", IF(is_header, "% Compl.", IFERROR(out_tracked / out_budget, "-"))) -> - | AC17: =IF(is_empty, "", IF(is_header, "Remaining", IF(out_budget - out_tracked > 0, out_budget - out_tracked, 0))) -> 0 | AD17: =IF(is_empty, "", IF(is_header, "Excess", IF(out_budget - out_tracked < 0, out_tracked - out_budget, 0))) -> 0 | AI17: =Calculations!E36 | AJ17: =Calculations!F36
C18: {=IF(C17=-1,-1, IF(C17<income_max_row, C17+1, IF(C17=income_max_row, income_total_row, IF(C17=income_total_row, "/1", IF(C17="/1", expenses_header_row, IF(C17<expenses_max_row, C17+1, IF(C17=expenses_max_row, expenses_total_row, IF(C17=expenses_total_row, "/2", IF(C17="/2", savings_header_row, IF(C17<savings_max_row, C17+1, IF(C17=savings_max_row, savings_total_row, -1)))))))))))} -> 15 | D18: =IF(is_header,row_id, IF(NOT(is_empty),D17,-1)) -> 10 | E18: {=1*OR(row_id=income_header_row, row_id=expenses_header_row, row_id=savings_header_row)} -> 0 | F18: =1*NOT(OR(is_header, is_total, is_empty)) -> 1 | G18: {=1*OR(row_id=income_total_row, row_id=expenses_total_row, row_id=savings_total_row)} -> 0 | H18: =1*OR(row_id="/1", row_id="/2", row_id=-1) -> 0 | I18: {=IFERROR(INDEX('Budget Planning'!$C:$C, header_row_id),"")} -> Income | J18: {=IFERROR(INDEX('Budget Planning'!$C:$C, row_id), "")} -> One Time Income | K18: {=IF( OR(is_header, is_empty, selected_period=""), "", IF( is_total, IF( selected_period="Total Year", SUMPRODUCT( Tracking[Amount] * (Tracking[Type]=type) * (YEAR(Tracking[Effective Date])=selected_year) ), SUMPRODUCT( Tracking[Amount] * (Tracking[Type]=type) * (YEAR(Tracking[Effective Date])=selected_year) * (MONTH(Tracking[Effective Date])=selected_period) ) ), IF( selected_period="Total Year", SUMPRODUCT( Tracking[Amount] * (Tracking[Type]=type) * (Tracking[Category]=item) * (YEAR(Tracking[Effective Date])=selected_year) ), SUMPRODUCT( Tracking[Amount] * (Tracking[Type]=type) * (Tracking[Category]=item) * (YEAR(Tracking[Effective Date])=selected_year) * (MONTH(Tracking[Effective Date])=selected_period) ) ) ) )} -> 0 | L18: {=IF( OR(is_header, is_empty), "", INDEX( 'Budget Planning'!$E:$FA, row_id, MATCH( IF( selected_period = "Total Year", selected_year, DATE(selected_year, selected_period, 1) ), 'Budget Planning'!$E$10:$FA$10, 0 ) ) )} -> 2100 | M18: {=IF( is_cat, IF( header_row_id = income_header_row, MATCH(income_min_row, $C:$C, 0), IF( header_row_id = expenses_header_row, MATCH(expenses_min_row, $C:$C, 0), IF( header_row_id = savings_header_row, MATCH(savings_min_row, $C:$C, 0), "" ) ) ), "" )} -> 14 | N18: {=IF( is_cat, IF( header_row_id = income_header_row, MATCH(income_max_row, $C:$C, 0), IF( header_row_id = expenses_header_row, MATCH(expenses_max_row, $C:$C, 0), IF( header_row_id = savings_header_row, MATCH(savings_max_row, $C:$C, 0), "" ) ) ), "" )} -> 18 | O18: =IF(is_cat, ADDRESS(sort_min_row, COLUMN(tracked)) &":" & ADDRESS(sort_max_row, COLUMN(tracked)), "") -> $K$14:$K$18 | P18: =IF(is_cat, RANK(tracked, INDIRECT(tracked_range), 0), "") -> 2 | Q18: =IF(is_cat, ADDRESS(sort_min_row, COLUMN(budget)) &":" & ADDRESS(sort_max_row, COLUMN(budget)), "") -> $L$14:$L$18 | R18: =IF(is_cat, RANK(budget, INDIRECT(budget_range), 0), "") -> 2 | S18: =IF(is_cat, _xlfn.NUMBERVALUE(tracked_rank & budget_rank), "") -> 22 | T18: =IF(is_cat, ADDRESS(sort_min_row, COLUMN(comb_rank)) &":" & ADDRESS(sort_max_row, COLUMN(comb_rank)), "") -> $S$14:$S$18 | U18: =IF(is_cat,RANK(comb_rank,INDIRECT(comb_rank_range),1),"") -> 2 | V18: =IF(is_cat, ADDRESS(sort_min_row, COLUMN(comb_rank_norm)) &":" & ADDRESS(ROW(), COLUMN(comb_rank_norm)), "") -> $U$14:$U$18 | W18: =IF(is_cat, comb_rank_norm + COUNTIF(INDIRECT(comb_rank_norm_run_range), comb_rank_norm)-1, "") -> 2 | X18: =IF(is_cat, header_row_id + comb_rank_unique, row_id) -> 12 | Y18: =IF(is_empty, "", INDEX($J:$J, MATCH(row_id, $X:$X, 0))) -> Bank Interest | Z18: =IF(is_empty, "", IF(is_header, "Tracked", INDEX($K:$K, MATCH(row_id, $X:$X, 0)))) -> 0 | AA18: =IF(is_empty, "", IF(is_header, "Budget", INDEX($L:$L, MATCH(row_id, $X:$X, 0)))) -> 0 | AB18: =IF(is_empty, "", IF(is_header, "% Compl.", IFERROR(out_tracked / out_budget, "-"))) -> - | AC18: =IF(is_empty, "", IF(is_header, "Remaining", IF(out_budget - out_tracked > 0, out_budget - out_tracked, 0))) -> 0 | AD18: =IF(is_empty, "", IF(is_header, "Excess", IF(out_budget - out_tracked < 0, out_tracked - out_budget, 0))) -> 0 | AI18: =Calculations!E37 | AJ18: =Calculations!F37
C19: {=IF(C18=-1,-1, IF(C18<income_max_row, C18+1, IF(C18=income_max_row, income_total_row, IF(C18=income_total_row, "/1", IF(C18="/1", expenses_header_row, IF(C18<expenses_max_row, C18+1, IF(C18=expenses_max_row, expenses_total_row, IF(C18=expenses_total_row, "/2", IF(C18="/2", savings_header_row, IF(C18<savings_max_row, C18+1, IF(C18=savings_max_row, savings_total_row, -1)))))))))))} -> 27 | D19: =IF(is_header,row_id, IF(NOT(is_empty),D18,-1)) -> 10 | E19: {=1*OR(row_id=income_header_row, row_id=expenses_header_row, row_id=savings_header_row)} -> 0 | F19: =1*NOT(OR(is_header, is_total, is_empty)) -> 0 | G19: {=1*OR(row_id=income_total_row, row_id=expenses_total_row, row_id=savings_total_row)} -> 1 | H19: =1*OR(row_id="/1", row_id="/2", row_id=-1) -> 0 | I19: {=IFERROR(INDEX('Budget Planning'!$C:$C, header_row_id),"")} -> Income | J19: {=IFERROR(INDEX('Budget Planning'!$C:$C, row_id), "")} -> Total | K19: {=IF( OR(is_header, is_empty, selected_period=""), "", IF( is_total, IF( selected_period="Total Year", SUMPRODUCT( Tracking[Amount] * (Tracking[Type]=type) * (YEAR(Tracking[Effective Date])=selected_year) ), SUMPRODUCT( Tracking[Amount] * (Tracking[Type]=type) * (YEAR(Tracking[Effective Date])=selected_year) * (MONTH(Tracking[Effective Date])=selected_period) ) ), IF( selected_period="Total Year", SUMPRODUCT( Tracking[Amount] * (Tracking[Type]=type) * (Tracking[Category]=item) * (YEAR(Tracking[Effective Date])=selected_year) ), SUMPRODUCT( Tracking[Amount] * (Tracking[Type]=type) * (Tracking[Category]=item) * (YEAR(Tracking[Effective Date])=selected_year) * (MONTH(Tracking[Effective Date])=selected_period) ) ) ) )} -> 291488 | L19: {=IF( OR(is_header, is_empty), "", INDEX( 'Budget Planning'!$E:$FA, row_id, MATCH( IF( selected_period = "Total Year", selected_year, DATE(selected_year, selected_period, 1) ), 'Budget Planning'!$E$10:$FA$10, 0 ) ) )} -> 293588 | M19: {=IF( is_cat, IF( header_row_id = income_header_row, MATCH(income_min_row, $C:$C, 0), IF( header_row_id = expenses_header_row, MATCH(expenses_min_row, $C:$C, 0), IF( header_row_id = savings_header_row, MATCH(savings_min_row, $C:$C, 0), "" ) ) ), "" )} | N19: {=IF( is_cat, IF( header_row_id = income_header_row, MATCH(income_max_row, $C:$C, 0), IF( header_row_id = expenses_header_row, MATCH(expenses_max_row, $C:$C, 0), IF( header_row_id = savings_header_row, MATCH(savings_max_row, $C:$C, 0), "" ) ) ), "" )} | O19: =IF(is_cat, ADDRESS(sort_min_row, COLUMN(tracked)) &":" & ADDRESS(sort_max_row, COLUMN(tracked)), "") | P19: =IF(is_cat, RANK(tracked, INDIRECT(tracked_range), 0), "") | Q19: =IF(is_cat, ADDRESS(sort_min_row, COLUMN(budget)) &":" & ADDRESS(sort_max_row, COLUMN(budget)), "") | R19: =IF(is_cat, RANK(budget, INDIRECT(budget_range), 0), "") | S19: =IF(is_cat, _xlfn.NUMBERVALUE(tracked_rank & budget_rank), "") | T19: =IF(is_cat, ADDRESS(sort_min_row, COLUMN(comb_rank)) &":" & ADDRESS(sort_max_row, COLUMN(comb_rank)), "") | U19: =IF(is_cat,RANK(comb_rank,INDIRECT(comb_rank_range),1),"") | V19: =IF(is_cat, ADDRESS(sort_min_row, COLUMN(comb_rank_norm)) &":" & ADDRESS(ROW(), COLUMN(comb_rank_norm)), "") | W19: =IF(is_cat, comb_rank_norm + COUNTIF(INDIRECT(comb_rank_norm_run_range), comb_rank_norm)-1, "") | X19: =IF(is_cat, header_row_id + comb_rank_unique, row_id) -> 27 | Y19: =IF(is_empty, "", INDEX($J:$J, MATCH(row_id, $X:$X, 0))) -> Total | Z19: =IF(is_empty, "", IF(is_header, "Tracked", INDEX($K:$K, MATCH(row_id, $X:$X, 0)))) -> 291488 | AA19: =IF(is_empty, "", IF(is_header, "Budget", INDEX($L:$L, MATCH(row_id, $X:$X, 0)))) -> 293588 | AB19: =IF(is_empty, "", IF(is_header, "% Compl.", IFERROR(out_tracked / out_budget, "-"))) -> 0.99284712 | AC19: =IF(is_empty, "", IF(is_header, "Remaining", IF(out_budget - out_tracked > 0, out_budget - out_tracked, 0))) -> 2100 | AD19: =IF(is_empty, "", IF(is_header, "Excess", IF(out_budget - out_tracked < 0, out_tracked - out_budget, 0))) -> 0 | AI19: =Calculations!E38 | AJ19: =Calculations!F38
C20: {=IF(C19=-1,-1, IF(C19<income_max_row, C19+1, IF(C19=income_max_row, income_total_row, IF(C19=income_total_row, "/1", IF(C19="/1", expenses_header_row, IF(C19<expenses_max_row, C19+1, IF(C19=expenses_max_row, expenses_total_row, IF(C19=expenses_total_row, "/2", IF(C19="/2", savings_header_row, IF(C19<savings_max_row, C19+1, IF(C19=savings_max_row, savings_total_row, -1)))))))))))} -> /1 | D20: =IF(is_header,row_id, IF(NOT(is_empty),D19,-1)) -> -1 | E20: {=1*OR(row_id=income_header_row, row_id=expenses_header_row, row_id=savings_header_row)} -> 0 | F20: =1*NOT(OR(is_header, is_total, is_empty)) -> 0 | G20: {=1*OR(row_id=income_total_row, row_id=expenses_total_row, row_id=savings_total_row)} -> 0 | H20: =1*OR(row_id="/1", row_id="/2", row_id=-1) -> 1 | I20: {=IFERROR(INDEX('Budget Planning'!$C:$C, header_row_id),"")} | J20: {=IFERROR(INDEX('Budget Planning'!$C:$C, row_id), "")} | K20: {=IF( OR(is_header, is_empty, selected_period=""), "", IF( is_total, IF( selected_period="Total Year", SUMPRODUCT( Tracking[Amount] * (Tracking[Type]=type) * (YEAR(Tracking[Effective Date])=selected_year) ), SUMPRODUCT( Tracking[Amount] * (Tracking[Type]=type) * (YEAR(Tracking[Effective Date])=selected_year) * (MONTH(Tracking[Effective Date])=selected_period) ) ), IF( selected_period="Total Year", SUMPRODUCT( Tracking[Amount] * (Tracking[Type]=type) * (Tracking[Category]=item) * (YEAR(Tracking[Effective Date])=selected_year) ), SUMPRODUCT( Tracking[Amount] * (Tracking[Type]=type) * (Tracking[Category]=item) * (YEAR(Tracking[Effective Date])=selected_year) * (MONTH(Tracking[Effective Date])=selected_period) ) ) ) )} | L20: {=IF( OR(is_header, is_empty), "", INDEX( 'Budget Planning'!$E:$FA, row_id, MATCH( IF( selected_period = "Total Year", selected_year, DATE(selected_year, selected_period, 1) ), 'Budget Planning'!$E$10:$FA$10, 0 ) ) )} | M20: {=IF( is_cat, IF( header_row_id = income_header_row, MATCH(income_min_row, $C:$C, 0), IF( header_row_id = expenses_header_row, MATCH(expenses_min_row, $C:$C, 0), IF( header_row_id = savings_header_row, MATCH(savings_min_row, $C:$C, 0), "" ) ) ), "" )} | N20: {=IF( is_cat, IF( header_row_id = income_header_row, MATCH(income_max_row, $C:$C, 0), IF( header_row_id = expenses_header_row, MATCH(expenses_max_row, $C:$C, 0), IF( header_row_id = savings_header_row, MATCH(savings_max_row, $C:$C, 0), "" ) ) ), "" )} | O20: =IF(is_cat, ADDRESS(sort_min_row, COLUMN(tracked)) &":" & ADDRESS(sort_max_row, COLUMN(tracked)), "") | P20: =IF(is_cat, RANK(tracked, INDIRECT(tracked_range), 0), "") | Q20: =IF(is_cat, ADDRESS(sort_min_row, COLUMN(budget)) &":" & ADDRESS(sort_max_row, COLUMN(budget)), "") | R20: =IF(is_cat, RANK(budget, INDIRECT(budget_range), 0), "") | S20: =IF(is_cat, _xlfn.NUMBERVALUE(tracked_rank & budget_rank), "") | T20: =IF(is_cat, ADDRESS(sort_min_row, COLUMN(comb_rank)) &":" & ADDRESS(sort_max_row, COLUMN(comb_rank)), "") | U20: =IF(is_cat,RANK(comb_rank,INDIRECT(comb_rank_range),1),"") | V20: =IF(is_cat, ADDRESS(sort_min_row, COLUMN(comb_rank_norm)) &":" & ADDRESS(ROW(), COLUMN(comb_rank_norm)), "") | W20: =IF(is_cat, comb_rank_norm + COUNTIF(INDIRECT(comb_rank_norm_run_range), comb_rank_norm)-1, "") | X20: =IF(is_cat, header_row_id + comb_rank_unique, row_id) -> /1 | Y20: =IF(is_empty, "", INDEX($J:$J, MATCH(row_id, $X:$X, 0))) | Z20: =IF(is_empty, "", IF(is_header, "Tracked", INDEX($K:$K, MATCH(row_id, $X:$X, 0)))) | AA20: =IF(is_empty, "", IF(is_header, "Budget", INDEX($L:$L, MATCH(row_id, $X:$X, 0)))) | AB20: =IF(is_empty, "", IF(is_header, "% Compl.", IFERROR(out_tracked / out_budget, "-"))) | AC20: =IF(is_empty, "", IF(is_header, "Remaining", IF(out_budget - out_tracked > 0, out_budget - out_tracked, 0))) | AD20: =IF(is_empty, "", IF(is_header, "Excess", IF(out_budget - out_tracked < 0, out_tracked - out_budget, 0))) | AI20: =Calculations!E39 | AJ20: =Calculations!F39
C21: {=IF(C20=-1,-1, IF(C20<income_max_row, C20+1, IF(C20=income_max_row, income_total_row, IF(C20=income_total_row, "/1", IF(C20="/1", expenses_header_row, IF(C20<expenses_max_row, C20+1, IF(C20=expenses_max_row, expenses_total_row, IF(C20=expenses_total_row, "/2", IF(C20="/2", savings_header_row, IF(C20<savings_max_row, C20+1, IF(C20=savings_max_row, savings_total_row, -1)))))))))))} -> 29 | D21: =IF(is_header,row_id, IF(NOT(is_empty),D20,-1)) -> 29 | E21: {=1*OR(row_id=income_header_row, row_id=expenses_header_row, row_id=savings_header_row)} -> 1 | F21: =1*NOT(OR(is_header, is_total, is_empty)) -> 0 | G21: {=1*OR(row_id=income_total_row, row_id=expenses_total_row, row_id=savings_total_row)} -> 0 | H21: =1*OR(row_id="/1", row_id="/2", row_id=-1) -> 0 | I21: {=IFERROR(INDEX('Budget Planning'!$C:$C, header_row_id),"")} -> Expenses | J21: {=IFERROR(INDEX('Budget Planning'!$C:$C, row_id), "")} -> Expenses | K21: {=IF( OR(is_header, is_empty, selected_period=""), "", IF( is_total, IF( selected_period="Total Year", SUMPRODUCT( Tracking[Amount] * (Tracking[Type]=type) * (YEAR(Tracking[Effective Date])=selected_year) ), SUMPRODUCT( Tracking[Amount] * (Tracking[Type]=type) * (YEAR(Tracking[Effective Date])=selected_year) * (MONTH(Tracking[Effective Date])=selected_period) ) ), IF( selected_period="Total Year", SUMPRODUCT( Tracking[Amount] * (Tracking[Type]=type) * (Tracking[Category]=item) * (YEAR(Tracking[Effective Date])=selected_year) ), SUMPRODUCT( Tracking[Amount] * (Tracking[Type]=type) * (Tracking[Category]=item) * (YEAR(Tracking[Effective Date])=selected_year) * (MONTH(Tracking[Effective Date])=selected_period) ) ) ) )} | L21: {=IF( OR(is_header, is_empty), "", INDEX( 'Budget Planning'!$E:$FA, row_id, MATCH( IF( selected_period = "Total Year", selected_year, DATE(selected_year, selected_period, 1) ), 'Budget Planning'!$E$10:$FA$10, 0 ) ) )} | M21: {=IF( is_cat, IF( header_row_id = income_header_row, MATCH(income_min_row, $C:$C, 0), IF( header_row_id = expenses_header_row, MATCH(expenses_min_row, $C:$C, 0), IF( header_row_id = savings_header_row, MATCH(savings_min_row, $C:$C, 0), "" ) ) ), "" )} | N21: {=IF( is_cat, IF( header_row_id = income_header_row, MATCH(income_max_row, $C:$C, 0), IF( header_row_id = expenses_header_row, MATCH(expenses_max_row, $C:$C, 0), IF( header_row_id = savings_header_row, MATCH(savings_max_row, $C:$C, 0), "" ) ) ), "" )} | O21: =IF(is_cat, ADDRESS(sort_min_row, COLUMN(tracked)) &":" & ADDRESS(sort_max_row, COLUMN(tracked)), "") | P21: =IF(is_cat, RANK(tracked, INDIRECT(tracked_range), 0), "") | Q21: =IF(is_cat, ADDRESS(sort_min_row, COLUMN(budget)) &":" & ADDRESS(sort_max_row, COLUMN(budget)), "") | R21: =IF(is_cat, RANK(budget, INDIRECT(budget_range), 0), "") | S21: =IF(is_cat, _xlfn.NUMBERVALUE(tracked_rank & budget_rank), "") | T21: =IF(is_cat, ADDRESS(sort_min_row, COLUMN(comb_rank)) &":" & ADDRESS(sort_max_row, COLUMN(comb_rank)), "") | U21: =IF(is_cat,RANK(comb_rank,INDIRECT(comb_rank_range),1),"") | V21: =IF(is_cat, ADDRESS(sort_min_row, COLUMN(comb_rank_norm)) &":" & ADDRESS(ROW(), COLUMN(comb_rank_norm)), "") | W21: =IF(is_cat, comb_rank_norm + COUNTIF(INDIRECT(comb_rank_norm_run_range), comb_rank_norm)-1, "") | X21: =IF(is_cat, header_row_id + comb_rank_unique, row_id) -> 29 | Y21: =IF(is_empty, "", INDEX($J:$J, MATCH(row_id, $X:$X, 0))) -> Expenses | Z21: =IF(is_empty, "", IF(is_header, "Tracked", INDEX($K:$K, MATCH(row_id, $X:$X, 0)))) -> Tracked | AA21: =IF(is_empty, "", IF(is_header, "Budget", INDEX($L:$L, MATCH(row_id, $X:$X, 0)))) -> Budget | AB21: =IF(is_empty, "", IF(is_header, "% Compl.", IFERROR(out_tracked / out_budget, "-"))) -> % Compl. | AC21: =IF(is_empty, "", IF(is_header, "Remaining", IF(out_budget - out_tracked > 0, out_budget - out_tracked, 0))) -> Remaining | AD21: =IF(is_empty, "", IF(is_header, "Excess", IF(out_budget - out_tracked < 0, out_tracked - out_budget, 0))) -> Excess | AI21: =Calculations!E40 | AJ21: =Calculations!F40
C22: {=IF(C21=-1,-1, IF(C21<income_max_row, C21+1, IF(C21=income_max_row, income_total_row, IF(C21=income_total_row, "/1", IF(C21="/1", expenses_header_row, IF(C21<expenses_max_row, C21+1, IF(C21=expenses_max_row, expenses_total_row, IF(C21=expenses_total_row, "/2", IF(C21="/2", savings_header_row, IF(C21<savings_max_row, C21+1, IF(C21=savings_max_row, savings_total_row, -1)))))))))))} -> 30 | D22: =IF(is_header,row_id, IF(NOT(is_empty),D21,-1)) -> 29 | E22: {=1*OR(row_id=income_header_row, row_id=expenses_header_row, row_id=savings_header_row)} -> 0 | F22: =1*NOT(OR(is_header, is_total, is_empty)) -> 1 | G22: {=1*OR(row_id=income_total_row, row_id=expenses_total_row, row_id=savings_total_row)} -> 0 | H22: =1*OR(row_id="/1", row_id="/2", row_id=-1) -> 0 | I22: {=IFERROR(INDEX('Budget Planning'!$C:$C, header_row_id),"")} -> Expenses | J22: {=IFERROR(INDEX('Budget Planning'!$C:$C, row_id), "")} -> Rent | K22: {=IF( OR(is_header, is_empty, selected_period=""), "", IF( is_total, IF( selected_period="Total Year", SUMPRODUCT( Tracking[Amount] * (Tracking[Type]=type) * (YEAR(Tracking[Effective Date])=selected_year) ), SUMPRODUCT( Tracking[Amount] * (Tracking[Type]=type) * (YEAR(Tracking[Effective Date])=selected_year) * (MONTH(Tracking[Effective Date])=selected_period) ) ), IF( selected_period="Total Year", SUMPRODUCT( Tracking[Amount] * (Tracking[Type]=type) * (Tracking[Category]=item) * (YEAR(Tracking[Effective Date])=selected_year) ), SUMPRODUCT( Tracking[Amount] * (Tracking[Type]=type) * (Tracking[Category]=item) * (YEAR(Tracking[Effective Date])=selected_year) * (MONTH(Tracking[Effective Date])=selected_period) ) ) ) )} -> 70000 | L22: {=IF( OR(is_header, is_empty), "", INDEX( 'Budget Planning'!$E:$FA, row_id, MATCH( IF( selected_period = "Total Year", selected_year, DATE(selected_year, selected_period, 1) ), 'Budget Planning'!$E$10:$FA$10, 0 ) ) )} -> 70000 | M22: {=IF( is_cat, IF( header_row_id = income_header_row, MATCH(income_min_row, $C:$C, 0), IF( header_row_id = expenses_header_row, MATCH(expenses_min_row, $C:$C, 0), IF( header_row_id = savings_header_row, MATCH(savings_min_row, $C:$C, 0), "" ) ) ), "" )} -> 22 | N22: {=IF( is_cat, IF( header_row_id = income_header_row, MATCH(income_max_row, $C:$C, 0), IF( header_row_id = expenses_header_row, MATCH(expenses_max_row, $C:$C, 0), IF( header_row_id = savings_header_row, MATCH(savings_max_row, $C:$C, 0), "" ) ) ), "" )} -> 36 | O22: =IF(is_cat, ADDRESS(sort_min_row, COLUMN(tracked)) &":" & ADDRESS(sort_max_row, COLUMN(tracked)), "") -> $K$22:$K$36 | P22: =IF(is_cat, RANK(tracked, INDIRECT(tracked_range), 0), "") -> 1 | Q22: =IF(is_cat, ADDRESS(sort_min_row, COLUMN(budget)) &":" & ADDRESS(sort_max_row, COLUMN(budget)), "") -> $L$22:$L$36 | R22: =IF(is_cat, RANK(budget, INDIRECT(budget_range), 0), "") -> 1 | S22: =IF(is_cat, _xlfn.NUMBERVALUE(tracked_rank & budget_rank), "") -> 11 | T22: =IF(is_cat, ADDRESS(sort_min_row, COLUMN(comb_rank)) &":" & ADDRESS(sort_max_row, COLUMN(comb_rank)), "") -> $S$22:$S$36 | U22: =IF(is_cat,RANK(comb_rank,INDIRECT(comb_rank_range),1),"") -> 1 | V22: =IF(is_cat, ADDRESS(sort_min_row, COLUMN(comb_rank_norm)) &":" & ADDRESS(ROW(), COLUMN(comb_rank_norm)), "") -> $U$22:$U$22 | W22: =IF(is_cat, comb_rank_norm + COUNTIF(INDIRECT(comb_rank_norm_run_range), comb_rank_norm)-1, "") -> 1 | X22: =IF(is_cat, header_row_id + comb_rank_unique, row_id) -> 30 | Y22: =IF(is_empty, "", INDEX($J:$J, MATCH(row_id, $X:$X, 0))) -> Rent | Z22: =IF(is_empty, "", IF(is_header, "Tracked", INDEX($K:$K, MATCH(row_id, $X:$X, 0)))) -> 70000 | AA22: =IF(is_empty, "", IF(is_header, "Budget", INDEX($L:$L, MATCH(row_id, $X:$X, 0)))) -> 70000 | AB22: =IF(is_empty, "", IF(is_header, "% Compl.", IFERROR(out_tracked / out_budget, "-"))) -> 1 | AC22: =IF(is_empty, "", IF(is_header, "Remaining", IF(out_budget - out_tracked > 0, out_budget - out_tracked, 0))) -> 0 | AD22: =IF(is_empty, "", IF(is_header, "Excess", IF(out_budget - out_tracked < 0, out_tracked - out_budget, 0))) -> 0 | AI22: =Calculations!E41 -> Total | AJ22: =Calculations!F41 -> 291488
C23: {=IF(C22=-1,-1, IF(C22<income_max_row, C22+1, IF(C22=income_max_row, income_total_row, IF(C22=income_total_row, "/1", IF(C22="/1", expenses_header_row, IF(C22<expenses_max_row, C22+1, IF(C22=expenses_max_row, expenses_total_row, IF(C22=expenses_total_row, "/2", IF(C22="/2", savings_header_row, IF(C22<savings_max_row, C22+1, IF(C22=savings_max_row, savings_total_row, -1)))))))))))} -> 31 | D23: =IF(is_header,row_id, IF(NOT(is_empty),D22,-1)) -> 29 | E23: {=1*OR(row_id=income_header_row, row_id=expenses_header_row, row_id=savings_header_row)} -> 0 | F23: =1*NOT(OR(is_header, is_total, is_empty)) -> 1 | G23: {=1*OR(row_id=income_total_row, row_id=expenses_total_row, row_id=savings_total_row)} -> 0 | H23: =1*OR(row_id="/1", row_id="/2", row_id=-1) -> 0 | I23: {=IFERROR(INDEX('Budget Planning'!$C:$C, header_row_id),"")} -> Expenses | J23: {=IFERROR(INDEX('Budget Planning'!$C:$C, row_id), "")} -> Groceries | K23: {=IF( OR(is_header, is_empty, selected_period=""), "", IF( is_total, IF( selected_period="Total Year", SUMPRODUCT( Tracking[Amount] * (Tracking[Type]=type) * (YEAR(Tracking[Effective Date])=selected_year) ), SUMPRODUCT( Tracking[Amount] * (Tracking[Type]=type) * (YEAR(Tracking[Effective Date])=selected_year) * (MONTH(Tracking[Effective Date])=selected_period) ) ), IF( selected_period="Total Year", SUMPRODUCT( Tracking[Amount] * (Tracking[Type]=type) * (Tracking[Category]=item) * (YEAR(Tracking[Effective Date])=selected_year) ), SUMPRODUCT( Tracking[Amount] * (Tracking[Type]=type) * (Tracking[Category]=item) * (YEAR(Tracking[Effective Date])=selected_year) * (MONTH(Tracking[Effective Date])=selected_period) ) ) ) )} -> 0 | L23: {=IF( OR(is_header, is_empty), "", INDEX( 'Budget Planning'!$E:$FA, row_id, MATCH( IF( selected_period = "Total Year", selected_year, DATE(selected_year, selected_period, 1) ), 'Budget Planning'!$E$10:$FA$10, 0 ) ) )} -> 0 | M23: {=IF( is_cat, IF( header_row_id = income_header_row, MATCH(income_min_row, $C:$C, 0), IF( header_row_id = expenses_header_row, MATCH(expenses_min_row, $C:$C, 0), IF( header_row_id = savings_header_row, MATCH(savings_min_row, $C:$C, 0), "" ) ) ), "" )} -> 22 | N23: {=IF( is_cat, IF( header_row_id = income_header_row, MATCH(income_max_row, $C:$C, 0), IF( header_row_id = expenses_header_row, MATCH(expenses_max_row, $C:$C, 0), IF( header_row_id = savings_header_row, MATCH(savings_max_row, $C:$C, 0), "" ) ) ), "" )} -> 36 | O23: =IF(is_cat, ADDRESS(sort_min_row, COLUMN(tracked)) &":" & ADDRESS(sort_max_row, COLUMN(tracked)), "") -> $K$22:$K$36 | P23: =IF(is_cat, RANK(tracked, INDIRECT(tracked_range), 0), "") -> 2 | Q23: =IF(is_cat, ADDRESS(sort_min_row, COLUMN(budget)) &":" & ADDRESS(sort_max_row, COLUMN(budget)), "") -> $L$22:$L$36 | R23: =IF(is_cat, RANK(budget, INDIRECT(budget_range), 0), "") -> 3 | S23: =IF(is_cat, _xlfn.NUMBERVALUE(tracked_rank & budget_rank), "") -> 23 | T23: =IF(is_cat, ADDRESS(sort_min_row, COLUMN(comb_rank)) &":" & ADDRESS(sort_max_row, COLUMN(comb_rank)), "") -> $S$22:$S$36 | U23: =IF(is_cat,RANK(comb_rank,INDIRECT(comb_rank_range),1),"") -> 3 | V23: =IF(is_cat, ADDRESS(sort_min_row, COLUMN(comb_rank_norm)) &":" & ADDRESS(ROW(), COLUMN(comb_rank_norm)), "") -> $U$22:$U$23 | W23: =IF(is_cat, comb_rank_norm + COUNTIF(INDIRECT(comb_rank_norm_run_range), comb_rank_norm)-1, "") -> 3 | X23: =IF(is_cat, header_row_id + comb_rank_unique, row_id) -> 32 | Y23: =IF(is_empty, "", INDEX($J:$J, MATCH(row_id, $X:$X, 0))) -> CC Bill | Z23: =IF(is_empty, "", IF(is_header, "Tracked", INDEX($K:$K, MATCH(row_id, $X:$X, 0)))) -> 0 | AA23: =IF(is_empty, "", IF(is_header, "Budget", INDEX($L:$L, MATCH(row_id, $X:$X, 0)))) -> 44417 | AB23: =IF(is_empty, "", IF(is_header, "% Compl.", IFERROR(out_tracked / out_budget, "-"))) -> 0 | AC23: =IF(is_empty, "", IF(is_header, "Remaining", IF(out_budget - out_tracked > 0, out_budget - out_tracked, 0))) -> 44417 | AD23: =IF(is_empty, "", IF(is_header, "Excess", IF(out_budget - out_tracked < 0, out_tracked - out_budget, 0))) -> 0
C24: {=IF(C23=-1,-1, IF(C23<income_max_row, C23+1, IF(C23=income_max_row, income_total_row, IF(C23=income_total_row, "/1", IF(C23="/1", expenses_header_row, IF(C23<expenses_max_row, C23+1, IF(C23=expenses_max_row, expenses_total_row, IF(C23=expenses_total_row, "/2", IF(C23="/2", savings_header_row, IF(C23<savings_max_row, C23+1, IF(C23=savings_max_row, savings_total_row, -1)))))))))))} -> 32 | D24: =IF(is_header,row_id, IF(NOT(is_empty),D23,-1)) -> 29 | E24: {=1*OR(row_id=income_header_row, row_id=expenses_header_row, row_id=savings_header_row)} -> 0 | F24: =1*NOT(OR(is_header, is_total, is_empty)) -> 1 | G24: {=1*OR(row_id=income_total_row, row_id=expenses_total_row, row_id=savings_total_row)} -> 0 | H24: =1*OR(row_id="/1", row_id="/2", row_id=-1) -> 0 | I24: {=IFERROR(INDEX('Budget Planning'!$C:$C, header_row_id),"")} -> Expenses | J24: {=IFERROR(INDEX('Budget Planning'!$C:$C, row_id), "")} -> Transport | K24: {=IF( OR(is_header, is_empty, selected_period=""), "", IF( is_total, IF( selected_period="Total Year", SUMPRODUCT( Tracking[Amount] * (Tracking[Type]=type) * (YEAR(Tracking[Effective Date])=selected_year) ), SUMPRODUCT( Tracking[Amount] * (Tracking[Type]=type) * (YEAR(Tracking[Effective Date])=selected_year) * (MONTH(Tracking[Effective Date])=selected_period) ) ), IF( selected_period="Total Year", SUMPRODUCT( Tracking[Amount] * (Tracking[Type]=type) * (Tracking[Category]=item) * (YEAR(Tracking[Effective Date])=selected_year) ), SUMPRODUCT( Tracking[Amount] * (Tracking[Type]=type) * (Tracking[Category]=item) * (YEAR(Tracking[Effective Date])=selected_year) * (MONTH(Tracking[Effective Date])=selected_period) ) ) ) )} -> 0 | L24: {=IF( OR(is_header, is_empty), "", INDEX( 'Budget Planning'!$E:$FA, row_id, MATCH( IF( selected_period = "Total Year", selected_year, DATE(selected_year, selected_period, 1) ), 'Budget Planning'!$E$10:$FA$10, 0 ) ) )} -> 0 | M24: {=IF( is_cat, IF( header_row_id = income_header_row, MATCH(income_min_row, $C:$C, 0), IF( header_row_id = expenses_header_row, MATCH(expenses_min_row, $C:$C, 0), IF( header_row_id = savings_header_row, MATCH(savings_min_row, $C:$C, 0), "" ) ) ), "" )} -> 22 | N24: {=IF( is_cat, IF( header_row_id = income_header_row, MATCH(income_max_row, $C:$C, 0), IF( header_row_id = expenses_header_row, MATCH(expenses_max_row, $C:$C, 0), IF( header_row_id = savings_header_row, MATCH(savings_max_row, $C:$C, 0), "" ) ) ), "" )} -> 36 | O24: =IF(is_cat, ADDRESS(sort_min_row, COLUMN(tracked)) &":" & ADDRESS(sort_max_row, COLUMN(tracked)), "") -> $K$22:$K$36 | P24: =IF(is_cat, RANK(tracked, INDIRECT(tracked_range), 0), "") -> 2 | Q24: =IF(is_cat, ADDRESS(sort_min_row, COLUMN(budget)) &":" & ADDRESS(sort_max_row, COLUMN(budget)), "") -> $L$22:$L$36 | R24: =IF(is_cat, RANK(budget, INDIRECT(budget_range), 0), "") -> 3 | S24: =IF(is_cat, _xlfn.NUMBERVALUE(tracked_rank & budget_rank), "") -> 23 | T24: =IF(is_cat, ADDRESS(sort_min_row, COLUMN(comb_rank)) &":" & ADDRESS(sort_max_row, COLUMN(comb_rank)), "") -> $S$22:$S$36 | U24: =IF(is_cat,RANK(comb_rank,INDIRECT(comb_rank_range),1),"") -> 3 | V24: =IF(is_cat, ADDRESS(sort_min_row, COLUMN(comb_rank_norm)) &":" & ADDRESS(ROW(), COLUMN(comb_rank_norm)), "") -> $U$22:$U$24 | W24: =IF(is_cat, comb_rank_norm + COUNTIF(INDIRECT(comb_rank_norm_run_range), comb_rank_norm)-1, "") -> 4 | X24: =IF(is_cat, header_row_id + comb_rank_unique, row_id) -> 33 | Y24: =IF(is_empty, "", INDEX($J:$J, MATCH(row_id, $X:$X, 0))) -> Groceries | Z24: =IF(is_empty, "", IF(is_header, "Tracked", INDEX($K:$K, MATCH(row_id, $X:$X, 0)))) -> 0 | AA24: =IF(is_empty, "", IF(is_header, "Budget", INDEX($L:$L, MATCH(row_id, $X:$X, 0)))) -> 0 | AB24: =IF(is_empty, "", IF(is_header, "% Compl.", IFERROR(out_tracked / out_budget, "-"))) -> - | AC24: =IF(is_empty, "", IF(is_header, "Remaining", IF(out_budget - out_tracked > 0, out_budget - out_tracked, 0))) -> 0 | AD24: =IF(is_empty, "", IF(is_header, "Excess", IF(out_budget - out_tracked < 0, out_tracked - out_budget, 0))) -> 0
C25: {=IF(C24=-1,-1, IF(C24<income_max_row, C24+1, IF(C24=income_max_row, income_total_row, IF(C24=income_total_row, "/1", IF(C24="/1", expenses_header_row, IF(C24<expenses_max_row, C24+1, IF(C24=expenses_max_row, expenses_total_row, IF(C24=expenses_total_row, "/2", IF(C24="/2", savings_header_row, IF(C24<savings_max_row, C24+1, IF(C24=savings_max_row, savings_total_row, -1)))))))))))} -> 33 | D25: =IF(is_header,row_id, IF(NOT(is_empty),D24,-1)) -> 29 | E25: {=1*OR(row_id=income_header_row, row_id=expenses_header_row, row_id=savings_header_row)} -> 0 | F25: =1*NOT(OR(is_header, is_total, is_empty)) -> 1 | G25: {=1*OR(row_id=income_total_row, row_id=expenses_total_row, row_id=savings_total_row)} -> 0 | H25: =1*OR(row_id="/1", row_id="/2", row_id=-1) -> 0 | I25: {=IFERROR(INDEX('Budget Planning'!$C:$C, header_row_id),"")} -> Expenses | J25: {=IFERROR(INDEX('Budget Planning'!$C:$C, row_id), "")} -> Utilities | K25: {=IF( OR(is_header, is_empty, selected_period=""), "", IF( is_total, IF( selected_period="Total Year", SUMPRODUCT( Tracking[Amount] * (Tracking[Type]=type) * (YEAR(Tracking[Effective Date])=selected_year) ), SUMPRODUCT( Tracking[Amount] * (Tracking[Type]=type) * (YEAR(Tracking[Effective Date])=selected_year) * (MONTH(Tracking[Effective Date])=selected_period) ) ), IF( selected_period="Total Year", SUMPRODUCT( Tracking[Amount] * (Tracking[Type]=type) * (Tracking[Category]=item) * (YEAR(Tracking[Effective Date])=selected_year) ), SUMPRODUCT( Tracking[Amount] * (Tracking[Type]=type) * (Tracking[Category]=item) * (YEAR(Tracking[Effective Date])=selected_year) * (MONTH(Tracking[Effective Date])=selected_period) ) ) ) )} -> 0 | L25: {=IF( OR(is_header, is_empty), "", INDEX( 'Budget Planning'!$E:$FA, row_id, MATCH( IF( selected_period = "Total Year", selected_year, DATE(selected_year, selected_period, 1) ), 'Budget Planning'!$E$10:$FA$10, 0 ) ) )} -> 0 | M25: {=IF( is_cat, IF( header_row_id = income_header_row, MATCH(income_min_row, $C:$C, 0), IF( header_row_id = expenses_header_row, MATCH(expenses_min_row, $C:$C, 0), IF( header_row_id = savings_header_row, MATCH(savings_min_row, $C:$C, 0), "" ) ) ), "" )} -> 22 | N25: {=IF( is_cat, IF( header_row_id = income_header_row, MATCH(income_max_row, $C:$C, 0), IF( header_row_id = expenses_header_row, MATCH(expenses_max_row, $C:$C, 0), IF( header_row_id = savings_header_row, MATCH(savings_max_row, $C:$C, 0), "" ) ) ), "" )} -> 36 | O25: =IF(is_cat, ADDRESS(sort_min_row, COLUMN(tracked)) &":" & ADDRESS(sort_max_row, COLUMN(tracked)), "") -> $K$22:$K$36 | P25: =IF(is_cat, RANK(tracked, INDIRECT(tracked_range), 0), "") -> 2 | Q25: =IF(is_cat, ADDRESS(sort_min_row, COLUMN(budget)) &":" & ADDRESS(sort_max_row, COLUMN(budget)), "") -> $L$22:$L$36 | R25: =IF(is_cat, RANK(budget, INDIRECT(budget_range), 0), "") -> 3 | S25: =IF(is_cat, _xlfn.NUMBERVALUE(tracked_rank & budget_rank), "") -> 23 | T25: =IF(is_cat, ADDRESS(sort_min_row, COLUMN(comb_rank)) &":" & ADDRESS(sort_max_row, COLUMN(comb_rank)), "") -> $S$22:$S$36 | U25: =IF(is_cat,RANK(comb_rank,INDIRECT(comb_rank_range),1),"") -> 3 | V25: =IF(is_cat, ADDRESS(sort_min_row, COLUMN(comb_rank_norm)) &":" & ADDRESS(ROW(), COLUMN(comb_rank_norm)), "") -> $U$22:$U$25 | W25: =IF(is_cat, comb_rank_norm + COUNTIF(INDIRECT(comb_rank_norm_run_range), comb_rank_norm)-1, "") -> 5 | X25: =IF(is_cat, header_row_id + comb_rank_unique, row_id) -> 34 | Y25: =IF(is_empty, "", INDEX($J:$J, MATCH(row_id, $X:$X, 0))) -> Transport | Z25: =IF(is_empty, "", IF(is_header, "Tracked", INDEX($K:$K, MATCH(row_id, $X:$X, 0)))) -> 0 | AA25: =IF(is_empty, "", IF(is_header, "Budget", INDEX($L:$L, MATCH(row_id, $X:$X, 0)))) -> 0 | AB25: =IF(is_empty, "", IF(is_header, "% Compl.", IFERROR(out_tracked / out_budget, "-"))) -> - | AC25: =IF(is_empty, "", IF(is_header, "Remaining", IF(out_budget - out_tracked > 0, out_budget - out_tracked, 0))) -> 0 | AD25: =IF(is_empty, "", IF(is_header, "Excess", IF(out_budget - out_tracked < 0, out_tracked - out_budget, 0))) -> 0
C26: {=IF(C25=-1,-1, IF(C25<income_max_row, C25+1, IF(C25=income_max_row, income_total_row, IF(C25=income_total_row, "/1", IF(C25="/1", expenses_header_row, IF(C25<expenses_max_row, C25+1, IF(C25=expenses_max_row, expenses_total_row, IF(C25=expenses_total_row, "/2", IF(C25="/2", savings_header_row, IF(C25<savings_max_row, C25+1, IF(C25=savings_max_row, savings_total_row, -1)))))))))))} -> 34 | D26: =IF(is_header,row_id, IF(NOT(is_empty),D25,-1)) -> 29 | E26: {=1*OR(row_id=income_header_row, row_id=expenses_header_row, row_id=savings_header_row)} -> 0 | F26: =1*NOT(OR(is_header, is_total, is_empty)) -> 1 | G26: {=1*OR(row_id=income_total_row, row_id=expenses_total_row, row_id=savings_total_row)} -> 0 | H26: =1*OR(row_id="/1", row_id="/2", row_id=-1) -> 0 | I26: {=IFERROR(INDEX('Budget Planning'!$C:$C, header_row_id),"")} -> Expenses | J26: {=IFERROR(INDEX('Budget Planning'!$C:$C, row_id), "")} -> Insurance | K26: {=IF( OR(is_header, is_empty, selected_period=""), "", IF( is_total, IF( selected_period="Total Year", SUMPRODUCT( Tracking[Amount] * (Tracking[Type]=type) * (YEAR(Tracking[Effective Date])=selected_year) ), SUMPRODUCT( Tracking[Amount] * (Tracking[Type]=type) * (YEAR(Tracking[Effective Date])=selected_year) * (MONTH(Tracking[Effective Date])=selected_period) ) ), IF( selected_period="Total Year", SUMPRODUCT( Tracking[Amount] * (Tracking[Type]=type) * (Tracking[Category]=item) * (YEAR(Tracking[Effective Date])=selected_year) ), SUMPRODUCT( Tracking[Amount] * (Tracking[Type]=type) * (Tracking[Category]=item) * (YEAR(Tracking[Effective Date])=selected_year) * (MONTH(Tracking[Effective Date])=selected_period) ) ) ) )} -> 0 | L26: {=IF( OR(is_header, is_empty), "", INDEX( 'Budget Planning'!$E:$FA, row_id, MATCH( IF( selected_period = "Total Year", selected_year, DATE(selected_year, selected_period, 1) ), 'Budget Planning'!$E$10:$FA$10, 0 ) ) )} -> 0 | M26: {=IF( is_cat, IF( header_row_id = income_header_row, MATCH(income_min_row, $C:$C, 0), IF( header_row_id = expenses_header_row, MATCH(expenses_min_row, $C:$C, 0), IF( header_row_id = savings_header_row, MATCH(savings_min_row, $C:$C, 0), "" ) ) ), "" )} -> 22 | N26: {=IF( is_cat, IF( header_row_id = income_header_row, MATCH(income_max_row, $C:$C, 0), IF( header_row_id = expenses_header_row, MATCH(expenses_max_row, $C:$C, 0), IF( header_row_id = savings_header_row, MATCH(savings_max_row, $C:$C, 0), "" ) ) ), "" )} -> 36 | O26: =IF(is_cat, ADDRESS(sort_min_row, COLUMN(tracked)) &":" & ADDRESS(sort_max_row, COLUMN(tracked)), "") -> $K$22:$K$36 | P26: =IF(is_cat, RANK(tracked, INDIRECT(tracked_range), 0), "") -> 2 | Q26: =IF(is_cat, ADDRESS(sort_min_row, COLUMN(budget)) &":" & ADDRESS(sort_max_row, COLUMN(budget)), "") -> $L$22:$L$36 | R26: =IF(is_cat, RANK(budget, INDIRECT(budget_range), 0), "") -> 3 | S26: =IF(is_cat, _xlfn.NUMBERVALUE(tracked_rank & budget_rank), "") -> 23 | T26: =IF(is_cat, ADDRESS(sort_min_row, COLUMN(comb_rank)) &":" & ADDRESS(sort_max_row, COLUMN(comb_rank)), "") -> $S$22:$S$36 | U26: =IF(is_cat,RANK(comb_rank,INDIRECT(comb_rank_range),1),"") -> 3 | V26: =IF(is_cat, ADDRESS(sort_min_row, COLUMN(comb_rank_norm)) &":" & ADDRESS(ROW(), COLUMN(comb_rank_norm)), "") -> $U$22:$U$26 | W26: =IF(is_cat, comb_rank_norm + COUNTIF(INDIRECT(comb_rank_norm_run_range), comb_rank_norm)-1, "") -> 6 | X26: =IF(is_cat, header_row_id + comb_rank_unique, row_id) -> 35 | Y26: =IF(is_empty, "", INDEX($J:$J, MATCH(row_id, $X:$X, 0))) -> Utilities | Z26: =IF(is_empty, "", IF(is_header, "Tracked", INDEX($K:$K, MATCH(row_id, $X:$X, 0)))) -> 0 | AA26: =IF(is_empty, "", IF(is_header, "Budget", INDEX($L:$L, MATCH(row_id, $X:$X, 0)))) -> 0 | AB26: =IF(is_empty, "", IF(is_header, "% Compl.", IFERROR(out_tracked / out_budget, "-"))) -> - | AC26: =IF(is_empty, "", IF(is_header, "Remaining", IF(out_budget - out_tracked > 0, out_budget - out_tracked, 0))) -> 0 | AD26: =IF(is_empty, "", IF(is_header, "Excess", IF(out_budget - out_tracked < 0, out_tracked - out_budget, 0))) -> 0
C27: {=IF(C26=-1,-1, IF(C26<income_max_row, C26+1, IF(C26=income_max_row, income_total_row, IF(C26=income_total_row, "/1", IF(C26="/1", expenses_header_row, IF(C26<expenses_max_row, C26+1, IF(C26=expenses_max_row, expenses_total_row, IF(C26=expenses_total_row, "/2", IF(C26="/2", savings_header_row, IF(C26<savings_max_row, C26+1, IF(C26=savings_max_row, savings_total_row, -1)))))))))))} -> 35 | D27: =IF(is_header,row_id, IF(NOT(is_empty),D26,-1)) -> 29 | E27: {=1*OR(row_id=income_header_row, row_id=expenses_header_row, row_id=savings_header_row)} -> 0 | F27: =1*NOT(OR(is_header, is_total, is_empty)) -> 1 | G27: {=1*OR(row_id=income_total_row, row_id=expenses_total_row, row_id=savings_total_row)} -> 0 | H27: =1*OR(row_id="/1", row_id="/2", row_id=-1) -> 0 | I27: {=IFERROR(INDEX('Budget Planning'!$C:$C, header_row_id),"")} -> Expenses | J27: {=IFERROR(INDEX('Budget Planning'!$C:$C, row_id), "")} -> Clothing | K27: {=IF( OR(is_header, is_empty, selected_period=""), "", IF( is_total, IF( selected_period="Total Year", SUMPRODUCT( Tracking[Amount] * (Tracking[Type]=type) * (YEAR(Tracking[Effective Date])=selected_year) ), SUMPRODUCT( Tracking[Amount] * (Tracking[Type]=type) * (YEAR(Tracking[Effective Date])=selected_year) * (MONTH(Tracking[Effective Date])=selected_period) ) ), IF( selected_period="Total Year", SUMPRODUCT( Tracking[Amount] * (Tracking[Type]=type) * (Tracking[Category]=item) * (YEAR(Tracking[Effective Date])=selected_year) ), SUMPRODUCT( Tracking[Amount] * (Tracking[Type]=type) * (Tracking[Category]=item) * (YEAR(Tracking[Effective Date])=selected_year) * (MONTH(Tracking[Effective Date])=selected_period) ) ) ) )} -> 0 | L27: {=IF( OR(is_header, is_empty), "", INDEX( 'Budget Planning'!$E:$FA, row_id, MATCH( IF( selected_period = "Total Year", selected_year, DATE(selected_year, selected_period, 1) ), 'Budget Planning'!$E$10:$FA$10, 0 ) ) )} -> 0 | M27: {=IF( is_cat, IF( header_row_id = income_header_row, MATCH(income_min_row, $C:$C, 0), IF( header_row_id = expenses_header_row, MATCH(expenses_min_row, $C:$C, 0), IF( header_row_id = savings_header_row, MATCH(savings_min_row, $C:$C, 0), "" ) ) ), "" )} -> 22 | N27: {=IF( is_cat, IF( header_row_id = income_header_row, MATCH(income_max_row, $C:$C, 0), IF( header_row_id = expenses_header_row, MATCH(expenses_max_row, $C:$C, 0), IF( header_row_id = savings_header_row, MATCH(savings_max_row, $C:$C, 0), "" ) ) ), "" )} -> 36 | O27: =IF(is_cat, ADDRESS(sort_min_row, COLUMN(tracked)) &":" & ADDRESS(sort_max_row, COLUMN(tracked)), "") -> $K$22:$K$36 | P27: =IF(is_cat, RANK(tracked, INDIRECT(tracked_range), 0), "") -> 2 | Q27: =IF(is_cat, ADDRESS(sort_min_row, COLUMN(budget)) &":" & ADDRESS(sort_max_row, COLUMN(budget)), "") -> $L$22:$L$36 | R27: =IF(is_cat, RANK(budget, INDIRECT(budget_range), 0), "") -> 3 | S27: =IF(is_cat, _xlfn.NUMBERVALUE(tracked_rank & budget_rank), "") -> 23 | T27: =IF(is_cat, ADDRESS(sort_min_row, COLUMN(comb_rank)) &":" & ADDRESS(sort_max_row, COLUMN(comb_rank)), "") -> $S$22:$S$36 | U27: =IF(is_cat,RANK(comb_rank,INDIRECT(comb_rank_range),1),"") -> 3 | V27: =IF(is_cat, ADDRESS(sort_min_row, COLUMN(comb_rank_norm)) &":" & ADDRESS(ROW(), COLUMN(comb_rank_norm)), "") -> $U$22:$U$27 | W27: =IF(is_cat, comb_rank_norm + COUNTIF(INDIRECT(comb_rank_norm_run_range), comb_rank_norm)-1, "") -> 7 | X27: =IF(is_cat, header_row_id + comb_rank_unique, row_id) -> 36 | Y27: =IF(is_empty, "", INDEX($J:$J, MATCH(row_id, $X:$X, 0))) -> Insurance | Z27: =IF(is_empty, "", IF(is_header, "Tracked", INDEX($K:$K, MATCH(row_id, $X:$X, 0)))) -> 0 | AA27: =IF(is_empty, "", IF(is_header, "Budget", INDEX($L:$L, MATCH(row_id, $X:$X, 0)))) -> 0 | AB27: =IF(is_empty, "", IF(is_header, "% Compl.", IFERROR(out_tracked / out_budget, "-"))) -> - | AC27: =IF(is_empty, "", IF(is_header, "Remaining", IF(out_budget - out_tracked > 0, out_budget - out_tracked, 0))) -> 0 | AD27: =IF(is_empty, "", IF(is_header, "Excess", IF(out_budget - out_tracked < 0, out_tracked - out_budget, 0))) -> 0
C28: {=IF(C27=-1,-1, IF(C27<income_max_row, C27+1, IF(C27=income_max_row, income_total_row, IF(C27=income_total_row, "/1", IF(C27="/1", expenses_header_row, IF(C27<expenses_max_row, C27+1, IF(C27=expenses_max_row, expenses_total_row, IF(C27=expenses_total_row, "/2", IF(C27="/2", savings_header_row, IF(C27<savings_max_row, C27+1, IF(C27=savings_max_row, savings_total_row, -1)))))))))))} -> 36 | D28: =IF(is_header,row_id, IF(NOT(is_empty),D27,-1)) -> 29 | E28: {=1*OR(row_id=income_header_row, row_id=expenses_header_row, row_id=savings_header_row)} -> 0 | F28: =1*NOT(OR(is_header, is_total, is_empty)) -> 1 | G28: {=1*OR(row_id=income_total_row, row_id=expenses_total_row, row_id=savings_total_row)} -> 0 | H28: =1*OR(row_id="/1", row_id="/2", row_id=-1) -> 0 | I28: {=IFERROR(INDEX('Budget Planning'!$C:$C, header_row_id),"")} -> Expenses | J28: {=IFERROR(INDEX('Budget Planning'!$C:$C, row_id), "")} -> Cosmetics | K28: {=IF( OR(is_header, is_empty, selected_period=""), "", IF( is_total, IF( selected_period="Total Year", SUMPRODUCT( Tracking[Amount] * (Tracking[Type]=type) * (YEAR(Tracking[Effective Date])=selected_year) ), SUMPRODUCT( Tracking[Amount] * (Tracking[Type]=type) * (YEAR(Tracking[Effective Date])=selected_year) * (MONTH(Tracking[Effective Date])=selected_period) ) ), IF( selected_period="Total Year", SUMPRODUCT( Tracking[Amount] * (Tracking[Type]=type) * (Tracking[Category]=item) * (YEAR(Tracking[Effective Date])=selected_year) ), SUMPRODUCT( Tracking[Amount] * (Tracking[Type]=type) * (Tracking[Category]=item) * (YEAR(Tracking[Effective Date])=selected_year) * (MONTH(Tracking[Effective Date])=selected_period) ) ) ) )} -> 0 | L28: {=IF( OR(is_header, is_empty), "", INDEX( 'Budget Planning'!$E:$FA, row_id, MATCH( IF( selected_period = "Total Year", selected_year, DATE(selected_year, selected_period, 1) ), 'Budget Planning'!$E$10:$FA$10, 0 ) ) )} -> 0 | M28: {=IF( is_cat, IF( header_row_id = income_header_row, MATCH(income_min_row, $C:$C, 0), IF( header_row_id = expenses_header_row, MATCH(expenses_min_row, $C:$C, 0), IF( header_row_id = savings_header_row, MATCH(savings_min_row, $C:$C, 0), "" ) ) ), "" )} -> 22 | N28: {=IF( is_cat, IF( header_row_id = income_header_row, MATCH(income_max_row, $C:$C, 0), IF( header_row_id = expenses_header_row, MATCH(expenses_max_row, $C:$C, 0), IF( header_row_id = savings_header_row, MATCH(savings_max_row, $C:$C, 0), "" ) ) ), "" )} -> 36 | O28: =IF(is_cat, ADDRESS(sort_min_row, COLUMN(tracked)) &":" & ADDRESS(sort_max_row, COLUMN(tracked)), "") -> $K$22:$K$36 | P28: =IF(is_cat, RANK(tracked, INDIRECT(tracked_range), 0), "") -> 2 | Q28: =IF(is_cat, ADDRESS(sort_min_row, COLUMN(budget)) &":" & ADDRESS(sort_max_row, COLUMN(budget)), "") -> $L$22:$L$36 | R28: =IF(is_cat, RANK(budget, INDIRECT(budget_range), 0), "") -> 3 | S28: =IF(is_cat, _xlfn.NUMBERVALUE(tracked_rank & budget_rank), "") -> 23 | T28: =IF(is_cat, ADDRESS(sort_min_row, COLUMN(comb_rank)) &":" & ADDRESS(sort_max_row, COLUMN(comb_rank)), "") -> $S$22:$S$36 | U28: =IF(is_cat,RANK(comb_rank,INDIRECT(comb_rank_range),1),"") -> 3 | V28: =IF(is_cat, ADDRESS(sort_min_row, COLUMN(comb_rank_norm)) &":" & ADDRESS(ROW(), COLUMN(comb_rank_norm)), "") -> $U$22:$U$28 | W28: =IF(is_cat, comb_rank_norm + COUNTIF(INDIRECT(comb_rank_norm_run_range), comb_rank_norm)-1, "") -> 8 | X28: =IF(is_cat, header_row_id + comb_rank_unique, row_id) -> 37 | Y28: =IF(is_empty, "", INDEX($J:$J, MATCH(row_id, $X:$X, 0))) -> Clothing | Z28: =IF(is_empty, "", IF(is_header, "Tracked", INDEX($K:$K, MATCH(row_id, $X:$X, 0)))) -> 0 | AA28: =IF(is_empty, "", IF(is_header, "Budget", INDEX($L:$L, MATCH(row_id, $X:$X, 0)))) -> 0 | AB28: =IF(is_empty, "", IF(is_header, "% Compl.", IFERROR(out_tracked / out_budget, "-"))) -> - | AC28: =IF(is_empty, "", IF(is_header, "Remaining", IF(out_budget - out_tracked > 0, out_budget - out_tracked, 0))) -> 0 | AD28: =IF(is_empty, "", IF(is_header, "Excess", IF(out_budget - out_tracked < 0, out_tracked - out_budget, 0))) -> 0
C29: {=IF(C28=-1,-1, IF(C28<income_max_row, C28+1, IF(C28=income_max_row, income_total_row, IF(C28=income_total_row, "/1", IF(C28="/1", expenses_header_row, IF(C28<expenses_max_row, C28+1, IF(C28=expenses_max_row, expenses_total_row, IF(C28=expenses_total_row, "/2", IF(C28="/2", savings_header_row, IF(C28<savings_max_row, C28+1, IF(C28=savings_max_row, savings_total_row, -1)))))))))))} -> 37 | D29: =IF(is_header,row_id, IF(NOT(is_empty),D28,-1)) -> 29 | E29: {=1*OR(row_id=income_header_row, row_id=expenses_header_row, row_id=savings_header_row)} -> 0 | F29: =1*NOT(OR(is_header, is_total, is_empty)) -> 1 | G29: {=1*OR(row_id=income_total_row, row_id=expenses_total_row, row_id=savings_total_row)} -> 0 | H29: =1*OR(row_id="/1", row_id="/2", row_id=-1) -> 0 | I29: {=IFERROR(INDEX('Budget Planning'!$C:$C, header_row_id),"")} -> Expenses | J29: {=IFERROR(INDEX('Budget Planning'!$C:$C, row_id), "")} -> Medicine | K29: {=IF( OR(is_header, is_empty, selected_period=""), "", IF( is_total, IF( selected_period="Total Year", SUMPRODUCT( Tracking[Amount] * (Tracking[Type]=type) * (YEAR(Tracking[Effective Date])=selected_year) ), SUMPRODUCT( Tracking[Amount] * (Tracking[Type]=type) * (YEAR(Tracking[Effective Date])=selected_year) * (MONTH(Tracking[Effective Date])=selected_period) ) ), IF( selected_period="Total Year", SUMPRODUCT( Tracking[Amount] * (Tracking[Type]=type) * (Tracking[Category]=item) * (YEAR(Tracking[Effective Date])=selected_year) ), SUMPRODUCT( Tracking[Amount] * (Tracking[Type]=type) * (Tracking[Category]=item) * (YEAR(Tracking[Effective Date])=selected_year) * (MONTH(Tracking[Effective Date])=selected_period) ) ) ) )} -> 0 | L29: {=IF( OR(is_header, is_empty), "", INDEX( 'Budget Planning'!$E:$FA, row_id, MATCH( IF( selected_period = "Total Year", selected_year, DATE(selected_year, selected_period, 1) ), 'Budget Planning'!$E$10:$FA$10, 0 ) ) )} -> 0 | M29: {=IF( is_cat, IF( header_row_id = income_header_row, MATCH(income_min_row, $C:$C, 0), IF( header_row_id = expenses_header_row, MATCH(expenses_min_row, $C:$C, 0), IF( header_row_id = savings_header_row, MATCH(savings_min_row, $C:$C, 0), "" ) ) ), "" )} -> 22 | N29: {=IF( is_cat, IF( header_row_id = income_header_row, MATCH(income_max_row, $C:$C, 0), IF( header_row_id = expenses_header_row, MATCH(expenses_max_row, $C:$C, 0), IF( header_row_id = savings_header_row, MATCH(savings_max_row, $C:$C, 0), "" ) ) ), "" )} -> 36 | O29: =IF(is_cat, ADDRESS(sort_min_row, COLUMN(tracked)) &":" & ADDRESS(sort_max_row, COLUMN(tracked)), "") -> $K$22:$K$36 | P29: =IF(is_cat, RANK(tracked, INDIRECT(tracked_range), 0), "") -> 2 | Q29: =IF(is_cat, ADDRESS(sort_min_row, COLUMN(budget)) &":" & ADDRESS(sort_max_row, COLUMN(budget)), "") -> $L$22:$L$36 | R29: =IF(is_cat, RANK(budget, INDIRECT(budget_range), 0), "") -> 3 | S29: =IF(is_cat, _xlfn.NUMBERVALUE(tracked_rank & budget_rank), "") -> 23 | T29: =IF(is_cat, ADDRESS(sort_min_row, COLUMN(comb_rank)) &":" & ADDRESS(sort_max_row, COLUMN(comb_rank)), "") -> $S$22:$S$36 | U29: =IF(is_cat,RANK(comb_rank,INDIRECT(comb_rank_range),1),"") -> 3 | V29: =IF(is_cat, ADDRESS(sort_min_row, COLUMN(comb_rank_norm)) &":" & ADDRESS(ROW(), COLUMN(comb_rank_norm)), "") -> $U$22:$U$29 | W29: =IF(is_cat, comb_rank_norm + COUNTIF(INDIRECT(comb_rank_norm_run_range), comb_rank_norm)-1, "") -> 9 | X29: =IF(is_cat, header_row_id + comb_rank_unique, row_id) -> 38 | Y29: =IF(is_empty, "", INDEX($J:$J, MATCH(row_id, $X:$X, 0))) -> Cosmetics | Z29: =IF(is_empty, "", IF(is_header, "Tracked", INDEX($K:$K, MATCH(row_id, $X:$X, 0)))) -> 0 | AA29: =IF(is_empty, "", IF(is_header, "Budget", INDEX($L:$L, MATCH(row_id, $X:$X, 0)))) -> 0 | AB29: =IF(is_empty, "", IF(is_header, "% Compl.", IFERROR(out_tracked / out_budget, "-"))) -> - | AC29: =IF(is_empty, "", IF(is_header, "Remaining", IF(out_budget - out_tracked > 0, out_budget - out_tracked, 0))) -> 0 | AD29: =IF(is_empty, "", IF(is_header, "Excess", IF(out_budget - out_tracked < 0, out_tracked - out_budget, 0))) -> 0 | AI29: =Calculations!I35 -> Rent | AJ29: =Calculations!J35 -> 70000 | AP29: =Calculations!M35 | AQ29: =Calculations!N35
C30: {=IF(C29=-1,-1, IF(C29<income_max_row, C29+1, IF(C29=income_max_row, income_total_row, IF(C29=income_total_row, "/1", IF(C29="/1", expenses_header_row, IF(C29<expenses_max_row, C29+1, IF(C29=expenses_max_row, expenses_total_row, IF(C29=expenses_total_row, "/2", IF(C29="/2", savings_header_row, IF(C29<savings_max_row, C29+1, IF(C29=savings_max_row, savings_total_row, -1)))))))))))} -> 38 | D30: =IF(is_header,row_id, IF(NOT(is_empty),D29,-1)) -> 29 | E30: {=1*OR(row_id=income_header_row, row_id=expenses_header_row, row_id=savings_header_row)} -> 0 | F30: =1*NOT(OR(is_header, is_total, is_empty)) -> 1 | G30: {=1*OR(row_id=income_total_row, row_id=expenses_total_row, row_id=savings_total_row)} -> 0 | H30: =1*OR(row_id="/1", row_id="/2", row_id=-1) -> 0 | I30: {=IFERROR(INDEX('Budget Planning'!$C:$C, header_row_id),"")} -> Expenses | J30: {=IFERROR(INDEX('Budget Planning'!$C:$C, row_id), "")} -> Media | K30: {=IF( OR(is_header, is_empty, selected_period=""), "", IF( is_total, IF( selected_period="Total Year", SUMPRODUCT( Tracking[Amount] * (Tracking[Type]=type) * (YEAR(Tracking[Effective Date])=selected_year) ), SUMPRODUCT( Tracking[Amount] * (Tracking[Type]=type) * (YEAR(Tracking[Effective Date])=selected_year) * (MONTH(Tracking[Effective Date])=selected_period) ) ), IF( selected_period="Total Year", SUMPRODUCT( Tracking[Amount] * (Tracking[Type]=type) * (Tracking[Category]=item) * (YEAR(Tracking[Effective Date])=selected_year) ), SUMPRODUCT( Tracking[Amount] * (Tracking[Type]=type) * (Tracking[Category]=item) * (YEAR(Tracking[Effective Date])=selected_year) * (MONTH(Tracking[Effective Date])=selected_period) ) ) ) )} -> 0 | L30: {=IF( OR(is_header, is_empty), "", INDEX( 'Budget Planning'!$E:$FA, row_id, MATCH( IF( selected_period = "Total Year", selected_year, DATE(selected_year, selected_period, 1) ), 'Budget Planning'!$E$10:$FA$10, 0 ) ) )} -> 0 | M30: {=IF( is_cat, IF( header_row_id = income_header_row, MATCH(income_min_row, $C:$C, 0), IF( header_row_id = expenses_header_row, MATCH(expenses_min_row, $C:$C, 0), IF( header_row_id = savings_header_row, MATCH(savings_min_row, $C:$C, 0), "" ) ) ), "" )} -> 22 | N30: {=IF( is_cat, IF( header_row_id = income_header_row, MATCH(income_max_row, $C:$C, 0), IF( header_row_id = expenses_header_row, MATCH(expenses_max_row, $C:$C, 0), IF( header_row_id = savings_header_row, MATCH(savings_max_row, $C:$C, 0), "" ) ) ), "" )} -> 36 | O30: =IF(is_cat, ADDRESS(sort_min_row, COLUMN(tracked)) &":" & ADDRESS(sort_max_row, COLUMN(tracked)), "") -> $K$22:$K$36 | P30: =IF(is_cat, RANK(tracked, INDIRECT(tracked_range), 0), "") -> 2 | Q30: =IF(is_cat, ADDRESS(sort_min_row, COLUMN(budget)) &":" & ADDRESS(sort_max_row, COLUMN(budget)), "") -> $L$22:$L$36 | R30: =IF(is_cat, RANK(budget, INDIRECT(budget_range), 0), "") -> 3 | S30: =IF(is_cat, _xlfn.NUMBERVALUE(tracked_rank & budget_rank), "") -> 23 | T30: =IF(is_cat, ADDRESS(sort_min_row, COLUMN(comb_rank)) &":" & ADDRESS(sort_max_row, COLUMN(comb_rank)), "") -> $S$22:$S$36 | U30: =IF(is_cat,RANK(comb_rank,INDIRECT(comb_rank_range),1),"") -> 3 | V30: =IF(is_cat, ADDRESS(sort_min_row, COLUMN(comb_rank_norm)) &":" & ADDRESS(ROW(), COLUMN(comb_rank_norm)), "") -> $U$22:$U$30 | W30: =IF(is_cat, comb_rank_norm + COUNTIF(INDIRECT(comb_rank_norm_run_range), comb_rank_norm)-1, "") -> 10 | X30: =IF(is_cat, header_row_id + comb_rank_unique, row_id) -> 39 | Y30: =IF(is_empty, "", INDEX($J:$J, MATCH(row_id, $X:$X, 0))) -> Medicine | Z30: =IF(is_empty, "", IF(is_header, "Tracked", INDEX($K:$K, MATCH(row_id, $X:$X, 0)))) -> 0 | AA30: =IF(is_empty, "", IF(is_header, "Budget", INDEX($L:$L, MATCH(row_id, $X:$X, 0)))) -> 0 | AB30: =IF(is_empty, "", IF(is_header, "% Compl.", IFERROR(out_tracked / out_budget, "-"))) -> - | AC30: =IF(is_empty, "", IF(is_header, "Remaining", IF(out_budget - out_tracked > 0, out_budget - out_tracked, 0))) -> 0 | AD30: =IF(is_empty, "", IF(is_header, "Excess", IF(out_budget - out_tracked < 0, out_tracked - out_budget, 0))) -> 0 | AI30: =Calculations!I36 | AJ30: =Calculations!J36 | AP30: =Calculations!M36 | AQ30: =Calculations!N36
C31: {=IF(C30=-1,-1, IF(C30<income_max_row, C30+1, IF(C30=income_max_row, income_total_row, IF(C30=income_total_row, "/1", IF(C30="/1", expenses_header_row, IF(C30<expenses_max_row, C30+1, IF(C30=expenses_max_row, expenses_total_row, IF(C30=expenses_total_row, "/2", IF(C30="/2", savings_header_row, IF(C30<savings_max_row, C30+1, IF(C30=savings_max_row, savings_total_row, -1)))))))))))} -> 39 | D31: =IF(is_header,row_id, IF(NOT(is_empty),D30,-1)) -> 29 | E31: {=1*OR(row_id=income_header_row, row_id=expenses_header_row, row_id=savings_header_row)} -> 0 | F31: =1*NOT(OR(is_header, is_total, is_empty)) -> 1 | G31: {=1*OR(row_id=income_total_row, row_id=expenses_total_row, row_id=savings_total_row)} -> 0 | H31: =1*OR(row_id="/1", row_id="/2", row_id=-1) -> 0 | I31: {=IFERROR(INDEX('Budget Planning'!$C:$C, header_row_id),"")} -> Expenses | J31: {=IFERROR(INDEX('Budget Planning'!$C:$C, row_id), "")} -> Fun & Vacation | K31: {=IF( OR(is_header, is_empty, selected_period=""), "", IF( is_total, IF( selected_period="Total Year", SUMPRODUCT( Tracking[Amount] * (Tracking[Type]=type) * (YEAR(Tracking[Effective Date])=selected_year) ), SUMPRODUCT( Tracking[Amount] * (Tracking[Type]=type) * (YEAR(Tracking[Effective Date])=selected_year) * (MONTH(Tracking[Effective Date])=selected_period) ) ), IF( selected_period="Total Year", SUMPRODUCT( Tracking[Amount] * (Tracking[Type]=type) * (Tracking[Category]=item) * (YEAR(Tracking[Effective Date])=selected_year) ), SUMPRODUCT( Tracking[Amount] * (Tracking[Type]=type) * (Tracking[Category]=item) * (YEAR(Tracking[Effective Date])=selected_year) * (MONTH(Tracking[Effective Date])=selected_period) ) ) ) )} -> 0 | L31: {=IF( OR(is_header, is_empty), "", INDEX( 'Budget Planning'!$E:$FA, row_id, MATCH( IF( selected_period = "Total Year", selected_year, DATE(selected_year, selected_period, 1) ), 'Budget Planning'!$E$10:$FA$10, 0 ) ) )} -> 0 | M31: {=IF( is_cat, IF( header_row_id = income_header_row, MATCH(income_min_row, $C:$C, 0), IF( header_row_id = expenses_header_row, MATCH(expenses_min_row, $C:$C, 0), IF( header_row_id = savings_header_row, MATCH(savings_min_row, $C:$C, 0), "" ) ) ), "" )} -> 22 | N31: {=IF( is_cat, IF( header_row_id = income_header_row, MATCH(income_max_row, $C:$C, 0), IF( header_row_id = expenses_header_row, MATCH(expenses_max_row, $C:$C, 0), IF( header_row_id = savings_header_row, MATCH(savings_max_row, $C:$C, 0), "" ) ) ), "" )} -> 36 | O31: =IF(is_cat, ADDRESS(sort_min_row, COLUMN(tracked)) &":" & ADDRESS(sort_max_row, COLUMN(tracked)), "") -> $K$22:$K$36 | P31: =IF(is_cat, RANK(tracked, INDIRECT(tracked_range), 0), "") -> 2 | Q31: =IF(is_cat, ADDRESS(sort_min_row, COLUMN(budget)) &":" & ADDRESS(sort_max_row, COLUMN(budget)), "") -> $L$22:$L$36 | R31: =IF(is_cat, RANK(budget, INDIRECT(budget_range), 0), "") -> 3 | S31: =IF(is_cat, _xlfn.NUMBERVALUE(tracked_rank & budget_rank), "") -> 23 | T31: =IF(is_cat, ADDRESS(sort_min_row, COLUMN(comb_rank)) &":" & ADDRESS(sort_max_row, COLUMN(comb_rank)), "") -> $S$22:$S$36 | U31: =IF(is_cat,RANK(comb_rank,INDIRECT(comb_rank_range),1),"") -> 3 | V31: =IF(is_cat, ADDRESS(sort_min_row, COLUMN(comb_rank_norm)) &":" & ADDRESS(ROW(), COLUMN(comb_rank_norm)), "") -> $U$22:$U$31 | W31: =IF(is_cat, comb_rank_norm + COUNTIF(INDIRECT(comb_rank_norm_run_range), comb_rank_norm)-1, "") -> 11 | X31: =IF(is_cat, header_row_id + comb_rank_unique, row_id) -> 40 | Y31: =IF(is_empty, "", INDEX($J:$J, MATCH(row_id, $X:$X, 0))) -> Media | Z31: =IF(is_empty, "", IF(is_header, "Tracked", INDEX($K:$K, MATCH(row_id, $X:$X, 0)))) -> 0 | AA31: =IF(is_empty, "", IF(is_header, "Budget", INDEX($L:$L, MATCH(row_id, $X:$X, 0)))) -> 0 | AB31: =IF(is_empty, "", IF(is_header, "% Compl.", IFERROR(out_tracked / out_budget, "-"))) -> - | AC31: =IF(is_empty, "", IF(is_header, "Remaining", IF(out_budget - out_tracked > 0, out_budget - out_tracked, 0))) -> 0 | AD31: =IF(is_empty, "", IF(is_header, "Excess", IF(out_budget - out_tracked < 0, out_tracked - out_budget, 0))) -> 0 | AI31: =Calculations!I37 | AJ31: =Calculations!J37 | AP31: =Calculations!M37 | AQ31: =Calculations!N37
C32: {=IF(C31=-1,-1, IF(C31<income_max_row, C31+1, IF(C31=income_max_row, income_total_row, IF(C31=income_total_row, "/1", IF(C31="/1", expenses_header_row, IF(C31<expenses_max_row, C31+1, IF(C31=expenses_max_row, expenses_total_row, IF(C31=expenses_total_row, "/2", IF(C31="/2", savings_header_row, IF(C31<savings_max_row, C31+1, IF(C31=savings_max_row, savings_total_row, -1)))))))))))} -> 40 | D32: =IF(is_header,row_id, IF(NOT(is_empty),D31,-1)) -> 29 | E32: {=1*OR(row_id=income_header_row, row_id=expenses_header_row, row_id=savings_header_row)} -> 0 | F32: =1*NOT(OR(is_header, is_total, is_empty)) -> 1 | G32: {=1*OR(row_id=income_total_row, row_id=expenses_total_row, row_id=savings_total_row)} -> 0 | H32: =1*OR(row_id="/1", row_id="/2", row_id=-1) -> 0 | I32: {=IFERROR(INDEX('Budget Planning'!$C:$C, header_row_id),"")} -> Expenses | J32: {=IFERROR(INDEX('Budget Planning'!$C:$C, row_id), "")} -> Gifting | K32: {=IF( OR(is_header, is_empty, selected_period=""), "", IF( is_total, IF( selected_period="Total Year", SUMPRODUCT( Tracking[Amount] * (Tracking[Type]=type) * (YEAR(Tracking[Effective Date])=selected_year) ), SUMPRODUCT( Tracking[Amount] * (Tracking[Type]=type) * (YEAR(Tracking[Effective Date])=selected_year) * (MONTH(Tracking[Effective Date])=selected_period) ) ), IF( selected_period="Total Year", SUMPRODUCT( Tracking[Amount] * (Tracking[Type]=type) * (Tracking[Category]=item) * (YEAR(Tracking[Effective Date])=selected_year) ), SUMPRODUCT( Tracking[Amount] * (Tracking[Type]=type) * (Tracking[Category]=item) * (YEAR(Tracking[Effective Date])=selected_year) * (MONTH(Tracking[Effective Date])=selected_period) ) ) ) )} -> 0 | L32: {=IF( OR(is_header, is_empty), "", INDEX( 'Budget Planning'!$E:$FA, row_id, MATCH( IF( selected_period = "Total Year", selected_year, DATE(selected_year, selected_period, 1) ), 'Budget Planning'!$E$10:$FA$10, 0 ) ) )} -> 0 | M32: {=IF( is_cat, IF( header_row_id = income_header_row, MATCH(income_min_row, $C:$C, 0), IF( header_row_id = expenses_header_row, MATCH(expenses_min_row, $C:$C, 0), IF( header_row_id = savings_header_row, MATCH(savings_min_row, $C:$C, 0), "" ) ) ), "" )} -> 22 | N32: {=IF( is_cat, IF( header_row_id = income_header_row, MATCH(income_max_row, $C:$C, 0), IF( header_row_id = expenses_header_row, MATCH(expenses_max_row, $C:$C, 0), IF( header_row_id = savings_header_row, MATCH(savings_max_row, $C:$C, 0), "" ) ) ), "" )} -> 36 | O32: =IF(is_cat, ADDRESS(sort_min_row, COLUMN(tracked)) &":" & ADDRESS(sort_max_row, COLUMN(tracked)), "") -> $K$22:$K$36 | P32: =IF(is_cat, RANK(tracked, INDIRECT(tracked_range), 0), "") -> 2 | Q32: =IF(is_cat, ADDRESS(sort_min_row, COLUMN(budget)) &":" & ADDRESS(sort_max_row, COLUMN(budget)), "") -> $L$22:$L$36 | R32: =IF(is_cat, RANK(budget, INDIRECT(budget_range), 0), "") -> 3 | S32: =IF(is_cat, _xlfn.NUMBERVALUE(tracked_rank & budget_rank), "") -> 23 | T32: =IF(is_cat, ADDRESS(sort_min_row, COLUMN(comb_rank)) &":" & ADDRESS(sort_max_row, COLUMN(comb_rank)), "") -> $S$22:$S$36 | U32: =IF(is_cat,RANK(comb_rank,INDIRECT(comb_rank_range),1),"") -> 3 | V32: =IF(is_cat, ADDRESS(sort_min_row, COLUMN(comb_rank_norm)) &":" & ADDRESS(ROW(), COLUMN(comb_rank_norm)), "") -> $U$22:$U$32 | W32: =IF(is_cat, comb_rank_norm + COUNTIF(INDIRECT(comb_rank_norm_run_range), comb_rank_norm)-1, "") -> 12 | X32: =IF(is_cat, header_row_id + comb_rank_unique, row_id) -> 41 | Y32: =IF(is_empty, "", INDEX($J:$J, MATCH(row_id, $X:$X, 0))) -> Fun & Vacation | Z32: =IF(is_empty, "", IF(is_header, "Tracked", INDEX($K:$K, MATCH(row_id, $X:$X, 0)))) -> 0 | AA32: =IF(is_empty, "", IF(is_header, "Budget", INDEX($L:$L, MATCH(row_id, $X:$X, 0)))) -> 0 | AB32: =IF(is_empty, "", IF(is_header, "% Compl.", IFERROR(out_tracked / out_budget, "-"))) -> - | AC32: =IF(is_empty, "", IF(is_header, "Remaining", IF(out_budget - out_tracked > 0, out_budget - out_tracked, 0))) -> 0 | AD32: =IF(is_empty, "", IF(is_header, "Excess", IF(out_budget - out_tracked < 0, out_tracked - out_budget, 0))) -> 0 | AI32: =Calculations!I38 | AJ32: =Calculations!J38 | AP32: =Calculations!M38 | AQ32: =Calculations!N38
C33: {=IF(C32=-1,-1, IF(C32<income_max_row, C32+1, IF(C32=income_max_row, income_total_row, IF(C32=income_total_row, "/1", IF(C32="/1", expenses_header_row, IF(C32<expenses_max_row, C32+1, IF(C32=expenses_max_row, expenses_total_row, IF(C32=expenses_total_row, "/2", IF(C32="/2", savings_header_row, IF(C32<savings_max_row, C32+1, IF(C32=savings_max_row, savings_total_row, -1)))))))))))} -> 41 | D33: =IF(is_header,row_id, IF(NOT(is_empty),D32,-1)) -> 29 | E33: {=1*OR(row_id=income_header_row, row_id=expenses_header_row, row_id=savings_header_row)} -> 0 | F33: =1*NOT(OR(is_header, is_total, is_empty)) -> 1 | G33: {=1*OR(row_id=income_total_row, row_id=expenses_total_row, row_id=savings_total_row)} -> 0 | H33: =1*OR(row_id="/1", row_id="/2", row_id=-1) -> 0 | I33: {=IFERROR(INDEX('Budget Planning'!$C:$C, header_row_id),"")} -> Expenses | J33: {=IFERROR(INDEX('Budget Planning'!$C:$C, row_id), "")} -> Miscellaneous | K33: {=IF( OR(is_header, is_empty, selected_period=""), "", IF( is_total, IF( selected_period="Total Year", SUMPRODUCT( Tracking[Amount] * (Tracking[Type]=type) * (YEAR(Tracking[Effective Date])=selected_year) ), SUMPRODUCT( Tracking[Amount] * (Tracking[Type]=type) * (YEAR(Tracking[Effective Date])=selected_year) * (MONTH(Tracking[Effective Date])=selected_period) ) ), IF( selected_period="Total Year", SUMPRODUCT( Tracking[Amount] * (Tracking[Type]=type) * (Tracking[Category]=item) * (YEAR(Tracking[Effective Date])=selected_year) ), SUMPRODUCT( Tracking[Amount] * (Tracking[Type]=type) * (Tracking[Category]=item) * (YEAR(Tracking[Effective Date])=selected_year) * (MONTH(Tracking[Effective Date])=selected_period) ) ) ) )} -> 0 | L33: {=IF( OR(is_header, is_empty), "", INDEX( 'Budget Planning'!$E:$FA, row_id, MATCH( IF( selected_period = "Total Year", selected_year, DATE(selected_year, selected_period, 1) ), 'Budget Planning'!$E$10:$FA$10, 0 ) ) )} -> 0 | M33: {=IF( is_cat, IF( header_row_id = income_header_row, MATCH(income_min_row, $C:$C, 0), IF( header_row_id = expenses_header_row, MATCH(expenses_min_row, $C:$C, 0), IF( header_row_id = savings_header_row, MATCH(savings_min_row, $C:$C, 0), "" ) ) ), "" )} -> 22 | N33: {=IF( is_cat, IF( header_row_id = income_header_row, MATCH(income_max_row, $C:$C, 0), IF( header_row_id = expenses_header_row, MATCH(expenses_max_row, $C:$C, 0), IF( header_row_id = savings_header_row, MATCH(savings_max_row, $C:$C, 0), "" ) ) ), "" )} -> 36 | O33: =IF(is_cat, ADDRESS(sort_min_row, COLUMN(tracked)) &":" & ADDRESS(sort_max_row, COLUMN(tracked)), "") -> $K$22:$K$36 | P33: =IF(is_cat, RANK(tracked, INDIRECT(tracked_range), 0), "") -> 2 | Q33: =IF(is_cat, ADDRESS(sort_min_row, COLUMN(budget)) &":" & ADDRESS(sort_max_row, COLUMN(budget)), "") -> $L$22:$L$36 | R33: =IF(is_cat, RANK(budget, INDIRECT(budget_range), 0), "") -> 3 | S33: =IF(is_cat, _xlfn.NUMBERVALUE(tracked_rank & budget_rank), "") -> 23 | T33: =IF(is_cat, ADDRESS(sort_min_row, COLUMN(comb_rank)) &":" & ADDRESS(sort_max_row, COLUMN(comb_rank)), "") -> $S$22:$S$36 | U33: =IF(is_cat,RANK(comb_rank,INDIRECT(comb_rank_range),1),"") -> 3 | V33: =IF(is_cat, ADDRESS(sort_min_row, COLUMN(comb_rank_norm)) &":" & ADDRESS(ROW(), COLUMN(comb_rank_norm)), "") -> $U$22:$U$33 | W33: =IF(is_cat, comb_rank_norm + COUNTIF(INDIRECT(comb_rank_norm_run_range), comb_rank_norm)-1, "") -> 13 | X33: =IF(is_cat, header_row_id + comb_rank_unique, row_id) -> 42 | Y33: =IF(is_empty, "", INDEX($J:$J, MATCH(row_id, $X:$X, 0))) -> Gifting | Z33: =IF(is_empty, "", IF(is_header, "Tracked", INDEX($K:$K, MATCH(row_id, $X:$X, 0)))) -> 0 | AA33: =IF(is_empty, "", IF(is_header, "Budget", INDEX($L:$L, MATCH(row_id, $X:$X, 0)))) -> 0 | AB33: =IF(is_empty, "", IF(is_header, "% Compl.", IFERROR(out_tracked / out_budget, "-"))) -> - | AC33: =IF(is_empty, "", IF(is_header, "Remaining", IF(out_budget - out_tracked > 0, out_budget - out_tracked, 0))) -> 0 | AD33: =IF(is_empty, "", IF(is_header, "Excess", IF(out_budget - out_tracked < 0, out_tracked - out_budget, 0))) -> 0 | AI33: =Calculations!I39 | AJ33: =Calculations!J39 | AP33: =Calculations!M39 | AQ33: =Calculations!N39
C34: {=IF(C33=-1,-1, IF(C33<income_max_row, C33+1, IF(C33=income_max_row, income_total_row, IF(C33=income_total_row, "/1", IF(C33="/1", expenses_header_row, IF(C33<expenses_max_row, C33+1, IF(C33=expenses_max_row, expenses_total_row, IF(C33=expenses_total_row, "/2", IF(C33="/2", savings_header_row, IF(C33<savings_max_row, C33+1, IF(C33=savings_max_row, savings_total_row, -1)))))))))))} -> 42 | D34: =IF(is_header,row_id, IF(NOT(is_empty),D33,-1)) -> 29 | E34: {=1*OR(row_id=income_header_row, row_id=expenses_header_row, row_id=savings_header_row)} -> 0 | F34: =1*NOT(OR(is_header, is_total, is_empty)) -> 1 | G34: {=1*OR(row_id=income_total_row, row_id=expenses_total_row, row_id=savings_total_row)} -> 0 | H34: =1*OR(row_id="/1", row_id="/2", row_id=-1) -> 0 | I34: {=IFERROR(INDEX('Budget Planning'!$C:$C, header_row_id),"")} -> Expenses | J34: {=IFERROR(INDEX('Budget Planning'!$C:$C, row_id), "")} -> Taxes | K34: {=IF( OR(is_header, is_empty, selected_period=""), "", IF( is_total, IF( selected_period="Total Year", SUMPRODUCT( Tracking[Amount] * (Tracking[Type]=type) * (YEAR(Tracking[Effective Date])=selected_year) ), SUMPRODUCT( Tracking[Amount] * (Tracking[Type]=type) * (YEAR(Tracking[Effective Date])=selected_year) * (MONTH(Tracking[Effective Date])=selected_period) ) ), IF( selected_period="Total Year", SUMPRODUCT( Tracking[Amount] * (Tracking[Type]=type) * (Tracking[Category]=item) * (YEAR(Tracking[Effective Date])=selected_year) ), SUMPRODUCT( Tracking[Amount] * (Tracking[Type]=type) * (Tracking[Category]=item) * (YEAR(Tracking[Effective Date])=selected_year) * (MONTH(Tracking[Effective Date])=selected_period) ) ) ) )} -> 0 | L34: {=IF( OR(is_header, is_empty), "", INDEX( 'Budget Planning'!$E:$FA, row_id, MATCH( IF( selected_period = "Total Year", selected_year, DATE(selected_year, selected_period, 1) ), 'Budget Planning'!$E$10:$FA$10, 0 ) ) )} -> 0 | M34: {=IF( is_cat, IF( header_row_id = income_header_row, MATCH(income_min_row, $C:$C, 0), IF( header_row_id = expenses_header_row, MATCH(expenses_min_row, $C:$C, 0), IF( header_row_id = savings_header_row, MATCH(savings_min_row, $C:$C, 0), "" ) ) ), "" )} -> 22 | N34: {=IF( is_cat, IF( header_row_id = income_header_row, MATCH(income_max_row, $C:$C, 0), IF( header_row_id = expenses_header_row, MATCH(expenses_max_row, $C:$C, 0), IF( header_row_id = savings_header_row, MATCH(savings_max_row, $C:$C, 0), "" ) ) ), "" )} -> 36 | O34: =IF(is_cat, ADDRESS(sort_min_row, COLUMN(tracked)) &":" & ADDRESS(sort_max_row, COLUMN(tracked)), "") -> $K$22:$K$36 | P34: =IF(is_cat, RANK(tracked, INDIRECT(tracked_range), 0), "") -> 2 | Q34: =IF(is_cat, ADDRESS(sort_min_row, COLUMN(budget)) &":" & ADDRESS(sort_max_row, COLUMN(budget)), "") -> $L$22:$L$36 | R34: =IF(is_cat, RANK(budget, INDIRECT(budget_range), 0), "") -> 3 | S34: =IF(is_cat, _xlfn.NUMBERVALUE(tracked_rank & budget_rank), "") -> 23 | T34: =IF(is_cat, ADDRESS(sort_min_row, COLUMN(comb_rank)) &":" & ADDRESS(sort_max_row, COLUMN(comb_rank)), "") -> $S$22:$S$36 | U34: =IF(is_cat,RANK(comb_rank,INDIRECT(comb_rank_range),1),"") -> 3 | V34: =IF(is_cat, ADDRESS(sort_min_row, COLUMN(comb_rank_norm)) &":" & ADDRESS(ROW(), COLUMN(comb_rank_norm)), "") -> $U$22:$U$34 | W34: =IF(is_cat, comb_rank_norm + COUNTIF(INDIRECT(comb_rank_norm_run_range), comb_rank_norm)-1, "") -> 14 | X34: =IF(is_cat, header_row_id + comb_rank_unique, row_id) -> 43 | Y34: =IF(is_empty, "", INDEX($J:$J, MATCH(row_id, $X:$X, 0))) -> Miscellaneous | Z34: =IF(is_empty, "", IF(is_header, "Tracked", INDEX($K:$K, MATCH(row_id, $X:$X, 0)))) -> 0 | AA34: =IF(is_empty, "", IF(is_header, "Budget", INDEX($L:$L, MATCH(row_id, $X:$X, 0)))) -> 0 | AB34: =IF(is_empty, "", IF(is_header, "% Compl.", IFERROR(out_tracked / out_budget, "-"))) -> - | AC34: =IF(is_empty, "", IF(is_header, "Remaining", IF(out_budget - out_tracked > 0, out_budget - out_tracked, 0))) -> 0 | AD34: =IF(is_empty, "", IF(is_header, "Excess", IF(out_budget - out_tracked < 0, out_tracked - out_budget, 0))) -> 0 | AI34: =Calculations!I40 | AJ34: =Calculations!J40 | AP34: =Calculations!M40 | AQ34: =Calculations!N40
C35: {=IF(C34=-1,-1, IF(C34<income_max_row, C34+1, IF(C34=income_max_row, income_total_row, IF(C34=income_total_row, "/1", IF(C34="/1", expenses_header_row, IF(C34<expenses_max_row, C34+1, IF(C34=expenses_max_row, expenses_total_row, IF(C34=expenses_total_row, "/2", IF(C34="/2", savings_header_row, IF(C34<savings_max_row, C34+1, IF(C34=savings_max_row, savings_total_row, -1)))))))))))} -> 43 | D35: =IF(is_header,row_id, IF(NOT(is_empty),D34,-1)) -> 29 | E35: {=1*OR(row_id=income_header_row, row_id=expenses_header_row, row_id=savings_header_row)} -> 0 | F35: =1*NOT(OR(is_header, is_total, is_empty)) -> 1 | G35: {=1*OR(row_id=income_total_row, row_id=expenses_total_row, row_id=savings_total_row)} -> 0 | H35: =1*OR(row_id="/1", row_id="/2", row_id=-1) -> 0 | I35: {=IFERROR(INDEX('Budget Planning'!$C:$C, header_row_id),"")} -> Expenses | J35: {=IFERROR(INDEX('Budget Planning'!$C:$C, row_id), "")} -> Debit Card Fees | K35: {=IF( OR(is_header, is_empty, selected_period=""), "", IF( is_total, IF( selected_period="Total Year", SUMPRODUCT( Tracking[Amount] * (Tracking[Type]=type) * (YEAR(Tracking[Effective Date])=selected_year) ), SUMPRODUCT( Tracking[Amount] * (Tracking[Type]=type) * (YEAR(Tracking[Effective Date])=selected_year) * (MONTH(Tracking[Effective Date])=selected_period) ) ), IF( selected_period="Total Year", SUMPRODUCT( Tracking[Amount] * (Tracking[Type]=type) * (Tracking[Category]=item) * (YEAR(Tracking[Effective Date])=selected_year) ), SUMPRODUCT( Tracking[Amount] * (Tracking[Type]=type) * (Tracking[Category]=item) * (YEAR(Tracking[Effective Date])=selected_year) * (MONTH(Tracking[Effective Date])=selected_period) ) ) ) )} -> 0 | L35: {=IF( OR(is_header, is_empty), "", INDEX( 'Budget Planning'!$E:$FA, row_id, MATCH( IF( selected_period = "Total Year", selected_year, DATE(selected_year, selected_period, 1) ), 'Budget Planning'!$E$10:$FA$10, 0 ) ) )} -> 0 | M35: {=IF( is_cat, IF( header_row_id = income_header_row, MATCH(income_min_row, $C:$C, 0), IF( header_row_id = expenses_header_row, MATCH(expenses_min_row, $C:$C, 0), IF( header_row_id = savings_header_row, MATCH(savings_min_row, $C:$C, 0), "" ) ) ), "" )} -> 22 | N35: {=IF( is_cat, IF( header_row_id = income_header_row, MATCH(income_max_row, $C:$C, 0), IF( header_row_id = expenses_header_row, MATCH(expenses_max_row, $C:$C, 0), IF( header_row_id = savings_header_row, MATCH(savings_max_row, $C:$C, 0), "" ) ) ), "" )} -> 36 | O35: =IF(is_cat, ADDRESS(sort_min_row, COLUMN(tracked)) &":" & ADDRESS(sort_max_row, COLUMN(tracked)), "") -> $K$22:$K$36 | P35: =IF(is_cat, RANK(tracked, INDIRECT(tracked_range), 0), "") -> 2 | Q35: =IF(is_cat, ADDRESS(sort_min_row, COLUMN(budget)) &":" & ADDRESS(sort_max_row, COLUMN(budget)), "") -> $L$22:$L$36 | R35: =IF(is_cat, RANK(budget, INDIRECT(budget_range), 0), "") -> 3 | S35: =IF(is_cat, _xlfn.NUMBERVALUE(tracked_rank & budget_rank), "") -> 23 | T35: =IF(is_cat, ADDRESS(sort_min_row, COLUMN(comb_rank)) &":" & ADDRESS(sort_max_row, COLUMN(comb_rank)), "") -> $S$22:$S$36 | U35: =IF(is_cat,RANK(comb_rank,INDIRECT(comb_rank_range),1),"") -> 3 | V35: =IF(is_cat, ADDRESS(sort_min_row, COLUMN(comb_rank_norm)) &":" & ADDRESS(ROW(), COLUMN(comb_rank_norm)), "") -> $U$22:$U$35 | W35: =IF(is_cat, comb_rank_norm + COUNTIF(INDIRECT(comb_rank_norm_run_range), comb_rank_norm)-1, "") -> 15 | X35: =IF(is_cat, header_row_id + comb_rank_unique, row_id) -> 44 | Y35: =IF(is_empty, "", INDEX($J:$J, MATCH(row_id, $X:$X, 0))) -> Taxes | Z35: =IF(is_empty, "", IF(is_header, "Tracked", INDEX($K:$K, MATCH(row_id, $X:$X, 0)))) -> 0 | AA35: =IF(is_empty, "", IF(is_header, "Budget", INDEX($L:$L, MATCH(row_id, $X:$X, 0)))) -> 0 | AB35: =IF(is_empty, "", IF(is_header, "% Compl.", IFERROR(out_tracked / out_budget, "-"))) -> - | AC35: =IF(is_empty, "", IF(is_header, "Remaining", IF(out_budget - out_tracked > 0, out_budget - out_tracked, 0))) -> 0 | AD35: =IF(is_empty, "", IF(is_header, "Excess", IF(out_budget - out_tracked < 0, out_tracked - out_budget, 0))) -> 0 | AI35: =Calculations!I41 -> Total | AJ35: =Calculations!J41 -> 70000 | AP35: =Calculations!M41 -> Total | AQ35: =Calculations!N41 -> 0
C36: {=IF(C35=-1,-1, IF(C35<income_max_row, C35+1, IF(C35=income_max_row, income_total_row, IF(C35=income_total_row, "/1", IF(C35="/1", expenses_header_row, IF(C35<expenses_max_row, C35+1, IF(C35=expenses_max_row, expenses_total_row, IF(C35=expenses_total_row, "/2", IF(C35="/2", savings_header_row, IF(C35<savings_max_row, C35+1, IF(C35=savings_max_row, savings_total_row, -1)))))))))))} -> 44 | D36: =IF(is_header,row_id, IF(NOT(is_empty),D35,-1)) -> 29 | E36: {=1*OR(row_id=income_header_row, row_id=expenses_header_row, row_id=savings_header_row)} -> 0 | F36: =1*NOT(OR(is_header, is_total, is_empty)) -> 1 | G36: {=1*OR(row_id=income_total_row, row_id=expenses_total_row, row_id=savings_total_row)} -> 0 | H36: =1*OR(row_id="/1", row_id="/2", row_id=-1) -> 0 | I36: {=IFERROR(INDEX('Budget Planning'!$C:$C, header_row_id),"")} -> Expenses | J36: {=IFERROR(INDEX('Budget Planning'!$C:$C, row_id), "")} -> CC Bill | K36: {=IF( OR(is_header, is_empty, selected_period=""), "", IF( is_total, IF( selected_period="Total Year", SUMPRODUCT( Tracking[Amount] * (Tracking[Type]=type) * (YEAR(Tracking[Effective Date])=selected_year) ), SUMPRODUCT( Tracking[Amount] * (Tracking[Type]=type) * (YEAR(Tracking[Effective Date])=selected_year) * (MONTH(Tracking[Effective Date])=selected_period) ) ), IF( selected_period="Total Year", SUMPRODUCT( Tracking[Amount] * (Tracking[Type]=type) * (Tracking[Category]=item) * (YEAR(Tracking[Effective Date])=selected_year) ), SUMPRODUCT( Tracking[Amount] * (Tracking[Type]=type) * (Tracking[Category]=item) * (YEAR(Tracking[Effective Date])=selected_year) * (MONTH(Tracking[Effective Date])=selected_period) ) ) ) )} -> 0 | L36: {=IF( OR(is_header, is_empty), "", INDEX( 'Budget Planning'!$E:$FA, row_id, MATCH( IF( selected_period = "Total Year", selected_year, DATE(selected_year, selected_period, 1) ), 'Budget Planning'!$E$10:$FA$10, 0 ) ) )} -> 44417 | M36: {=IF( is_cat, IF( header_row_id = income_header_row, MATCH(income_min_row, $C:$C, 0), IF( header_row_id = expenses_header_row, MATCH(expenses_min_row, $C:$C, 0), IF( header_row_id = savings_header_row, MATCH(savings_min_row, $C:$C, 0), "" ) ) ), "" )} -> 22 | N36: {=IF( is_cat, IF( header_row_id = income_header_row, MATCH(income_max_row, $C:$C, 0), IF( header_row_id = expenses_header_row, MATCH(expenses_max_row, $C:$C, 0), IF( header_row_id = savings_header_row, MATCH(savings_max_row, $C:$C, 0), "" ) ) ), "" )} -> 36 | O36: =IF(is_cat, ADDRESS(sort_min_row, COLUMN(tracked)) &":" & ADDRESS(sort_max_row, COLUMN(tracked)), "") -> $K$22:$K$36 | P36: =IF(is_cat, RANK(tracked, INDIRECT(tracked_range), 0), "") -> 2 | Q36: =IF(is_cat, ADDRESS(sort_min_row, COLUMN(budget)) &":" & ADDRESS(sort_max_row, COLUMN(budget)), "") -> $L$22:$L$36 | R36: =IF(is_cat, RANK(budget, INDIRECT(budget_range), 0), "") -> 2 | S36: =IF(is_cat, _xlfn.NUMBERVALUE(tracked_rank & budget_rank), "") -> 22 | T36: =IF(is_cat, ADDRESS(sort_min_row, COLUMN(comb_rank)) &":" & ADDRESS(sort_max_row, COLUMN(comb_rank)), "") -> $S$22:$S$36 | U36: =IF(is_cat,RANK(comb_rank,INDIRECT(comb_rank_range),1),"") -> 2 | V36: =IF(is_cat, ADDRESS(sort_min_row, COLUMN(comb_rank_norm)) &":" & ADDRESS(ROW(), COLUMN(comb_rank_norm)), "") -> $U$22:$U$36 | W36: =IF(is_cat, comb_rank_norm + COUNTIF(INDIRECT(comb_rank_norm_run_range), comb_rank_norm)-1, "") -> 2 | X36: =IF(is_cat, header_row_id + comb_rank_unique, row_id) -> 31 | Y36: =IF(is_empty, "", INDEX($J:$J, MATCH(row_id, $X:$X, 0))) -> Debit Card Fees | Z36: =IF(is_empty, "", IF(is_header, "Tracked", INDEX($K:$K, MATCH(row_id, $X:$X, 0)))) -> 0 | AA36: =IF(is_empty, "", IF(is_header, "Budget", INDEX($L:$L, MATCH(row_id, $X:$X, 0)))) -> 0 | AB36: =IF(is_empty, "", IF(is_header, "% Compl.", IFERROR(out_tracked / out_budget, "-"))) -> - | AC36: =IF(is_empty, "", IF(is_header, "Remaining", IF(out_budget - out_tracked > 0, out_budget - out_tracked, 0))) -> 0 | AD36: =IF(is_empty, "", IF(is_header, "Excess", IF(out_budget - out_tracked < 0, out_tracked - out_budget, 0))) -> 0
C37: {=IF(C36=-1,-1, IF(C36<income_max_row, C36+1, IF(C36=income_max_row, income_total_row, IF(C36=income_total_row, "/1", IF(C36="/1", expenses_header_row, IF(C36<expenses_max_row, C36+1, IF(C36=expenses_max_row, expenses_total_row, IF(C36=expenses_total_row, "/2", IF(C36="/2", savings_header_row, IF(C36<savings_max_row, C36+1, IF(C36=savings_max_row, savings_total_row, -1)))))))))))} -> 46 | D37: =IF(is_header,row_id, IF(NOT(is_empty),D36,-1)) -> 29 | E37: {=1*OR(row_id=income_header_row, row_id=expenses_header_row, row_id=savings_header_row)} -> 0 | F37: =1*NOT(OR(is_header, is_total, is_empty)) -> 0 | G37: {=1*OR(row_id=income_total_row, row_id=expenses_total_row, row_id=savings_total_row)} -> 1 | H37: =1*OR(row_id="/1", row_id="/2", row_id=-1) -> 0 | I37: {=IFERROR(INDEX('Budget Planning'!$C:$C, header_row_id),"")} -> Expenses | J37: {=IFERROR(INDEX('Budget Planning'!$C:$C, row_id), "")} -> Total | K37: {=IF( OR(is_header, is_empty, selected_period=""), "", IF( is_total, IF( selected_period="Total Year", SUMPRODUCT( Tracking[Amount] * (Tracking[Type]=type) * (YEAR(Tracking[Effective Date])=selected_year) ), SUMPRODUCT( Tracking[Amount] * (Tracking[Type]=type) * (YEAR(Tracking[Effective Date])=selected_year) * (MONTH(Tracking[Effective Date])=selected_period) ) ), IF( selected_period="Total Year", SUMPRODUCT( Tracking[Amount] * (Tracking[Type]=type) * (Tracking[Category]=item) * (YEAR(Tracking[Effective Date])=selected_year) ), SUMPRODUCT( Tracking[Amount] * (Tracking[Type]=type) * (Tracking[Category]=item) * (YEAR(Tracking[Effective Date])=selected_year) * (MONTH(Tracking[Effective Date])=selected_period) ) ) ) )} -> 70000 | L37: {=IF( OR(is_header, is_empty), "", INDEX( 'Budget Planning'!$E:$FA, row_id, MATCH( IF( selected_period = "Total Year", selected_year, DATE(selected_year, selected_period, 1) ), 'Budget Planning'!$E$10:$FA$10, 0 ) ) )} -> 114417 | M37: {=IF( is_cat, IF( header_row_id = income_header_row, MATCH(income_min_row, $C:$C, 0), IF( header_row_id = expenses_header_row, MATCH(expenses_min_row, $C:$C, 0), IF( header_row_id = savings_header_row, MATCH(savings_min_row, $C:$C, 0), "" ) ) ), "" )} | N37: {=IF( is_cat, IF( header_row_id = income_header_row, MATCH(income_max_row, $C:$C, 0), IF( header_row_id = expenses_header_row, MATCH(expenses_max_row, $C:$C, 0), IF( header_row_id = savings_header_row, MATCH(savings_max_row, $C:$C, 0), "" ) ) ), "" )} | O37: =IF(is_cat, ADDRESS(sort_min_row, COLUMN(tracked)) &":" & ADDRESS(sort_max_row, COLUMN(tracked)), "") | P37: =IF(is_cat, RANK(tracked, INDIRECT(tracked_range), 0), "") | Q37: =IF(is_cat, ADDRESS(sort_min_row, COLUMN(budget)) &":" & ADDRESS(sort_max_row, COLUMN(budget)), "") | R37: =IF(is_cat, RANK(budget, INDIRECT(budget_range), 0), "") | S37: =IF(is_cat, _xlfn.NUMBERVALUE(tracked_rank & budget_rank), "") | T37: =IF(is_cat, ADDRESS(sort_min_row, COLUMN(comb_rank)) &":" & ADDRESS(sort_max_row, COLUMN(comb_rank)), "") | U37: =IF(is_cat,RANK(comb_rank,INDIRECT(comb_rank_range),1),"") | V37: =IF(is_cat, ADDRESS(sort_min_row, COLUMN(comb_rank_norm)) &":" & ADDRESS(ROW(), COLUMN(comb_rank_norm)), "") | W37: =IF(is_cat, comb_rank_norm + COUNTIF(INDIRECT(comb_rank_norm_run_range), comb_rank_norm)-1, "") | X37: =IF(is_cat, header_row_id + comb_rank_unique, row_id) -> 46 | Y37: =IF(is_empty, "", INDEX($J:$J, MATCH(row_id, $X:$X, 0))) -> Total | Z37: =IF(is_empty, "", IF(is_header, "Tracked", INDEX($K:$K, MATCH(row_id, $X:$X, 0)))) -> 70000 | AA37: =IF(is_empty, "", IF(is_header, "Budget", INDEX($L:$L, MATCH(row_id, $X:$X, 0)))) -> 114417 | AB37: =IF(is_empty, "", IF(is_header, "% Compl.", IFERROR(out_tracked / out_budget, "-"))) -> 0.6117972 | AC37: =IF(is_empty, "", IF(is_header, "Remaining", IF(out_budget - out_tracked > 0, out_budget - out_tracked, 0))) -> 44417 | AD37: =IF(is_empty, "", IF(is_header, "Excess", IF(out_budget - out_tracked < 0, out_tracked - out_budget, 0))) -> 0
C38: {=IF(C37=-1,-1, IF(C37<income_max_row, C37+1, IF(C37=income_max_row, income_total_row, IF(C37=income_total_row, "/1", IF(C37="/1", expenses_header_row, IF(C37<expenses_max_row, C37+1, IF(C37=expenses_max_row, expenses_total_row, IF(C37=expenses_total_row, "/2", IF(C37="/2", savings_header_row, IF(C37<savings_max_row, C37+1, IF(C37=savings_max_row, savings_total_row, -1)))))))))))} -> /2 | D38: =IF(is_header,row_id, IF(NOT(is_empty),D37,-1)) -> -1 | E38: {=1*OR(row_id=income_header_row, row_id=expenses_header_row, row_id=savings_header_row)} -> 0 | F38: =1*NOT(OR(is_header, is_total, is_empty)) -> 0 | G38: {=1*OR(row_id=income_total_row, row_id=expenses_total_row, row_id=savings_total_row)} -> 0 | H38: =1*OR(row_id="/1", row_id="/2", row_id=-1) -> 1 | I38: {=IFERROR(INDEX('Budget Planning'!$C:$C, header_row_id),"")} | J38: {=IFERROR(INDEX('Budget Planning'!$C:$C, row_id), "")} | K38: {=IF( OR(is_header, is_empty, selected_period=""), "", IF( is_total, IF( selected_period="Total Year", SUMPRODUCT( Tracking[Amount] * (Tracking[Type]=type) * (YEAR(Tracking[Effective Date])=selected_year) ), SUMPRODUCT( Tracking[Amount] * (Tracking[Type]=type) * (YEAR(Tracking[Effective Date])=selected_year) * (MONTH(Tracking[Effective Date])=selected_period) ) ), IF( selected_period="Total Year", SUMPRODUCT( Tracking[Amount] * (Tracking[Type]=type) * (Tracking[Category]=item) * (YEAR(Tracking[Effective Date])=selected_year) ), SUMPRODUCT( Tracking[Amount] * (Tracking[Type]=type) * (Tracking[Category]=item) * (YEAR(Tracking[Effective Date])=selected_year) * (MONTH(Tracking[Effective Date])=selected_period) ) ) ) )} | L38: {=IF( OR(is_header, is_empty), "", INDEX( 'Budget Planning'!$E:$FA, row_id, MATCH( IF( selected_period = "Total Year", selected_year, DATE(selected_year, selected_period, 1) ), 'Budget Planning'!$E$10:$FA$10, 0 ) ) )} | M38: {=IF( is_cat, IF( header_row_id = income_header_row, MATCH(income_min_row, $C:$C, 0), IF( header_row_id = expenses_header_row, MATCH(expenses_min_row, $C:$C, 0), IF( header_row_id = savings_header_row, MATCH(savings_min_row, $C:$C, 0), "" ) ) ), "" )} | N38: {=IF( is_cat, IF( header_row_id = income_header_row, MATCH(income_max_row, $C:$C, 0), IF( header_row_id = expenses_header_row, MATCH(expenses_max_row, $C:$C, 0), IF( header_row_id = savings_header_row, MATCH(savings_max_row, $C:$C, 0), "" ) ) ), "" )} | O38: =IF(is_cat, ADDRESS(sort_min_row, COLUMN(tracked)) &":" & ADDRESS(sort_max_row, COLUMN(tracked)), "") | P38: =IF(is_cat, RANK(tracked, INDIRECT(tracked_range), 0), "") | Q38: =IF(is_cat, ADDRESS(sort_min_row, COLUMN(budget)) &":" & ADDRESS(sort_max_row, COLUMN(budget)), "") | R38: =IF(is_cat, RANK(budget, INDIRECT(budget_range), 0), "") | S38: =IF(is_cat, _xlfn.NUMBERVALUE(tracked_rank & budget_rank), "") | T38: =IF(is_cat, ADDRESS(sort_min_row, COLUMN(comb_rank)) &":" & ADDRESS(sort_max_row, COLUMN(comb_rank)), "") | U38: =IF(is_cat,RANK(comb_rank,INDIRECT(comb_rank_range),1),"") | V38: =IF(is_cat, ADDRESS(sort_min_row, COLUMN(comb_rank_norm)) &":" & ADDRESS(ROW(), COLUMN(comb_rank_norm)), "") | W38: =IF(is_cat, comb_rank_norm + COUNTIF(INDIRECT(comb_rank_norm_run_range), comb_rank_norm)-1, "") | X38: =IF(is_cat, header_row_id + comb_rank_unique, row_id) -> /2 | Y38: =IF(is_empty, "", INDEX($J:$J, MATCH(row_id, $X:$X, 0))) | Z38: =IF(is_empty, "", IF(is_header, "Tracked", INDEX($K:$K, MATCH(row_id, $X:$X, 0)))) | AA38: =IF(is_empty, "", IF(is_header, "Budget", INDEX($L:$L, MATCH(row_id, $X:$X, 0)))) | AB38: =IF(is_empty, "", IF(is_header, "% Compl.", IFERROR(out_tracked / out_budget, "-"))) | AC38: =IF(is_empty, "", IF(is_header, "Remaining", IF(out_budget - out_tracked > 0, out_budget - out_tracked, 0))) | AD38: =IF(is_empty, "", IF(is_header, "Excess", IF(out_budget - out_tracked < 0, out_tracked - out_budget, 0)))
C39: {=IF(C38=-1,-1, IF(C38<income_max_row, C38+1, IF(C38=income_max_row, income_total_row, IF(C38=income_total_row, "/1", IF(C38="/1", expenses_header_row, IF(C38<expenses_max_row, C38+1, IF(C38=expenses_max_row, expenses_total_row, IF(C38=expenses_total_row, "/2", IF(C38="/2", savings_header_row, IF(C38<savings_max_row, C38+1, IF(C38=savings_max_row, savings_total_row, -1)))))))))))} -> 48 | D39: =IF(is_header,row_id, IF(NOT(is_empty),D38,-1)) -> 48 | E39: {=1*OR(row_id=income_header_row, row_id=expenses_header_row, row_id=savings_header_row)} -> 1 | F39: =1*NOT(OR(is_header, is_total, is_empty)) -> 0 | G39: {=1*OR(row_id=income_total_row, row_id=expenses_total_row, row_id=savings_total_row)} -> 0 | H39: =1*OR(row_id="/1", row_id="/2", row_id=-1) -> 0 | I39: {=IFERROR(INDEX('Budget Planning'!$C:$C, header_row_id),"")} -> Savings | J39: {=IFERROR(INDEX('Budget Planning'!$C:$C, row_id), "")} -> Savings | K39: {=IF( OR(is_header, is_empty, selected_period=""), "", IF( is_total, IF( selected_period="Total Year", SUMPRODUCT( Tracking[Amount] * (Tracking[Type]=type) * (YEAR(Tracking[Effective Date])=selected_year) ), SUMPRODUCT( Tracking[Amount] * (Tracking[Type]=type) * (YEAR(Tracking[Effective Date])=selected_year) * (MONTH(Tracking[Effective Date])=selected_period) ) ), IF( selected_period="Total Year", SUMPRODUCT( Tracking[Amount] * (Tracking[Type]=type) * (Tracking[Category]=item) * (YEAR(Tracking[Effective Date])=selected_year) ), SUMPRODUCT( Tracking[Amount] * (Tracking[Type]=type) * (Tracking[Category]=item) * (YEAR(Tracking[Effective Date])=selected_year) * (MONTH(Tracking[Effective Date])=selected_period) ) ) ) )} | L39: {=IF( OR(is_header, is_empty), "", INDEX( 'Budget Planning'!$E:$FA, row_id, MATCH( IF( selected_period = "Total Year", selected_year, DATE(selected_year, selected_period, 1) ), 'Budget Planning'!$E$10:$FA$10, 0 ) ) )} | M39: {=IF( is_cat, IF( header_row_id = income_header_row, MATCH(income_min_row, $C:$C, 0), IF( header_row_id = expenses_header_row, MATCH(expenses_min_row, $C:$C, 0), IF( header_row_id = savings_header_row, MATCH(savings_min_row, $C:$C, 0), "" ) ) ), "" )} | N39: {=IF( is_cat, IF( header_row_id = income_header_row, MATCH(income_max_row, $C:$C, 0), IF( header_row_id = expenses_header_row, MATCH(expenses_max_row, $C:$C, 0), IF( header_row_id = savings_header_row, MATCH(savings_max_row, $C:$C, 0), "" ) ) ), "" )} | O39: =IF(is_cat, ADDRESS(sort_min_row, COLUMN(tracked)) &":" & ADDRESS(sort_max_row, COLUMN(tracked)), "") | P39: =IF(is_cat, RANK(tracked, INDIRECT(tracked_range), 0), "") | Q39: =IF(is_cat, ADDRESS(sort_min_row, COLUMN(budget)) &":" & ADDRESS(sort_max_row, COLUMN(budget)), "") | R39: =IF(is_cat, RANK(budget, INDIRECT(budget_range), 0), "") | S39: =IF(is_cat, _xlfn.NUMBERVALUE(tracked_rank & budget_rank), "") | T39: =IF(is_cat, ADDRESS(sort_min_row, COLUMN(comb_rank)) &":" & ADDRESS(sort_max_row, COLUMN(comb_rank)), "") | U39: =IF(is_cat,RANK(comb_rank,INDIRECT(comb_rank_range),1),"") | V39: =IF(is_cat, ADDRESS(sort_min_row, COLUMN(comb_rank_norm)) &":" & ADDRESS(ROW(), COLUMN(comb_rank_norm)), "") | W39: =IF(is_cat, comb_rank_norm + COUNTIF(INDIRECT(comb_rank_norm_run_range), comb_rank_norm)-1, "") | X39: =IF(is_cat, header_row_id + comb_rank_unique, row_id) -> 48 | Y39: =IF(is_empty, "", INDEX($J:$J, MATCH(row_id, $X:$X, 0))) -> Savings | Z39: =IF(is_empty, "", IF(is_header, "Tracked", INDEX($K:$K, MATCH(row_id, $X:$X, 0)))) -> Tracked | AA39: =IF(is_empty, "", IF(is_header, "Budget", INDEX($L:$L, MATCH(row_id, $X:$X, 0)))) -> Budget | AB39: =IF(is_empty, "", IF(is_header, "% Compl.", IFERROR(out_tracked / out_budget, "-"))) -> % Compl. | AC39: =IF(is_empty, "", IF(is_header, "Remaining", IF(out_budget - out_tracked > 0, out_budget - out_tracked, 0))) -> Remaining | AD39: =IF(is_empty, "", IF(is_header, "Excess", IF(out_budget - out_tracked < 0, out_tracked - out_budget, 0))) -> Excess
C40: {=IF(C39=-1,-1, IF(C39<income_max_row, C39+1, IF(C39=income_max_row, income_total_row, IF(C39=income_total_row, "/1", IF(C39="/1", expenses_header_row, IF(C39<expenses_max_row, C39+1, IF(C39=expenses_max_row, expenses_total_row, IF(C39=expenses_total_row, "/2", IF(C39="/2", savings_header_row, IF(C39<savings_max_row, C39+1, IF(C39=savings_max_row, savings_total_row, -1)))))))))))} -> 49 | D40: =IF(is_header,row_id, IF(NOT(is_empty),D39,-1)) -> 48 | E40: {=1*OR(row_id=income_header_row, row_id=expenses_header_row, row_id=savings_header_row)} -> 0 | F40: =1*NOT(OR(is_header, is_total, is_empty)) -> 1 | G40: {=1*OR(row_id=income_total_row, row_id=expenses_total_row, row_id=savings_total_row)} -> 0 | H40: =1*OR(row_id="/1", row_id="/2", row_id=-1) -> 0 | I40: {=IFERROR(INDEX('Budget Planning'!$C:$C, header_row_id),"")} -> Savings | J40: {=IFERROR(INDEX('Budget Planning'!$C:$C, row_id), "")} -> Bank | K40: {=IF( OR(is_header, is_empty, selected_period=""), "", IF( is_total, IF( selected_period="Total Year", SUMPRODUCT( Tracking[Amount] * (Tracking[Type]=type) * (YEAR(Tracking[Effective Date])=selected_year) ), SUMPRODUCT( Tracking[Amount] * (Tracking[Type]=type) * (YEAR(Tracking[Effective Date])=selected_year) * (MONTH(Tracking[Effective Date])=selected_period) ) ), IF( selected_period="Total Year", SUMPRODUCT( Tracking[Amount] * (Tracking[Type]=type) * (Tracking[Category]=item) * (YEAR(Tracking[Effective Date])=selected_year) ), SUMPRODUCT( Tracking[Amount] * (Tracking[Type]=type) * (Tracking[Category]=item) * (YEAR(Tracking[Effective Date])=selected_year) * (MONTH(Tracking[Effective Date])=selected_period) ) ) ) )} -> 0 | L40: {=IF( OR(is_header, is_empty), "", INDEX( 'Budget Planning'!$E:$FA, row_id, MATCH( IF( selected_period = "Total Year", selected_year, DATE(selected_year, selected_period, 1) ), 'Budget Planning'!$E$10:$FA$10, 0 ) ) )} -> 0 | M40: {=IF( is_cat, IF( header_row_id = income_header_row, MATCH(income_min_row, $C:$C, 0), IF( header_row_id = expenses_header_row, MATCH(expenses_min_row, $C:$C, 0), IF( header_row_id = savings_header_row, MATCH(savings_min_row, $C:$C, 0), "" ) ) ), "" )} -> 40 | N40: {=IF( is_cat, IF( header_row_id = income_header_row, MATCH(income_max_row, $C:$C, 0), IF( header_row_id = expenses_header_row, MATCH(expenses_max_row, $C:$C, 0), IF( header_row_id = savings_header_row, MATCH(savings_max_row, $C:$C, 0), "" ) ) ), "" )} -> 45 | O40: =IF(is_cat, ADDRESS(sort_min_row, COLUMN(tracked)) &":" & ADDRESS(sort_max_row, COLUMN(tracked)), "") -> $K$40:$K$45 | P40: =IF(is_cat, RANK(tracked, INDIRECT(tracked_range), 0), "") -> 1 | Q40: =IF(is_cat, ADDRESS(sort_min_row, COLUMN(budget)) &":" & ADDRESS(sort_max_row, COLUMN(budget)), "") -> $L$40:$L$45 | R40: =IF(is_cat, RANK(budget, INDIRECT(budget_range), 0), "") -> 1 | S40: =IF(is_cat, _xlfn.NUMBERVALUE(tracked_rank & budget_rank), "") -> 11 | T40: =IF(is_cat, ADDRESS(sort_min_row, COLUMN(comb_rank)) &":" & ADDRESS(sort_max_row, COLUMN(comb_rank)), "") -> $S$40:$S$45 | U40: =IF(is_cat,RANK(comb_rank,INDIRECT(comb_rank_range),1),"") -> 1 | V40: =IF(is_cat, ADDRESS(sort_min_row, COLUMN(comb_rank_norm)) &":" & ADDRESS(ROW(), COLUMN(comb_rank_norm)), "") -> $U$40:$U$40 | W40: =IF(is_cat, comb_rank_norm + COUNTIF(INDIRECT(comb_rank_norm_run_range), comb_rank_norm)-1, "") -> 1 | X40: =IF(is_cat, header_row_id + comb_rank_unique, row_id) -> 49 | Y40: =IF(is_empty, "", INDEX($J:$J, MATCH(row_id, $X:$X, 0))) -> Bank | Z40: =IF(is_empty, "", IF(is_header, "Tracked", INDEX($K:$K, MATCH(row_id, $X:$X, 0)))) -> 0 | AA40: =IF(is_empty, "", IF(is_header, "Budget", INDEX($L:$L, MATCH(row_id, $X:$X, 0)))) -> 0 | AB40: =IF(is_empty, "", IF(is_header, "% Compl.", IFERROR(out_tracked / out_budget, "-"))) -> - | AC40: =IF(is_empty, "", IF(is_header, "Remaining", IF(out_budget - out_tracked > 0, out_budget - out_tracked, 0))) -> 0 | AD40: =IF(is_empty, "", IF(is_header, "Excess", IF(out_budget - out_tracked < 0, out_tracked - out_budget, 0))) -> 0
C41: {=IF(C40=-1,-1, IF(C40<income_max_row, C40+1, IF(C40=income_max_row, income_total_row, IF(C40=income_total_row, "/1", IF(C40="/1", expenses_header_row, IF(C40<expenses_max_row, C40+1, IF(C40=expenses_max_row, expenses_total_row, IF(C40=expenses_total_row, "/2", IF(C40="/2", savings_header_row, IF(C40<savings_max_row, C40+1, IF(C40=savings_max_row, savings_total_row, -1)))))))))))} -> 50 | D41: =IF(is_header,row_id, IF(NOT(is_empty),D40,-1)) -> 48 | E41: {=1*OR(row_id=income_header_row, row_id=expenses_header_row, row_id=savings_header_row)} -> 0 | F41: =1*NOT(OR(is_header, is_total, is_empty)) -> 1 | G41: {=1*OR(row_id=income_total_row, row_id=expenses_total_row, row_id=savings_total_row)} -> 0 | H41: =1*OR(row_id="/1", row_id="/2", row_id=-1) -> 0 | I41: {=IFERROR(INDEX('Budget Planning'!$C:$C, header_row_id),"")} -> Savings | J41: {=IFERROR(INDEX('Budget Planning'!$C:$C, row_id), "")} -> Emergency Fund | K41: {=IF( OR(is_header, is_empty, selected_period=""), "", IF( is_total, IF( selected_period="Total Year", SUMPRODUCT( Tracking[Amount] * (Tracking[Type]=type) * (YEAR(Tracking[Effective Date])=selected_year) ), SUMPRODUCT( Tracking[Amount] * (Tracking[Type]=type) * (YEAR(Tracking[Effective Date])=selected_year) * (MONTH(Tracking[Effective Date])=selected_period) ) ), IF( selected_period="Total Year", SUMPRODUCT( Tracking[Amount] * (Tracking[Type]=type) * (Tracking[Category]=item) * (YEAR(Tracking[Effective Date])=selected_year) ), SUMPRODUCT( Tracking[Amount] * (Tracking[Type]=type) * (Tracking[Category]=item) * (YEAR(Tracking[Effective Date])=selected_year) * (MONTH(Tracking[Effective Date])=selected_period) ) ) ) )} -> 0 | L41: {=IF( OR(is_header, is_empty), "", INDEX( 'Budget Planning'!$E:$FA, row_id, MATCH( IF( selected_period = "Total Year", selected_year, DATE(selected_year, selected_period, 1) ), 'Budget Planning'!$E$10:$FA$10, 0 ) ) )} -> 0 | M41: {=IF( is_cat, IF( header_row_id = income_header_row, MATCH(income_min_row, $C:$C, 0), IF( header_row_id = expenses_header_row, MATCH(expenses_min_row, $C:$C, 0), IF( header_row_id = savings_header_row, MATCH(savings_min_row, $C:$C, 0), "" ) ) ), "" )} -> 40 | N41: {=IF( is_cat, IF( header_row_id = income_header_row, MATCH(income_max_row, $C:$C, 0), IF( header_row_id = expenses_header_row, MATCH(expenses_max_row, $C:$C, 0), IF( header_row_id = savings_header_row, MATCH(savings_max_row, $C:$C, 0), "" ) ) ), "" )} -> 45 | O41: =IF(is_cat, ADDRESS(sort_min_row, COLUMN(tracked)) &":" & ADDRESS(sort_max_row, COLUMN(tracked)), "") -> $K$40:$K$45 | P41: =IF(is_cat, RANK(tracked, INDIRECT(tracked_range), 0), "") -> 1 | Q41: =IF(is_cat, ADDRESS(sort_min_row, COLUMN(budget)) &":" & ADDRESS(sort_max_row, COLUMN(budget)), "") -> $L$40:$L$45 | R41: =IF(is_cat, RANK(budget, INDIRECT(budget_range), 0), "") -> 1 | S41: =IF(is_cat, _xlfn.NUMBERVALUE(tracked_rank & budget_rank), "") -> 11 | T41: =IF(is_cat, ADDRESS(sort_min_row, COLUMN(comb_rank)) &":" & ADDRESS(sort_max_row, COLUMN(comb_rank)), "") -> $S$40:$S$45 | U41: =IF(is_cat,RANK(comb_rank,INDIRECT(comb_rank_range),1),"") -> 1 | V41: =IF(is_cat, ADDRESS(sort_min_row, COLUMN(comb_rank_norm)) &":" & ADDRESS(ROW(), COLUMN(comb_rank_norm)), "") -> $U$40:$U$41 | W41: =IF(is_cat, comb_rank_norm + COUNTIF(INDIRECT(comb_rank_norm_run_range), comb_rank_norm)-1, "") -> 2 | X41: =IF(is_cat, header_row_id + comb_rank_unique, row_id) -> 50 | Y41: =IF(is_empty, "", INDEX($J:$J, MATCH(row_id, $X:$X, 0))) -> Emergency Fund | Z41: =IF(is_empty, "", IF(is_header, "Tracked", INDEX($K:$K, MATCH(row_id, $X:$X, 0)))) -> 0 | AA41: =IF(is_empty, "", IF(is_header, "Budget", INDEX($L:$L, MATCH(row_id, $X:$X, 0)))) -> 0 | AB41: =IF(is_empty, "", IF(is_header, "% Compl.", IFERROR(out_tracked / out_budget, "-"))) -> - | AC41: =IF(is_empty, "", IF(is_header, "Remaining", IF(out_budget - out_tracked > 0, out_budget - out_tracked, 0))) -> 0 | AD41: =IF(is_empty, "", IF(is_header, "Excess", IF(out_budget - out_tracked < 0, out_tracked - out_budget, 0))) -> 0
C42: {=IF(C41=-1,-1, IF(C41<income_max_row, C41+1, IF(C41=income_max_row, income_total_row, IF(C41=income_total_row, "/1", IF(C41="/1", expenses_header_row, IF(C41<expenses_max_row, C41+1, IF(C41=expenses_max_row, expenses_total_row, IF(C41=expenses_total_row, "/2", IF(C41="/2", savings_header_row, IF(C41<savings_max_row, C41+1, IF(C41=savings_max_row, savings_total_row, -1)))))))))))} -> 51 | D42: =IF(is_header,row_id, IF(NOT(is_empty),D41,-1)) -> 48 | E42: {=1*OR(row_id=income_header_row, row_id=expenses_header_row, row_id=savings_header_row)} -> 0 | F42: =1*NOT(OR(is_header, is_total, is_empty)) -> 1 | G42: {=1*OR(row_id=income_total_row, row_id=expenses_total_row, row_id=savings_total_row)} -> 0 | H42: =1*OR(row_id="/1", row_id="/2", row_id=-1) -> 0 | I42: {=IFERROR(INDEX('Budget Planning'!$C:$C, header_row_id),"")} -> Savings | J42: {=IFERROR(INDEX('Budget Planning'!$C:$C, row_id), "")} -> Gold | K42: {=IF( OR(is_header, is_empty, selected_period=""), "", IF( is_total, IF( selected_period="Total Year", SUMPRODUCT( Tracking[Amount] * (Tracking[Type]=type) * (YEAR(Tracking[Effective Date])=selected_year) ), SUMPRODUCT( Tracking[Amount] * (Tracking[Type]=type) * (YEAR(Tracking[Effective Date])=selected_year) * (MONTH(Tracking[Effective Date])=selected_period) ) ), IF( selected_period="Total Year", SUMPRODUCT( Tracking[Amount] * (Tracking[Type]=type) * (Tracking[Category]=item) * (YEAR(Tracking[Effective Date])=selected_year) ), SUMPRODUCT( Tracking[Amount] * (Tracking[Type]=type) * (Tracking[Category]=item) * (YEAR(Tracking[Effective Date])=selected_year) * (MONTH(Tracking[Effective Date])=selected_period) ) ) ) )} -> 0 | L42: {=IF( OR(is_header, is_empty), "", INDEX( 'Budget Planning'!$E:$FA, row_id, MATCH( IF( selected_period = "Total Year", selected_year, DATE(selected_year, selected_period, 1) ), 'Budget Planning'!$E$10:$FA$10, 0 ) ) )} -> 0 | M42: {=IF( is_cat, IF( header_row_id = income_header_row, MATCH(income_min_row, $C:$C, 0), IF( header_row_id = expenses_header_row, MATCH(expenses_min_row, $C:$C, 0), IF( header_row_id = savings_header_row, MATCH(savings_min_row, $C:$C, 0), "" ) ) ), "" )} -> 40 | N42: {=IF( is_cat, IF( header_row_id = income_header_row, MATCH(income_max_row, $C:$C, 0), IF( header_row_id = expenses_header_row, MATCH(expenses_max_row, $C:$C, 0), IF( header_row_id = savings_header_row, MATCH(savings_max_row, $C:$C, 0), "" ) ) ), "" )} -> 45 | O42: =IF(is_cat, ADDRESS(sort_min_row, COLUMN(tracked)) &":" & ADDRESS(sort_max_row, COLUMN(tracked)), "") -> $K$40:$K$45 | P42: =IF(is_cat, RANK(tracked, INDIRECT(tracked_range), 0), "") -> 1 | Q42: =IF(is_cat, ADDRESS(sort_min_row, COLUMN(budget)) &":" & ADDRESS(sort_max_row, COLUMN(budget)), "") -> $L$40:$L$45 | R42: =IF(is_cat, RANK(budget, INDIRECT(budget_range), 0), "") -> 1 | S42: =IF(is_cat, _xlfn.NUMBERVALUE(tracked_rank & budget_rank), "") -> 11 | T42: =IF(is_cat, ADDRESS(sort_min_row, COLUMN(comb_rank)) &":" & ADDRESS(sort_max_row, COLUMN(comb_rank)), "") -> $S$40:$S$45 | U42: =IF(is_cat,RANK(comb_rank,INDIRECT(comb_rank_range),1),"") -> 1 | V42: =IF(is_cat, ADDRESS(sort_min_row, COLUMN(comb_rank_norm)) &":" & ADDRESS(ROW(), COLUMN(comb_rank_norm)), "") -> $U$40:$U$42 | W42: =IF(is_cat, comb_rank_norm + COUNTIF(INDIRECT(comb_rank_norm_run_range), comb_rank_norm)-1, "") -> 3 | X42: =IF(is_cat, header_row_id + comb_rank_unique, row_id) -> 51 | Y42: =IF(is_empty, "", INDEX($J:$J, MATCH(row_id, $X:$X, 0))) -> Gold | Z42: =IF(is_empty, "", IF(is_header, "Tracked", INDEX($K:$K, MATCH(row_id, $X:$X, 0)))) -> 0 | AA42: =IF(is_empty, "", IF(is_header, "Budget", INDEX($L:$L, MATCH(row_id, $X:$X, 0)))) -> 0 | AB42: =IF(is_empty, "", IF(is_header, "% Compl.", IFERROR(out_tracked / out_budget, "-"))) -> - | AC42: =IF(is_empty, "", IF(is_header, "Remaining", IF(out_budget - out_tracked > 0, out_budget - out_tracked, 0))) -> 0 | AD42: =IF(is_empty, "", IF(is_header, "Excess", IF(out_budget - out_tracked < 0, out_tracked - out_budget, 0))) -> 0
C43: {=IF(C42=-1,-1, IF(C42<income_max_row, C42+1, IF(C42=income_max_row, income_total_row, IF(C42=income_total_row, "/1", IF(C42="/1", expenses_header_row, IF(C42<expenses_max_row, C42+1, IF(C42=expenses_max_row, expenses_total_row, IF(C42=expenses_total_row, "/2", IF(C42="/2", savings_header_row, IF(C42<savings_max_row, C42+1, IF(C42=savings_max_row, savings_total_row, -1)))))))))))} -> 52 | D43: =IF(is_header,row_id, IF(NOT(is_empty),D42,-1)) -> 48 | E43: {=1*OR(row_id=income_header_row, row_id=expenses_header_row, row_id=savings_header_row)} -> 0 | F43: =1*NOT(OR(is_header, is_total, is_empty)) -> 1 | G43: {=1*OR(row_id=income_total_row, row_id=expenses_total_row, row_id=savings_total_row)} -> 0 | H43: =1*OR(row_id="/1", row_id="/2", row_id=-1) -> 0 | I43: {=IFERROR(INDEX('Budget Planning'!$C:$C, header_row_id),"")} -> Savings | J43: {=IFERROR(INDEX('Budget Planning'!$C:$C, row_id), "")} -> Retirement Fund | K43: {=IF( OR(is_header, is_empty, selected_period=""), "", IF( is_total, IF( selected_period="Total Year", SUMPRODUCT( Tracking[Amount] * (Tracking[Type]=type) * (YEAR(Tracking[Effective Date])=selected_year) ), SUMPRODUCT( Tracking[Amount] * (Tracking[Type]=type) * (YEAR(Tracking[Effective Date])=selected_year) * (MONTH(Tracking[Effective Date])=selected_period) ) ), IF( selected_period="Total Year", SUMPRODUCT( Tracking[Amount] * (Tracking[Type]=type) * (Tracking[Category]=item) * (YEAR(Tracking[Effective Date])=selected_year) ), SUMPRODUCT( Tracking[Amount] * (Tracking[Type]=type) * (Tracking[Category]=item) * (YEAR(Tracking[Effective Date])=selected_year) * (MONTH(Tracking[Effective Date])=selected_period) ) ) ) )} -> 0 | L43: {=IF( OR(is_header, is_empty), "", INDEX( 'Budget Planning'!$E:$FA, row_id, MATCH( IF( selected_period = "Total Year", selected_year, DATE(selected_year, selected_period, 1) ), 'Budget Planning'!$E$10:$FA$10, 0 ) ) )} -> 0 | M43: {=IF( is_cat, IF( header_row_id = income_header_row, MATCH(income_min_row, $C:$C, 0), IF( header_row_id = expenses_header_row, MATCH(expenses_min_row, $C:$C, 0), IF( header_row_id = savings_header_row, MATCH(savings_min_row, $C:$C, 0), "" ) ) ), "" )} -> 40 | N43: {=IF( is_cat, IF( header_row_id = income_header_row, MATCH(income_max_row, $C:$C, 0), IF( header_row_id = expenses_header_row, MATCH(expenses_max_row, $C:$C, 0), IF( header_row_id = savings_header_row, MATCH(savings_max_row, $C:$C, 0), "" ) ) ), "" )} -> 45 | O43: =IF(is_cat, ADDRESS(sort_min_row, COLUMN(tracked)) &":" & ADDRESS(sort_max_row, COLUMN(tracked)), "") -> $K$40:$K$45 | P43: =IF(is_cat, RANK(tracked, INDIRECT(tracked_range), 0), "") -> 1 | Q43: =IF(is_cat, ADDRESS(sort_min_row, COLUMN(budget)) &":" & ADDRESS(sort_max_row, COLUMN(budget)), "") -> $L$40:$L$45 | R43: =IF(is_cat, RANK(budget, INDIRECT(budget_range), 0), "") -> 1 | S43: =IF(is_cat, _xlfn.NUMBERVALUE(tracked_rank & budget_rank), "") -> 11 | T43: =IF(is_cat, ADDRESS(sort_min_row, COLUMN(comb_rank)) &":" & ADDRESS(sort_max_row, COLUMN(comb_rank)), "") -> $S$40:$S$45 | U43: =IF(is_cat,RANK(comb_rank,INDIRECT(comb_rank_range),1),"") -> 1 | V43: =IF(is_cat, ADDRESS(sort_min_row, COLUMN(comb_rank_norm)) &":" & ADDRESS(ROW(), COLUMN(comb_rank_norm)), "") -> $U$40:$U$43 | W43: =IF(is_cat, comb_rank_norm + COUNTIF(INDIRECT(comb_rank_norm_run_range), comb_rank_norm)-1, "") -> 4 | X43: =IF(is_cat, header_row_id + comb_rank_unique, row_id) -> 52 | Y43: =IF(is_empty, "", INDEX($J:$J, MATCH(row_id, $X:$X, 0))) -> Retirement Fund | Z43: =IF(is_empty, "", IF(is_header, "Tracked", INDEX($K:$K, MATCH(row_id, $X:$X, 0)))) -> 0 | AA43: =IF(is_empty, "", IF(is_header, "Budget", INDEX($L:$L, MATCH(row_id, $X:$X, 0)))) -> 0 | AB43: =IF(is_empty, "", IF(is_header, "% Compl.", IFERROR(out_tracked / out_budget, "-"))) -> - | AC43: =IF(is_empty, "", IF(is_header, "Remaining", IF(out_budget - out_tracked > 0, out_budget - out_tracked, 0))) -> 0 | AD43: =IF(is_empty, "", IF(is_header, "Excess", IF(out_budget - out_tracked < 0, out_tracked - out_budget, 0))) -> 0
C44: {=IF(C43=-1,-1, IF(C43<income_max_row, C43+1, IF(C43=income_max_row, income_total_row, IF(C43=income_total_row, "/1", IF(C43="/1", expenses_header_row, IF(C43<expenses_max_row, C43+1, IF(C43=expenses_max_row, expenses_total_row, IF(C43=expenses_total_row, "/2", IF(C43="/2", savings_header_row, IF(C43<savings_max_row, C43+1, IF(C43=savings_max_row, savings_total_row, -1)))))))))))} -> 53 | D44: =IF(is_header,row_id, IF(NOT(is_empty),D43,-1)) -> 48 | E44: {=1*OR(row_id=income_header_row, row_id=expenses_header_row, row_id=savings_header_row)} -> 0 | F44: =1*NOT(OR(is_header, is_total, is_empty)) -> 1 | G44: {=1*OR(row_id=income_total_row, row_id=expenses_total_row, row_id=savings_total_row)} -> 0 | H44: =1*OR(row_id="/1", row_id="/2", row_id=-1) -> 0 | I44: {=IFERROR(INDEX('Budget Planning'!$C:$C, header_row_id),"")} -> Savings | J44: {=IFERROR(INDEX('Budget Planning'!$C:$C, row_id), "")} -> Sinking Fund Down Payment | K44: {=IF( OR(is_header, is_empty, selected_period=""), "", IF( is_total, IF( selected_period="Total Year", SUMPRODUCT( Tracking[Amount] * (Tracking[Type]=type) * (YEAR(Tracking[Effective Date])=selected_year) ), SUMPRODUCT( Tracking[Amount] * (Tracking[Type]=type) * (YEAR(Tracking[Effective Date])=selected_year) * (MONTH(Tracking[Effective Date])=selected_period) ) ), IF( selected_period="Total Year", SUMPRODUCT( Tracking[Amount] * (Tracking[Type]=type) * (Tracking[Category]=item) * (YEAR(Tracking[Effective Date])=selected_year) ), SUMPRODUCT( Tracking[Amount] * (Tracking[Type]=type) * (Tracking[Category]=item) * (YEAR(Tracking[Effective Date])=selected_year) * (MONTH(Tracking[Effective Date])=selected_period) ) ) ) )} -> 0 | L44: {=IF( OR(is_header, is_empty), "", INDEX( 'Budget Planning'!$E:$FA, row_id, MATCH( IF( selected_period = "Total Year", selected_year, DATE(selected_year, selected_period, 1) ), 'Budget Planning'!$E$10:$FA$10, 0 ) ) )} -> 0 | M44: {=IF( is_cat, IF( header_row_id = income_header_row, MATCH(income_min_row, $C:$C, 0), IF( header_row_id = expenses_header_row, MATCH(expenses_min_row, $C:$C, 0), IF( header_row_id = savings_header_row, MATCH(savings_min_row, $C:$C, 0), "" ) ) ), "" )} -> 40 | N44: {=IF( is_cat, IF( header_row_id = income_header_row, MATCH(income_max_row, $C:$C, 0), IF( header_row_id = expenses_header_row, MATCH(expenses_max_row, $C:$C, 0), IF( header_row_id = savings_header_row, MATCH(savings_max_row, $C:$C, 0), "" ) ) ), "" )} -> 45 | O44: =IF(is_cat, ADDRESS(sort_min_row, COLUMN(tracked)) &":" & ADDRESS(sort_max_row, COLUMN(tracked)), "") -> $K$40:$K$45 | P44: =IF(is_cat, RANK(tracked, INDIRECT(tracked_range), 0), "") -> 1 | Q44: =IF(is_cat, ADDRESS(sort_min_row, COLUMN(budget)) &":" & ADDRESS(sort_max_row, COLUMN(budget)), "") -> $L$40:$L$45 | R44: =IF(is_cat, RANK(budget, INDIRECT(budget_range), 0), "") -> 1 | S44: =IF(is_cat, _xlfn.NUMBERVALUE(tracked_rank & budget_rank), "") -> 11 | T44: =IF(is_cat, ADDRESS(sort_min_row, COLUMN(comb_rank)) &":" & ADDRESS(sort_max_row, COLUMN(comb_rank)), "") -> $S$40:$S$45 | U44: =IF(is_cat,RANK(comb_rank,INDIRECT(comb_rank_range),1),"") -> 1 | V44: =IF(is_cat, ADDRESS(sort_min_row, COLUMN(comb_rank_norm)) &":" & ADDRESS(ROW(), COLUMN(comb_rank_norm)), "") -> $U$40:$U$44 | W44: =IF(is_cat, comb_rank_norm + COUNTIF(INDIRECT(comb_rank_norm_run_range), comb_rank_norm)-1, "") -> 5 | X44: =IF(is_cat, header_row_id + comb_rank_unique, row_id) -> 53 | Y44: =IF(is_empty, "", INDEX($J:$J, MATCH(row_id, $X:$X, 0))) -> Sinking Fund Down Payment | Z44: =IF(is_empty, "", IF(is_header, "Tracked", INDEX($K:$K, MATCH(row_id, $X:$X, 0)))) -> 0 | AA44: =IF(is_empty, "", IF(is_header, "Budget", INDEX($L:$L, MATCH(row_id, $X:$X, 0)))) -> 0 | AB44: =IF(is_empty, "", IF(is_header, "% Compl.", IFERROR(out_tracked / out_budget, "-"))) -> - | AC44: =IF(is_empty, "", IF(is_header, "Remaining", IF(out_budget - out_tracked > 0, out_budget - out_tracked, 0))) -> 0 | AD44: =IF(is_empty, "", IF(is_header, "Excess", IF(out_budget - out_tracked < 0, out_tracked - out_budget, 0))) -> 0
C45: {=IF(C44=-1,-1, IF(C44<income_max_row, C44+1, IF(C44=income_max_row, income_total_row, IF(C44=income_total_row, "/1", IF(C44="/1", expenses_header_row, IF(C44<expenses_max_row, C44+1, IF(C44=expenses_max_row, expenses_total_row, IF(C44=expenses_total_row, "/2", IF(C44="/2", savings_header_row, IF(C44<savings_max_row, C44+1, IF(C44=savings_max_row, savings_total_row, -1)))))))))))} -> 54 | D45: =IF(is_header,row_id, IF(NOT(is_empty),D44,-1)) -> 48 | E45: {=1*OR(row_id=income_header_row, row_id=expenses_header_row, row_id=savings_header_row)} -> 0 | F45: =1*NOT(OR(is_header, is_total, is_empty)) -> 1 | G45: {=1*OR(row_id=income_total_row, row_id=expenses_total_row, row_id=savings_total_row)} -> 0 | H45: =1*OR(row_id="/1", row_id="/2", row_id=-1) -> 0 | I45: {=IFERROR(INDEX('Budget Planning'!$C:$C, header_row_id),"")} -> Savings | J45: {=IFERROR(INDEX('Budget Planning'!$C:$C, row_id), "")} -> Sinking Fund Future Payment | K45: {=IF( OR(is_header, is_empty, selected_period=""), "", IF( is_total, IF( selected_period="Total Year", SUMPRODUCT( Tracking[Amount] * (Tracking[Type]=type) * (YEAR(Tracking[Effective Date])=selected_year) ), SUMPRODUCT( Tracking[Amount] * (Tracking[Type]=type) * (YEAR(Tracking[Effective Date])=selected_year) * (MONTH(Tracking[Effective Date])=selected_period) ) ), IF( selected_period="Total Year", SUMPRODUCT( Tracking[Amount] * (Tracking[Type]=type) * (Tracking[Category]=item) * (YEAR(Tracking[Effective Date])=selected_year) ), SUMPRODUCT( Tracking[Amount] * (Tracking[Type]=type) * (Tracking[Category]=item) * (YEAR(Tracking[Effective Date])=selected_year) * (MONTH(Tracking[Effective Date])=selected_period) ) ) ) )} -> 0 | L45: {=IF( OR(is_header, is_empty), "", INDEX( 'Budget Planning'!$E:$FA, row_id, MATCH( IF( selected_period = "Total Year", selected_year, DATE(selected_year, selected_period, 1) ), 'Budget Planning'!$E$10:$FA$10, 0 ) ) )} -> 0 | M45: {=IF( is_cat, IF( header_row_id = income_header_row, MATCH(income_min_row, $C:$C, 0), IF( header_row_id = expenses_header_row, MATCH(expenses_min_row, $C:$C, 0), IF( header_row_id = savings_header_row, MATCH(savings_min_row, $C:$C, 0), "" ) ) ), "" )} -> 40 | N45: {=IF( is_cat, IF( header_row_id = income_header_row, MATCH(income_max_row, $C:$C, 0), IF( header_row_id = expenses_header_row, MATCH(expenses_max_row, $C:$C, 0), IF( header_row_id = savings_header_row, MATCH(savings_max_row, $C:$C, 0), "" ) ) ), "" )} -> 45 | O45: =IF(is_cat, ADDRESS(sort_min_row, COLUMN(tracked)) &":" & ADDRESS(sort_max_row, COLUMN(tracked)), "") -> $K$40:$K$45 | P45: =IF(is_cat, RANK(tracked, INDIRECT(tracked_range), 0), "") -> 1 | Q45: =IF(is_cat, ADDRESS(sort_min_row, COLUMN(budget)) &":" & ADDRESS(sort_max_row, COLUMN(budget)), "") -> $L$40:$L$45 | R45: =IF(is_cat, RANK(budget, INDIRECT(budget_range), 0), "") -> 1 | S45: =IF(is_cat, _xlfn.NUMBERVALUE(tracked_rank & budget_rank), "") -> 11 | T45: =IF(is_cat, ADDRESS(sort_min_row, COLUMN(comb_rank)) &":" & ADDRESS(sort_max_row, COLUMN(comb_rank)), "") -> $S$40:$S$45 | U45: =IF(is_cat,RANK(comb_rank,INDIRECT(comb_rank_range),1),"") -> 1 | V45: =IF(is_cat, ADDRESS(sort_min_row, COLUMN(comb_rank_norm)) &":" & ADDRESS(ROW(), COLUMN(comb_rank_norm)), "") -> $U$40:$U$45 | W45: =IF(is_cat, comb_rank_norm + COUNTIF(INDIRECT(comb_rank_norm_run_range), comb_rank_norm)-1, "") -> 6 | X45: =IF(is_cat, header_row_id + comb_rank_unique, row_id) -> 54 | Y45: =IF(is_empty, "", INDEX($J:$J, MATCH(row_id, $X:$X, 0))) -> Sinking Fund Future Payment | Z45: =IF(is_empty, "", IF(is_header, "Tracked", INDEX($K:$K, MATCH(row_id, $X:$X, 0)))) -> 0 | AA45: =IF(is_empty, "", IF(is_header, "Budget", INDEX($L:$L, MATCH(row_id, $X:$X, 0)))) -> 0 | AB45: =IF(is_empty, "", IF(is_header, "% Compl.", IFERROR(out_tracked / out_budget, "-"))) -> - | AC45: =IF(is_empty, "", IF(is_header, "Remaining", IF(out_budget - out_tracked > 0, out_budget - out_tracked, 0))) -> 0 | AD45: =IF(is_empty, "", IF(is_header, "Excess", IF(out_budget - out_tracked < 0, out_tracked - out_budget, 0))) -> 0
C46: {=IF(C45=-1,-1, IF(C45<income_max_row, C45+1, IF(C45=income_max_row, income_total_row, IF(C45=income_total_row, "/1", IF(C45="/1", expenses_header_row, IF(C45<expenses_max_row, C45+1, IF(C45=expenses_max_row, expenses_total_row, IF(C45=expenses_total_row, "/2", IF(C45="/2", savings_header_row, IF(C45<savings_max_row, C45+1, IF(C45=savings_max_row, savings_total_row, -1)))))))))))} -> 65 | D46: =IF(is_header,row_id, IF(NOT(is_empty),D45,-1)) -> 48 | E46: {=1*OR(row_id=income_header_row, row_id=expenses_header_row, row_id=savings_header_row)} -> 0 | F46: =1*NOT(OR(is_header, is_total, is_empty)) -> 0 | G46: {=1*OR(row_id=income_total_row, row_id=expenses_total_row, row_id=savings_total_row)} -> 1 | H46: =1*OR(row_id="/1", row_id="/2", row_id=-1) -> 0 | I46: {=IFERROR(INDEX('Budget Planning'!$C:$C, header_row_id),"")} -> Savings | J46: {=IFERROR(INDEX('Budget Planning'!$C:$C, row_id), "")} -> Total | K46: {=IF( OR(is_header, is_empty, selected_period=""), "", IF( is_total, IF( selected_period="Total Year", SUMPRODUCT( Tracking[Amount] * (Tracking[Type]=type) * (YEAR(Tracking[Effective Date])=selected_year) ), SUMPRODUCT( Tracking[Amount] * (Tracking[Type]=type) * (YEAR(Tracking[Effective Date])=selected_year) * (MONTH(Tracking[Effective Date])=selected_period) ) ), IF( selected_period="Total Year", SUMPRODUCT( Tracking[Amount] * (Tracking[Type]=type) * (Tracking[Category]=item) * (YEAR(Tracking[Effective Date])=selected_year) ), SUMPRODUCT( Tracking[Amount] * (Tracking[Type]=type) * (Tracking[Category]=item) * (YEAR(Tracking[Effective Date])=selected_year) * (MONTH(Tracking[Effective Date])=selected_period) ) ) ) )} -> 0 | L46: {=IF( OR(is_header, is_empty), "", INDEX( 'Budget Planning'!$E:$FA, row_id, MATCH( IF( selected_period = "Total Year", selected_year, DATE(selected_year, selected_period, 1) ), 'Budget Planning'!$E$10:$FA$10, 0 ) ) )} -> 0 | M46: {=IF( is_cat, IF( header_row_id = income_header_row, MATCH(income_min_row, $C:$C, 0), IF( header_row_id = expenses_header_row, MATCH(expenses_min_row, $C:$C, 0), IF( header_row_id = savings_header_row, MATCH(savings_min_row, $C:$C, 0), "" ) ) ), "" )} | N46: {=IF( is_cat, IF( header_row_id = income_header_row, MATCH(income_max_row, $C:$C, 0), IF( header_row_id = expenses_header_row, MATCH(expenses_max_row, $C:$C, 0), IF( header_row_id = savings_header_row, MATCH(savings_max_row, $C:$C, 0), "" ) ) ), "" )} | O46: =IF(is_cat, ADDRESS(sort_min_row, COLUMN(tracked)) &":" & ADDRESS(sort_max_row, COLUMN(tracked)), "") | P46: =IF(is_cat, RANK(tracked, INDIRECT(tracked_range), 0), "") | Q46: =IF(is_cat, ADDRESS(sort_min_row, COLUMN(budget)) &":" & ADDRESS(sort_max_row, COLUMN(budget)), "") | R46: =IF(is_cat, RANK(budget, INDIRECT(budget_range), 0), "") | S46: =IF(is_cat, _xlfn.NUMBERVALUE(tracked_rank & budget_rank), "") | T46: =IF(is_cat, ADDRESS(sort_min_row, COLUMN(comb_rank)) &":" & ADDRESS(sort_max_row, COLUMN(comb_rank)), "") | U46: =IF(is_cat,RANK(comb_rank,INDIRECT(comb_rank_range),1),"") | V46: =IF(is_cat, ADDRESS(sort_min_row, COLUMN(comb_rank_norm)) &":" & ADDRESS(ROW(), COLUMN(comb_rank_norm)), "") | W46: =IF(is_cat, comb_rank_norm + COUNTIF(INDIRECT(comb_rank_norm_run_range), comb_rank_norm)-1, "") | X46: =IF(is_cat, header_row_id + comb_rank_unique, row_id) -> 65 | Y46: =IF(is_empty, "", INDEX($J:$J, MATCH(row_id, $X:$X, 0))) -> Total | Z46: =IF(is_empty, "", IF(is_header, "Tracked", INDEX($K:$K, MATCH(row_id, $X:$X, 0)))) -> 0 | AA46: =IF(is_empty, "", IF(is_header, "Budget", INDEX($L:$L, MATCH(row_id, $X:$X, 0)))) -> 0 | AB46: =IF(is_empty, "", IF(is_header, "% Compl.", IFERROR(out_tracked / out_budget, "-"))) -> - | AC46: =IF(is_empty, "", IF(is_header, "Remaining", IF(out_budget - out_tracked > 0, out_budget - out_tracked, 0))) -> 0 | AD46: =IF(is_empty, "", IF(is_header, "Excess", IF(out_budget - out_tracked < 0, out_tracked - out_budget, 0))) -> 0
C47: {=IF(C46=-1,-1, IF(C46<income_max_row, C46+1, IF(C46=income_max_row, income_total_row, IF(C46=income_total_row, "/1", IF(C46="/1", expenses_header_row, IF(C46<expenses_max_row, C46+1, IF(C46=expenses_max_row, expenses_total_row, IF(C46=expenses_total_row, "/2", IF(C46="/2", savings_header_row, IF(C46<savings_max_row, C46+1, IF(C46=savings_max_row, savings_total_row, -1)))))))))))} -> -1 | D47: =IF(is_header,row_id, IF(NOT(is_empty),D46,-1)) -> -1 | E47: {=1*OR(row_id=income_header_row, row_id=expenses_header_row, row_id=savings_header_row)} -> 0 | F47: =1*NOT(OR(is_header, is_total, is_empty)) -> 0 | G47: {=1*OR(row_id=income_total_row, row_id=expenses_total_row, row_id=savings_total_row)} -> 0 | H47: =1*OR(row_id="/1", row_id="/2", row_id=-1) -> 1 | I47: {=IFERROR(INDEX('Budget Planning'!$C:$C, header_row_id),"")} | J47: {=IFERROR(INDEX('Budget Planning'!$C:$C, row_id), "")} | K47: {=IF( OR(is_header, is_empty, selected_period=""), "", IF( is_total, IF( selected_period="Total Year", SUMPRODUCT( Tracking[Amount] * (Tracking[Type]=type) * (YEAR(Tracking[Effective Date])=selected_year) ), SUMPRODUCT( Tracking[Amount] * (Tracking[Type]=type) * (YEAR(Tracking[Effective Date])=selected_year) * (MONTH(Tracking[Effective Date])=selected_period) ) ), IF( selected_period="Total Year", SUMPRODUCT( Tracking[Amount] * (Tracking[Type]=type) * (Tracking[Category]=item) * (YEAR(Tracking[Effective Date])=selected_year) ), SUMPRODUCT( Tracking[Amount] * (Tracking[Type]=type) * (Tracking[Category]=item) * (YEAR(Tracking[Effective Date])=selected_year) * (MONTH(Tracking[Effective Date])=selected_period) ) ) ) )} | L47: {=IF( OR(is_header, is_empty), "", INDEX( 'Budget Planning'!$E:$FA, row_id, MATCH( IF( selected_period = "Total Year", selected_year, DATE(selected_year, selected_period, 1) ), 'Budget Planning'!$E$10:$FA$10, 0 ) ) )} | M47: {=IF( is_cat, IF( header_row_id = income_header_row, MATCH(income_min_row, $C:$C, 0), IF( header_row_id = expenses_header_row, MATCH(expenses_min_row, $C:$C, 0), IF( header_row_id = savings_header_row, MATCH(savings_min_row, $C:$C, 0), "" ) ) ), "" )} | N47: {=IF( is_cat, IF( header_row_id = income_header_row, MATCH(income_max_row, $C:$C, 0), IF( header_row_id = expenses_header_row, MATCH(expenses_max_row, $C:$C, 0), IF( header_row_id = savings_header_row, MATCH(savings_max_row, $C:$C, 0), "" ) ) ), "" )} | O47: =IF(is_cat, ADDRESS(sort_min_row, COLUMN(tracked)) &":" & ADDRESS(sort_max_row, COLUMN(tracked)), "") | P47: =IF(is_cat, RANK(tracked, INDIRECT(tracked_range), 0), "") | Q47: =IF(is_cat, ADDRESS(sort_min_row, COLUMN(budget)) &":" & ADDRESS(sort_max_row, COLUMN(budget)), "") | R47: =IF(is_cat, RANK(budget, INDIRECT(budget_range), 0), "") | S47: =IF(is_cat, _xlfn.NUMBERVALUE(tracked_rank & budget_rank), "") | T47: =IF(is_cat, ADDRESS(sort_min_row, COLUMN(comb_rank)) &":" & ADDRESS(sort_max_row, COLUMN(comb_rank)), "") | U47: =IF(is_cat,RANK(comb_rank,INDIRECT(comb_rank_range),1),"") | V47: =IF(is_cat, ADDRESS(sort_min_row, COLUMN(comb_rank_norm)) &":" & ADDRESS(ROW(), COLUMN(comb_rank_norm)), "") | W47: =IF(is_cat, comb_rank_norm + COUNTIF(INDIRECT(comb_rank_norm_run_range), comb_rank_norm)-1, "") | X47: =IF(is_cat, header_row_id + comb_rank_unique, row_id) -> -1 | Y47: =IF(is_empty, "", INDEX($J:$J, MATCH(row_id, $X:$X, 0))) | Z47: =IF(is_empty, "", IF(is_header, "Tracked", INDEX($K:$K, MATCH(row_id, $X:$X, 0)))) | AA47: =IF(is_empty, "", IF(is_header, "Budget", INDEX($L:$L, MATCH(row_id, $X:$X, 0)))) | AB47: =IF(is_empty, "", IF(is_header, "% Compl.", IFERROR(out_tracked / out_budget, "-"))) | AC47: =IF(is_empty, "", IF(is_header, "Remaining", IF(out_budget - out_tracked > 0, out_budget - out_tracked, 0))) | AD47: =IF(is_empty, "", IF(is_header, "Excess", IF(out_budget - out_tracked < 0, out_tracked - out_budget, 0)))
C48: {=IF(C47=-1,-1, IF(C47<income_max_row, C47+1, IF(C47=income_max_row, income_total_row, IF(C47=income_total_row, "/1", IF(C47="/1", expenses_header_row, IF(C47<expenses_max_row, C47+1, IF(C47=expenses_max_row, expenses_total_row, IF(C47=expenses_total_row, "/2", IF(C47="/2", savings_header_row, IF(C47<savings_max_row, C47+1, IF(C47=savings_max_row, savings_total_row, -1)))))))))))} -> -1 | D48: =IF(is_header,row_id, IF(NOT(is_empty),D47,-1)) -> -1 | E48: {=1*OR(row_id=income_header_row, row_id=expenses_header_row, row_id=savings_header_row)} -> 0 | F48: =1*NOT(OR(is_header, is_total, is_empty)) -> 0 | G48: {=1*OR(row_id=income_total_row, row_id=expenses_total_row, row_id=savings_total_row)} -> 0 | H48: =1*OR(row_id="/1", row_id="/2", row_id=-1) -> 1 | I48: {=IFERROR(INDEX('Budget Planning'!$C:$C, header_row_id),"")} | J48: {=IFERROR(INDEX('Budget Planning'!$C:$C, row_id), "")} | K48: {=IF( OR(is_header, is_empty, selected_period=""), "", IF( is_total, IF( selected_period="Total Year", SUMPRODUCT( Tracking[Amount] * (Tracking[Type]=type) * (YEAR(Tracking[Effective Date])=selected_year) ), SUMPRODUCT( Tracking[Amount] * (Tracking[Type]=type) * (YEAR(Tracking[Effective Date])=selected_year) * (MONTH(Tracking[Effective Date])=selected_period) ) ), IF( selected_period="Total Year", SUMPRODUCT( Tracking[Amount] * (Tracking[Type]=type) * (Tracking[Category]=item) * (YEAR(Tracking[Effective Date])=selected_year) ), SUMPRODUCT( Tracking[Amount] * (Tracking[Type]=type) * (Tracking[Category]=item) * (YEAR(Tracking[Effective Date])=selected_year) * (MONTH(Tracking[Effective Date])=selected_period) ) ) ) )} | L48: {=IF( OR(is_header, is_empty), "", INDEX( 'Budget Planning'!$E:$FA, row_id, MATCH( IF( selected_period = "Total Year", selected_year, DATE(selected_year, selected_period, 1) ), 'Budget Planning'!$E$10:$FA$10, 0 ) ) )} | M48: {=IF( is_cat, IF( header_row_id = income_header_row, MATCH(income_min_row, $C:$C, 0), IF( header_row_id = expenses_header_row, MATCH(expenses_min_row, $C:$C, 0), IF( header_row_id = savings_header_row, MATCH(savings_min_row, $C:$C, 0), "" ) ) ), "" )} | N48: {=IF( is_cat, IF( header_row_id = income_header_row, MATCH(income_max_row, $C:$C, 0), IF( header_row_id = expenses_header_row, MATCH(expenses_max_row, $C:$C, 0), IF( header_row_id = savings_header_row, MATCH(savings_max_row, $C:$C, 0), "" ) ) ), "" )} | O48: =IF(is_cat, ADDRESS(sort_min_row, COLUMN(tracked)) &":" & ADDRESS(sort_max_row, COLUMN(tracked)), "") | P48: =IF(is_cat, RANK(tracked, INDIRECT(tracked_range), 0), "") | Q48: =IF(is_cat, ADDRESS(sort_min_row, COLUMN(budget)) &":" & ADDRESS(sort_max_row, COLUMN(budget)), "") | R48: =IF(is_cat, RANK(budget, INDIRECT(budget_range), 0), "") | S48: =IF(is_cat, _xlfn.NUMBERVALUE(tracked_rank & budget_rank), "") | T48: =IF(is_cat, ADDRESS(sort_min_row, COLUMN(comb_rank)) &":" & ADDRESS(sort_max_row, COLUMN(comb_rank)), "") | U48: =IF(is_cat,RANK(comb_rank,INDIRECT(comb_rank_range),1),"") | V48: =IF(is_cat, ADDRESS(sort_min_row, COLUMN(comb_rank_norm)) &":" & ADDRESS(ROW(), COLUMN(comb_rank_norm)), "") | W48: =IF(is_cat, comb_rank_norm + COUNTIF(INDIRECT(comb_rank_norm_run_range), comb_rank_norm)-1, "") | X48: =IF(is_cat, header_row_id + comb_rank_unique, row_id) -> -1 | Y48: =IF(is_empty, "", INDEX($J:$J, MATCH(row_id, $X:$X, 0))) | Z48: =IF(is_empty, "", IF(is_header, "Tracked", INDEX($K:$K, MATCH(row_id, $X:$X, 0)))) | AA48: =IF(is_empty, "", IF(is_header, "Budget", INDEX($L:$L, MATCH(row_id, $X:$X, 0)))) | AB48: =IF(is_empty, "", IF(is_header, "% Compl.", IFERROR(out_tracked / out_budget, "-"))) | AC48: =IF(is_empty, "", IF(is_header, "Remaining", IF(out_budget - out_tracked > 0, out_budget - out_tracked, 0))) | AD48: =IF(is_empty, "", IF(is_header, "Excess", IF(out_budget - out_tracked < 0, out_tracked - out_budget, 0)))
C49: {=IF(C48=-1,-1, IF(C48<income_max_row, C48+1, IF(C48=income_max_row, income_total_row, IF(C48=income_total_row, "/1", IF(C48="/1", expenses_header_row, IF(C48<expenses_max_row, C48+1, IF(C48=expenses_max_row, expenses_total_row, IF(C48=expenses_total_row, "/2", IF(C48="/2", savings_header_row, IF(C48<savings_max_row, C48+1, IF(C48=savings_max_row, savings_total_row, -1)))))))))))} -> -1 | D49: =IF(is_header,row_id, IF(NOT(is_empty),D48,-1)) -> -1 | E49: TRUE | F49: =1*NOT(OR(is_header, is_total, is_empty)) -> 0 | G49: {=1*OR(row_id=income_total_row, row_id=expenses_total_row, row_id=savings_total_row)} -> 0 | H49: =1*OR(row_id="/1", row_id="/2", row_id=-1) -> 1 | I49: {=IFERROR(INDEX('Budget Planning'!$C:$C, header_row_id),"")} | J49: {=IFERROR(INDEX('Budget Planning'!$C:$C, row_id), "")} | K49: {=IF( OR(is_header, is_empty, selected_period=""), "", IF( is_total, IF( selected_period="Total Year", SUMPRODUCT( Tracking[Amount] * (Tracking[Type]=type) * (YEAR(Tracking[Effective Date])=selected_year) ), SUMPRODUCT( Tracking[Amount] * (Tracking[Type]=type) * (YEAR(Tracking[Effective Date])=selected_year) * (MONTH(Tracking[Effective Date])=selected_period) ) ), IF( selected_period="Total Year", SUMPRODUCT( Tracking[Amount] * (Tracking[Type]=type) * (Tracking[Category]=item) * (YEAR(Tracking[Effective Date])=selected_year) ), SUMPRODUCT( Tracking[Amount] * (Tracking[Type]=type) * (Tracking[Category]=item) * (YEAR(Tracking[Effective Date])=selected_year) * (MONTH(Tracking[Effective Date])=selected_period) ) ) ) )} | L49: {=IF( OR(is_header, is_empty), "", INDEX( 'Budget Planning'!$E:$FA, row_id, MATCH( IF( selected_period = "Total Year", selected_year, DATE(selected_year, selected_period, 1) ), 'Budget Planning'!$E$10:$FA$10, 0 ) ) )} | M49: {=IF( is_cat, IF( header_row_id = income_header_row, MATCH(income_min_row, $C:$C, 0), IF( header_row_id = expenses_header_row, MATCH(expenses_min_row, $C:$C, 0), IF( header_row_id = savings_header_row, MATCH(savings_min_row, $C:$C, 0), "" ) ) ), "" )} | N49: {=IF( is_cat, IF( header_row_id = income_header_row, MATCH(income_max_row, $C:$C, 0), IF( header_row_id = expenses_header_row, MATCH(expenses_max_row, $C:$C, 0), IF( header_row_id = savings_header_row, MATCH(savings_max_row, $C:$C, 0), "" ) ) ), "" )} | O49: =IF(is_cat, ADDRESS(sort_min_row, COLUMN(tracked)) &":" & ADDRESS(sort_max_row, COLUMN(tracked)), "") | P49: =IF(is_cat, RANK(tracked, INDIRECT(tracked_range), 0), "") | Q49: =IF(is_cat, ADDRESS(sort_min_row, COLUMN(budget)) &":" & ADDRESS(sort_max_row, COLUMN(budget)), "") | R49: =IF(is_cat, RANK(budget, INDIRECT(budget_range), 0), "") | S49: =IF(is_cat, _xlfn.NUMBERVALUE(tracked_rank & budget_rank), "") | T49: =IF(is_cat, ADDRESS(sort_min_row, COLUMN(comb_rank)) &":" & ADDRESS(sort_max_row, COLUMN(comb_rank)), "") | U49: =IF(is_cat,RANK(comb_rank,INDIRECT(comb_rank_range),1),"") | V49: =IF(is_cat, ADDRESS(sort_min_row, COLUMN(comb_rank_norm)) &":" & ADDRESS(ROW(), COLUMN(comb_rank_norm)), "") | W49: =IF(is_cat, comb_rank_norm + COUNTIF(INDIRECT(comb_rank_norm_run_range), comb_rank_norm)-1, "") | X49: =IF(is_cat, header_row_id + comb_rank_unique, row_id) -> -1 | Y49: =IF(is_empty, "", INDEX($J:$J, MATCH(row_id, $X:$X, 0))) | Z49: =IF(is_empty, "", IF(is_header, "Tracked", INDEX($K:$K, MATCH(row_id, $X:$X, 0)))) | AA49: =IF(is_empty, "", IF(is_header, "Budget", INDEX($L:$L, MATCH(row_id, $X:$X, 0)))) | AB49: =IF(is_empty, "", IF(is_header, "% Compl.", IFERROR(out_tracked / out_budget, "-"))) | AC49: =IF(is_empty, "", IF(is_header, "Remaining", IF(out_budget - out_tracked > 0, out_budget - out_tracked, 0))) | AD49: =IF(is_empty, "", IF(is_header, "Excess", IF(out_budget - out_tracked < 0, out_tracked - out_budget, 0)))
C50: {=IF(C49=-1,-1, IF(C49<income_max_row, C49+1, IF(C49=income_max_row, income_total_row, IF(C49=income_total_row, "/1", IF(C49="/1", expenses_header_row, IF(C49<expenses_max_row, C49+1, IF(C49=expenses_max_row, expenses_total_row, IF(C49=expenses_total_row, "/2", IF(C49="/2", savings_header_row, IF(C49<savings_max_row, C49+1, IF(C49=savings_max_row, savings_total_row, -1)))))))))))} -> -1 | D50: =IF(is_header,row_id, IF(NOT(is_empty),D49,-1)) -> -1 | E50: TRUE | F50: =1*NOT(OR(is_header, is_total, is_empty)) -> 0 | G50: {=1*OR(row_id=income_total_row, row_id=expenses_total_row, row_id=savings_total_row)} -> 0 | H50: =1*OR(row_id="/1", row_id="/2", row_id=-1) -> 1 | I50: {=IFERROR(INDEX('Budget Planning'!$C:$C, header_row_id),"")} | J50: {=IFERROR(INDEX('Budget Planning'!$C:$C, row_id), "")} | K50: {=IF( OR(is_header, is_empty, selected_period=""), "", IF( is_total, IF( selected_period="Total Year", SUMPRODUCT( Tracking[Amount] * (Tracking[Type]=type) * (YEAR(Tracking[Effective Date])=selected_year) ), SUMPRODUCT( Tracking[Amount] * (Tracking[Type]=type) * (YEAR(Tracking[Effective Date])=selected_year) * (MONTH(Tracking[Effective Date])=selected_period) ) ), IF( selected_period="Total Year", SUMPRODUCT( Tracking[Amount] * (Tracking[Type]=type) * (Tracking[Category]=item) * (YEAR(Tracking[Effective Date])=selected_year) ), SUMPRODUCT( Tracking[Amount] * (Tracking[Type]=type) * (Tracking[Category]=item) * (YEAR(Tracking[Effective Date])=selected_year) * (MONTH(Tracking[Effective Date])=selected_period) ) ) ) )} | L50: {=IF( OR(is_header, is_empty), "", INDEX( 'Budget Planning'!$E:$FA, row_id, MATCH( IF( selected_period = "Total Year", selected_year, DATE(selected_year, selected_period, 1) ), 'Budget Planning'!$E$10:$FA$10, 0 ) ) )} | M50: {=IF( is_cat, IF( header_row_id = income_header_row, MATCH(income_min_row, $C:$C, 0), IF( header_row_id = expenses_header_row, MATCH(expenses_min_row, $C:$C, 0), IF( header_row_id = savings_header_row, MATCH(savings_min_row, $C:$C, 0), "" ) ) ), "" )} | N50: {=IF( is_cat, IF( header_row_id = income_header_row, MATCH(income_max_row, $C:$C, 0), IF( header_row_id = expenses_header_row, MATCH(expenses_max_row, $C:$C, 0), IF( header_row_id = savings_header_row, MATCH(savings_max_row, $C:$C, 0), "" ) ) ), "" )} | O50: =IF(is_cat, ADDRESS(sort_min_row, COLUMN(tracked)) &":" & ADDRESS(sort_max_row, COLUMN(tracked)), "") | P50: =IF(is_cat, RANK(tracked, INDIRECT(tracked_range), 0), "") | Q50: =IF(is_cat, ADDRESS(sort_min_row, COLUMN(budget)) &":" & ADDRESS(sort_max_row, COLUMN(budget)), "") | R50: =IF(is_cat, RANK(budget, INDIRECT(budget_range), 0), "") | S50: =IF(is_cat, _xlfn.NUMBERVALUE(tracked_rank & budget_rank), "") | T50: =IF(is_cat, ADDRESS(sort_min_row, COLUMN(comb_rank)) &":" & ADDRESS(sort_max_row, COLUMN(comb_rank)), "") | U50: =IF(is_cat,RANK(comb_rank,INDIRECT(comb_rank_range),1),"") | V50: =IF(is_cat, ADDRESS(sort_min_row, COLUMN(comb_rank_norm)) &":" & ADDRESS(ROW(), COLUMN(comb_rank_norm)), "") | W50: =IF(is_cat, comb_rank_norm + COUNTIF(INDIRECT(comb_rank_norm_run_range), comb_rank_norm)-1, "") | X50: =IF(is_cat, header_row_id + comb_rank_unique, row_id) -> -1 | Y50: =IF(is_empty, "", INDEX($J:$J, MATCH(row_id, $X:$X, 0))) | Z50: =IF(is_empty, "", IF(is_header, "Tracked", INDEX($K:$K, MATCH(row_id, $X:$X, 0)))) | AA50: =IF(is_empty, "", IF(is_header, "Budget", INDEX($L:$L, MATCH(row_id, $X:$X, 0)))) | AB50: =IF(is_empty, "", IF(is_header, "% Compl.", IFERROR(out_tracked / out_budget, "-"))) | AC50: =IF(is_empty, "", IF(is_header, "Remaining", IF(out_budget - out_tracked > 0, out_budget - out_tracked, 0))) | AD50: =IF(is_empty, "", IF(is_header, "Excess", IF(out_budget - out_tracked < 0, out_tracked - out_budget, 0)))
C51: {=IF(C50=-1,-1, IF(C50<income_max_row, C50+1, IF(C50=income_max_row, income_total_row, IF(C50=income_total_row, "/1", IF(C50="/1", expenses_header_row, IF(C50<expenses_max_row, C50+1, IF(C50=expenses_max_row, expenses_total_row, IF(C50=expenses_total_row, "/2", IF(C50="/2", savings_header_row, IF(C50<savings_max_row, C50+1, IF(C50=savings_max_row, savings_total_row, -1)))))))))))} -> -1 | D51: =IF(is_header,row_id, IF(NOT(is_empty),D50,-1)) -> -1 | E51: TRUE | F51: =1*NOT(OR(is_header, is_total, is_empty)) -> 0 | G51: {=1*OR(row_id=income_total_row, row_id=expenses_total_row, row_id=savings_total_row)} -> 0 | H51: =1*OR(row_id="/1", row_id="/2", row_id=-1) -> 1 | I51: {=IFERROR(INDEX('Budget Planning'!$C:$C, header_row_id),"")} | J51: {=IFERROR(INDEX('Budget Planning'!$C:$C, row_id), "")} | K51: {=IF( OR(is_header, is_empty, selected_period=""), "", IF( is_total, IF( selected_period="Total Year", SUMPRODUCT( Tracking[Amount] * (Tracking[Type]=type) * (YEAR(Tracking[Effective Date])=selected_year) ), SUMPRODUCT( Tracking[Amount] * (Tracking[Type]=type) * (YEAR(Tracking[Effective Date])=selected_year) * (MONTH(Tracking[Effective Date])=selected_period) ) ), IF( selected_period="Total Year", SUMPRODUCT( Tracking[Amount] * (Tracking[Type]=type) * (Tracking[Category]=item) * (YEAR(Tracking[Effective Date])=selected_year) ), SUMPRODUCT( Tracking[Amount] * (Tracking[Type]=type) * (Tracking[Category]=item) * (YEAR(Tracking[Effective Date])=selected_year) * (MONTH(Tracking[Effective Date])=selected_period) ) ) ) )} | L51: {=IF( OR(is_header, is_empty), "", INDEX( 'Budget Planning'!$E:$FA, row_id, MATCH( IF( selected_period = "Total Year", selected_year, DATE(selected_year, selected_period, 1) ), 'Budget Planning'!$E$10:$FA$10, 0 ) ) )} | M51: {=IF( is_cat, IF( header_row_id = income_header_row, MATCH(income_min_row, $C:$C, 0), IF( header_row_id = expenses_header_row, MATCH(expenses_min_row, $C:$C, 0), IF( header_row_id = savings_header_row, MATCH(savings_min_row, $C:$C, 0), "" ) ) ), "" )} | N51: {=IF( is_cat, IF( header_row_id = income_header_row, MATCH(income_max_row, $C:$C, 0), IF( header_row_id = expenses_header_row, MATCH(expenses_max_row, $C:$C, 0), IF( header_row_id = savings_header_row, MATCH(savings_max_row, $C:$C, 0), "" ) ) ), "" )} | O51: =IF(is_cat, ADDRESS(sort_min_row, COLUMN(tracked)) &":" & ADDRESS(sort_max_row, COLUMN(tracked)), "") | P51: =IF(is_cat, RANK(tracked, INDIRECT(tracked_range), 0), "") | Q51: =IF(is_cat, ADDRESS(sort_min_row, COLUMN(budget)) &":" & ADDRESS(sort_max_row, COLUMN(budget)), "") | R51: =IF(is_cat, RANK(budget, INDIRECT(budget_range), 0), "") | S51: =IF(is_cat, _xlfn.NUMBERVALUE(tracked_rank & budget_rank), "") | T51: =IF(is_cat, ADDRESS(sort_min_row, COLUMN(comb_rank)) &":" & ADDRESS(sort_max_row, COLUMN(comb_rank)), "") | U51: =IF(is_cat,RANK(comb_rank,INDIRECT(comb_rank_range),1),"") | V51: =IF(is_cat, ADDRESS(sort_min_row, COLUMN(comb_rank_norm)) &":" & ADDRESS(ROW(), COLUMN(comb_rank_norm)), "") | W51: =IF(is_cat, comb_rank_norm + COUNTIF(INDIRECT(comb_rank_norm_run_range), comb_rank_norm)-1, "") | X51: =IF(is_cat, header_row_id + comb_rank_unique, row_id) -> -1 | Y51: =IF(is_empty, "", INDEX($J:$J, MATCH(row_id, $X:$X, 0))) | Z51: =IF(is_empty, "", IF(is_header, "Tracked", INDEX($K:$K, MATCH(row_id, $X:$X, 0)))) | AA51: =IF(is_empty, "", IF(is_header, "Budget", INDEX($L:$L, MATCH(row_id, $X:$X, 0)))) | AB51: =IF(is_empty, "", IF(is_header, "% Compl.", IFERROR(out_tracked / out_budget, "-"))) | AC51: =IF(is_empty, "", IF(is_header, "Remaining", IF(out_budget - out_tracked > 0, out_budget - out_tracked, 0))) | AD51: =IF(is_empty, "", IF(is_header, "Excess", IF(out_budget - out_tracked < 0, out_tracked - out_budget, 0)))
C52: {=IF(C51=-1,-1, IF(C51<income_max_row, C51+1, IF(C51=income_max_row, income_total_row, IF(C51=income_total_row, "/1", IF(C51="/1", expenses_header_row, IF(C51<expenses_max_row, C51+1, IF(C51=expenses_max_row, expenses_total_row, IF(C51=expenses_total_row, "/2", IF(C51="/2", savings_header_row, IF(C51<savings_max_row, C51+1, IF(C51=savings_max_row, savings_total_row, -1)))))))))))} -> -1 | D52: =IF(is_header,row_id, IF(NOT(is_empty),D51,-1)) -> -1 | E52: TRUE | F52: =1*NOT(OR(is_header, is_total, is_empty)) -> 0 | G52: {=1*OR(row_id=income_total_row, row_id=expenses_total_row, row_id=savings_total_row)} -> 0 | H52: =1*OR(row_id="/1", row_id="/2", row_id=-1) -> 1 | I52: {=IFERROR(INDEX('Budget Planning'!$C:$C, header_row_id),"")} | J52: {=IFERROR(INDEX('Budget Planning'!$C:$C, row_id), "")} | K52: {=IF( OR(is_header, is_empty, selected_period=""), "", IF( is_total, IF( selected_period="Total Year", SUMPRODUCT( Tracking[Amount] * (Tracking[Type]=type) * (YEAR(Tracking[Effective Date])=selected_year) ), SUMPRODUCT( Tracking[Amount] * (Tracking[Type]=type) * (YEAR(Tracking[Effective Date])=selected_year) * (MONTH(Tracking[Effective Date])=selected_period) ) ), IF( selected_period="Total Year", SUMPRODUCT( Tracking[Amount] * (Tracking[Type]=type) * (Tracking[Category]=item) * (YEAR(Tracking[Effective Date])=selected_year) ), SUMPRODUCT( Tracking[Amount] * (Tracking[Type]=type) * (Tracking[Category]=item) * (YEAR(Tracking[Effective Date])=selected_year) * (MONTH(Tracking[Effective Date])=selected_period) ) ) ) )} | L52: {=IF( OR(is_header, is_empty), "", INDEX( 'Budget Planning'!$E:$FA, row_id, MATCH( IF( selected_period = "Total Year", selected_year, DATE(selected_year, selected_period, 1) ), 'Budget Planning'!$E$10:$FA$10, 0 ) ) )} | M52: {=IF( is_cat, IF( header_row_id = income_header_row, MATCH(income_min_row, $C:$C, 0), IF( header_row_id = expenses_header_row, MATCH(expenses_min_row, $C:$C, 0), IF( header_row_id = savings_header_row, MATCH(savings_min_row, $C:$C, 0), "" ) ) ), "" )} | N52: {=IF( is_cat, IF( header_row_id = income_header_row, MATCH(income_max_row, $C:$C, 0), IF( header_row_id = expenses_header_row, MATCH(expenses_max_row, $C:$C, 0), IF( header_row_id = savings_header_row, MATCH(savings_max_row, $C:$C, 0), "" ) ) ), "" )} | O52: =IF(is_cat, ADDRESS(sort_min_row, COLUMN(tracked)) &":" & ADDRESS(sort_max_row, COLUMN(tracked)), "") | P52: =IF(is_cat, RANK(tracked, INDIRECT(tracked_range), 0), "") | Q52: =IF(is_cat, ADDRESS(sort_min_row, COLUMN(budget)) &":" & ADDRESS(sort_max_row, COLUMN(budget)), "") | R52: =IF(is_cat, RANK(budget, INDIRECT(budget_range), 0), "") | S52: =IF(is_cat, _xlfn.NUMBERVALUE(tracked_rank & budget_rank), "") | T52: =IF(is_cat, ADDRESS(sort_min_row, COLUMN(comb_rank)) &":" & ADDRESS(sort_max_row, COLUMN(comb_rank)), "") | U52: =IF(is_cat,RANK(comb_rank,INDIRECT(comb_rank_range),1),"") | V52: =IF(is_cat, ADDRESS(sort_min_row, COLUMN(comb_rank_norm)) &":" & ADDRESS(ROW(), COLUMN(comb_rank_norm)), "") | W52: =IF(is_cat, comb_rank_norm + COUNTIF(INDIRECT(comb_rank_norm_run_range), comb_rank_norm)-1, "") | X52: =IF(is_cat, header_row_id + comb_rank_unique, row_id) -> -1 | Y52: =IF(is_empty, "", INDEX($J:$J, MATCH(row_id, $X:$X, 0))) | Z52: =IF(is_empty, "", IF(is_header, "Tracked", INDEX($K:$K, MATCH(row_id, $X:$X, 0)))) | AA52: =IF(is_empty, "", IF(is_header, "Budget", INDEX($L:$L, MATCH(row_id, $X:$X, 0)))) | AB52: =IF(is_empty, "", IF(is_header, "% Compl.", IFERROR(out_tracked / out_budget, "-"))) | AC52: =IF(is_empty, "", IF(is_header, "Remaining", IF(out_budget - out_tracked > 0, out_budget - out_tracked, 0))) | AD52: =IF(is_empty, "", IF(is_header, "Excess", IF(out_budget - out_tracked < 0, out_tracked - out_budget, 0)))
C53: {=IF(C52=-1,-1, IF(C52<income_max_row, C52+1, IF(C52=income_max_row, income_total_row, IF(C52=income_total_row, "/1", IF(C52="/1", expenses_header_row, IF(C52<expenses_max_row, C52+1, IF(C52=expenses_max_row, expenses_total_row, IF(C52=expenses_total_row, "/2", IF(C52="/2", savings_header_row, IF(C52<savings_max_row, C52+1, IF(C52=savings_max_row, savings_total_row, -1)))))))))))} -> -1 | D53: =IF(is_header,row_id, IF(NOT(is_empty),D52,-1)) -> -1 | E53: {=1*OR(row_id=income_header_row, row_id=expenses_header_row, row_id=savings_header_row)} -> 0 | F53: =1*NOT(OR(is_header, is_total, is_empty)) -> 0 | G53: {=1*OR(row_id=income_total_row, row_id=expenses_total_row, row_id=savings_total_row)} -> 0 | H53: =1*OR(row_id="/1", row_id="/2", row_id=-1) -> 1 | I53: {=IFERROR(INDEX('Budget Planning'!$C:$C, header_row_id),"")} | J53: {=IFERROR(INDEX('Budget Planning'!$C:$C, row_id), "")} | K53: {=IF( OR(is_header, is_empty, selected_period=""), "", IF( is_total, IF( selected_period="Total Year", SUMPRODUCT( Tracking[Amount] * (Tracking[Type]=type) * (YEAR(Tracking[Effective Date])=selected_year) ), SUMPRODUCT( Tracking[Amount] * (Tracking[Type]=type) * (YEAR(Tracking[Effective Date])=selected_year) * (MONTH(Tracking[Effective Date])=selected_period) ) ), IF( selected_period="Total Year", SUMPRODUCT( Tracking[Amount] * (Tracking[Type]=type) * (Tracking[Category]=item) * (YEAR(Tracking[Effective Date])=selected_year) ), SUMPRODUCT( Tracking[Amount] * (Tracking[Type]=type) * (Tracking[Category]=item) * (YEAR(Tracking[Effective Date])=selected_year) * (MONTH(Tracking[Effective Date])=selected_period) ) ) ) )} | L53: {=IF( OR(is_header, is_empty), "", INDEX( 'Budget Planning'!$E:$FA, row_id, MATCH( IF( selected_period = "Total Year", selected_year, DATE(selected_year, selected_period, 1) ), 'Budget Planning'!$E$10:$FA$10, 0 ) ) )} | M53: {=IF( is_cat, IF( header_row_id = income_header_row, MATCH(income_min_row, $C:$C, 0), IF( header_row_id = expenses_header_row, MATCH(expenses_min_row, $C:$C, 0), IF( header_row_id = savings_header_row, MATCH(savings_min_row, $C:$C, 0), "" ) ) ), "" )} | N53: {=IF( is_cat, IF( header_row_id = income_header_row, MATCH(income_max_row, $C:$C, 0), IF( header_row_id = expenses_header_row, MATCH(expenses_max_row, $C:$C, 0), IF( header_row_id = savings_header_row, MATCH(savings_max_row, $C:$C, 0), "" ) ) ), "" )} | O53: =IF(is_cat, ADDRESS(sort_min_row, COLUMN(tracked)) &":" & ADDRESS(sort_max_row, COLUMN(tracked)), "") | P53: =IF(is_cat, RANK(tracked, INDIRECT(tracked_range), 0), "") | Q53: =IF(is_cat, ADDRESS(sort_min_row, COLUMN(budget)) &":" & ADDRESS(sort_max_row, COLUMN(budget)), "") | R53: =IF(is_cat, RANK(budget, INDIRECT(budget_range), 0), "") | S53: =IF(is_cat, _xlfn.NUMBERVALUE(tracked_rank & budget_rank), "") | T53: =IF(is_cat, ADDRESS(sort_min_row, COLUMN(comb_rank)) &":" & ADDRESS(sort_max_row, COLUMN(comb_rank)), "") | U53: =IF(is_cat,RANK(comb_rank,INDIRECT(comb_rank_range),1),"") | V53: =IF(is_cat, ADDRESS(sort_min_row, COLUMN(comb_rank_norm)) &":" & ADDRESS(ROW(), COLUMN(comb_rank_norm)), "") | W53: =IF(is_cat, comb_rank_norm + COUNTIF(INDIRECT(comb_rank_norm_run_range), comb_rank_norm)-1, "") | X53: =IF(is_cat, header_row_id + comb_rank_unique, row_id) -> -1 | Y53: =IF(is_empty, "", INDEX($J:$J, MATCH(row_id, $X:$X, 0))) | Z53: =IF(is_empty, "", IF(is_header, "Tracked", INDEX($K:$K, MATCH(row_id, $X:$X, 0)))) | AA53: =IF(is_empty, "", IF(is_header, "Budget", INDEX($L:$L, MATCH(row_id, $X:$X, 0)))) | AB53: =IF(is_empty, "", IF(is_header, "% Compl.", IFERROR(out_tracked / out_budget, "-"))) | AC53: =IF(is_empty, "", IF(is_header, "Remaining", IF(out_budget - out_tracked > 0, out_budget - out_tracked, 0))) | AD53: =IF(is_empty, "", IF(is_header, "Excess", IF(out_budget - out_tracked < 0, out_tracked - out_budget, 0)))
C54: {=IF(C53=-1,-1, IF(C53<income_max_row, C53+1, IF(C53=income_max_row, income_total_row, IF(C53=income_total_row, "/1", IF(C53="/1", expenses_header_row, IF(C53<expenses_max_row, C53+1, IF(C53=expenses_max_row, expenses_total_row, IF(C53=expenses_total_row, "/2", IF(C53="/2", savings_header_row, IF(C53<savings_max_row, C53+1, IF(C53=savings_max_row, savings_total_row, -1)))))))))))} -> -1 | D54: =IF(is_header,row_id, IF(NOT(is_empty),D53,-1)) -> -1 | E54: {=1*OR(row_id=income_header_row, row_id=expenses_header_row, row_id=savings_header_row)} -> 0 | F54: =1*NOT(OR(is_header, is_total, is_empty)) -> 0 | G54: {=1*OR(row_id=income_total_row, row_id=expenses_total_row, row_id=savings_total_row)} -> 0 | H54: =1*OR(row_id="/1", row_id="/2", row_id=-1) -> 1 | I54: {=IFERROR(INDEX('Budget Planning'!$C:$C, header_row_id),"")} | J54: {=IFERROR(INDEX('Budget Planning'!$C:$C, row_id), "")} | K54: {=IF( OR(is_header, is_empty, selected_period=""), "", IF( is_total, IF( selected_period="Total Year", SUMPRODUCT( Tracking[Amount] * (Tracking[Type]=type) * (YEAR(Tracking[Effective Date])=selected_year) ), SUMPRODUCT( Tracking[Amount] * (Tracking[Type]=type) * (YEAR(Tracking[Effective Date])=selected_year) * (MONTH(Tracking[Effective Date])=selected_period) ) ), IF( selected_period="Total Year", SUMPRODUCT( Tracking[Amount] * (Tracking[Type]=type) * (Tracking[Category]=item) * (YEAR(Tracking[Effective Date])=selected_year) ), SUMPRODUCT( Tracking[Amount] * (Tracking[Type]=type) * (Tracking[Category]=item) * (YEAR(Tracking[Effective Date])=selected_year) * (MONTH(Tracking[Effective Date])=selected_period) ) ) ) )} | L54: {=IF( OR(is_header, is_empty), "", INDEX( 'Budget Planning'!$E:$FA, row_id, MATCH( IF( selected_period = "Total Year", selected_year, DATE(selected_year, selected_period, 1) ), 'Budget Planning'!$E$10:$FA$10, 0 ) ) )} | M54: {=IF( is_cat, IF( header_row_id = income_header_row, MATCH(income_min_row, $C:$C, 0), IF( header_row_id = expenses_header_row, MATCH(expenses_min_row, $C:$C, 0), IF( header_row_id = savings_header_row, MATCH(savings_min_row, $C:$C, 0), "" ) ) ), "" )} | N54: {=IF( is_cat, IF( header_row_id = income_header_row, MATCH(income_max_row, $C:$C, 0), IF( header_row_id = expenses_header_row, MATCH(expenses_max_row, $C:$C, 0), IF( header_row_id = savings_header_row, MATCH(savings_max_row, $C:$C, 0), "" ) ) ), "" )} | O54: =IF(is_cat, ADDRESS(sort_min_row, COLUMN(tracked)) &":" & ADDRESS(sort_max_row, COLUMN(tracked)), "") | P54: =IF(is_cat, RANK(tracked, INDIRECT(tracked_range), 0), "") | Q54: =IF(is_cat, ADDRESS(sort_min_row, COLUMN(budget)) &":" & ADDRESS(sort_max_row, COLUMN(budget)), "") | R54: =IF(is_cat, RANK(budget, INDIRECT(budget_range), 0), "") | S54: =IF(is_cat, _xlfn.NUMBERVALUE(tracked_rank & budget_rank), "") | T54: =IF(is_cat, ADDRESS(sort_min_row, COLUMN(comb_rank)) &":" & ADDRESS(sort_max_row, COLUMN(comb_rank)), "") | U54: =IF(is_cat,RANK(comb_rank,INDIRECT(comb_rank_range),1),"") | V54: =IF(is_cat, ADDRESS(sort_min_row, COLUMN(comb_rank_norm)) &":" & ADDRESS(ROW(), COLUMN(comb_rank_norm)), "") | W54: =IF(is_cat, comb_rank_norm + COUNTIF(INDIRECT(comb_rank_norm_run_range), comb_rank_norm)-1, "") | X54: =IF(is_cat, header_row_id + comb_rank_unique, row_id) -> -1 | Y54: =IF(is_empty, "", INDEX($J:$J, MATCH(row_id, $X:$X, 0))) | Z54: =IF(is_empty, "", IF(is_header, "Tracked", INDEX($K:$K, MATCH(row_id, $X:$X, 0)))) | AA54: =IF(is_empty, "", IF(is_header, "Budget", INDEX($L:$L, MATCH(row_id, $X:$X, 0)))) | AB54: =IF(is_empty, "", IF(is_header, "% Compl.", IFERROR(out_tracked / out_budget, "-"))) | AC54: =IF(is_empty, "", IF(is_header, "Remaining", IF(out_budget - out_tracked > 0, out_budget - out_tracked, 0))) | AD54: =IF(is_empty, "", IF(is_header, "Excess", IF(out_budget - out_tracked < 0, out_tracked - out_budget, 0)))
C55: {=IF(C54=-1,-1, IF(C54<income_max_row, C54+1, IF(C54=income_max_row, income_total_row, IF(C54=income_total_row, "/1", IF(C54="/1", expenses_header_row, IF(C54<expenses_max_row, C54+1, IF(C54=expenses_max_row, expenses_total_row, IF(C54=expenses_total_row, "/2", IF(C54="/2", savings_header_row, IF(C54<savings_max_row, C54+1, IF(C54=savings_max_row, savings_total_row, -1)))))))))))} -> -1 | D55: =IF(is_header,row_id, IF(NOT(is_empty),D54,-1)) -> -1 | E55: {=1*OR(row_id=income_header_row, row_id=expenses_header_row, row_id=savings_header_row)} -> 0 | F55: =1*NOT(OR(is_header, is_total, is_empty)) -> 0 | G55: {=1*OR(row_id=income_total_row, row_id=expenses_total_row, row_id=savings_total_row)} -> 0 | H55: =1*OR(row_id="/1", row_id="/2", row_id=-1) -> 1 | I55: {=IFERROR(INDEX('Budget Planning'!$C:$C, header_row_id),"")} | J55: {=IFERROR(INDEX('Budget Planning'!$C:$C, row_id), "")} | K55: {=IF( OR(is_header, is_empty, selected_period=""), "", IF( is_total, IF( selected_period="Total Year", SUMPRODUCT( Tracking[Amount] * (Tracking[Type]=type) * (YEAR(Tracking[Effective Date])=selected_year) ), SUMPRODUCT( Tracking[Amount] * (Tracking[Type]=type) * (YEAR(Tracking[Effective Date])=selected_year) * (MONTH(Tracking[Effective Date])=selected_period) ) ), IF( selected_period="Total Year", SUMPRODUCT( Tracking[Amount] * (Tracking[Type]=type) * (Tracking[Category]=item) * (YEAR(Tracking[Effective Date])=selected_year) ), SUMPRODUCT( Tracking[Amount] * (Tracking[Type]=type) * (Tracking[Category]=item) * (YEAR(Tracking[Effective Date])=selected_year) * (MONTH(Tracking[Effective Date])=selected_period) ) ) ) )} | L55: {=IF( OR(is_header, is_empty), "", INDEX( 'Budget Planning'!$E:$FA, row_id, MATCH( IF( selected_period = "Total Year", selected_year, DATE(selected_year, selected_period, 1) ), 'Budget Planning'!$E$10:$FA$10, 0 ) ) )} | M55: {=IF( is_cat, IF( header_row_id = income_header_row, MATCH(income_min_row, $C:$C, 0), IF( header_row_id = expenses_header_row, MATCH(expenses_min_row, $C:$C, 0), IF( header_row_id = savings_header_row, MATCH(savings_min_row, $C:$C, 0), "" ) ) ), "" )} | N55: {=IF( is_cat, IF( header_row_id = income_header_row, MATCH(income_max_row, $C:$C, 0), IF( header_row_id = expenses_header_row, MATCH(expenses_max_row, $C:$C, 0), IF( header_row_id = savings_header_row, MATCH(savings_max_row, $C:$C, 0), "" ) ) ), "" )} | O55: =IF(is_cat, ADDRESS(sort_min_row, COLUMN(tracked)) &":" & ADDRESS(sort_max_row, COLUMN(tracked)), "") | P55: =IF(is_cat, RANK(tracked, INDIRECT(tracked_range), 0), "") | Q55: =IF(is_cat, ADDRESS(sort_min_row, COLUMN(budget)) &":" & ADDRESS(sort_max_row, COLUMN(budget)), "") | R55: =IF(is_cat, RANK(budget, INDIRECT(budget_range), 0), "") | S55: =IF(is_cat, _xlfn.NUMBERVALUE(tracked_rank & budget_rank), "") | T55: =IF(is_cat, ADDRESS(sort_min_row, COLUMN(comb_rank)) &":" & ADDRESS(sort_max_row, COLUMN(comb_rank)), "") | U55: =IF(is_cat,RANK(comb_rank,INDIRECT(comb_rank_range),1),"") | V55: =IF(is_cat, ADDRESS(sort_min_row, COLUMN(comb_rank_norm)) &":" & ADDRESS(ROW(), COLUMN(comb_rank_norm)), "") | W55: =IF(is_cat, comb_rank_norm + COUNTIF(INDIRECT(comb_rank_norm_run_range), comb_rank_norm)-1, "") | X55: =IF(is_cat, header_row_id + comb_rank_unique, row_id) -> -1 | Y55: =IF(is_empty, "", INDEX($J:$J, MATCH(row_id, $X:$X, 0))) | Z55: =IF(is_empty, "", IF(is_header, "Tracked", INDEX($K:$K, MATCH(row_id, $X:$X, 0)))) | AA55: =IF(is_empty, "", IF(is_header, "Budget", INDEX($L:$L, MATCH(row_id, $X:$X, 0)))) | AB55: =IF(is_empty, "", IF(is_header, "% Compl.", IFERROR(out_tracked / out_budget, "-"))) | AC55: =IF(is_empty, "", IF(is_header, "Remaining", IF(out_budget - out_tracked > 0, out_budget - out_tracked, 0))) | AD55: =IF(is_empty, "", IF(is_header, "Excess", IF(out_budget - out_tracked < 0, out_tracked - out_budget, 0)))
C56: {=IF(C55=-1,-1, IF(C55<income_max_row, C55+1, IF(C55=income_max_row, income_total_row, IF(C55=income_total_row, "/1", IF(C55="/1", expenses_header_row, IF(C55<expenses_max_row, C55+1, IF(C55=expenses_max_row, expenses_total_row, IF(C55=expenses_total_row, "/2", IF(C55="/2", savings_header_row, IF(C55<savings_max_row, C55+1, IF(C55=savings_max_row, savings_total_row, -1)))))))))))} -> -1 | D56: =IF(is_header,row_id, IF(NOT(is_empty),D55,-1)) -> -1 | E56: {=1*OR(row_id=income_header_row, row_id=expenses_header_row, row_id=savings_header_row)} -> 0 | F56: =1*NOT(OR(is_header, is_total, is_empty)) -> 0 | G56: {=1*OR(row_id=income_total_row, row_id=expenses_total_row, row_id=savings_total_row)} -> 0 | H56: =1*OR(row_id="/1", row_id="/2", row_id=-1) -> 1 | I56: {=IFERROR(INDEX('Budget Planning'!$C:$C, header_row_id),"")} | J56: {=IFERROR(INDEX('Budget Planning'!$C:$C, row_id), "")} | K56: {=IF( OR(is_header, is_empty, selected_period=""), "", IF( is_total, IF( selected_period="Total Year", SUMPRODUCT( Tracking[Amount] * (Tracking[Type]=type) * (YEAR(Tracking[Effective Date])=selected_year) ), SUMPRODUCT( Tracking[Amount] * (Tracking[Type]=type) * (YEAR(Tracking[Effective Date])=selected_year) * (MONTH(Tracking[Effective Date])=selected_period) ) ), IF( selected_period="Total Year", SUMPRODUCT( Tracking[Amount] * (Tracking[Type]=type) * (Tracking[Category]=item) * (YEAR(Tracking[Effective Date])=selected_year) ), SUMPRODUCT( Tracking[Amount] * (Tracking[Type]=type) * (Tracking[Category]=item) * (YEAR(Tracking[Effective Date])=selected_year) * (MONTH(Tracking[Effective Date])=selected_period) ) ) ) )} | L56: {=IF( OR(is_header, is_empty), "", INDEX( 'Budget Planning'!$E:$FA, row_id, MATCH( IF( selected_period = "Total Year", selected_year, DATE(selected_year, selected_period, 1) ), 'Budget Planning'!$E$10:$FA$10, 0 ) ) )} | M56: {=IF( is_cat, IF( header_row_id = income_header_row, MATCH(income_min_row, $C:$C, 0), IF( header_row_id = expenses_header_row, MATCH(expenses_min_row, $C:$C, 0), IF( header_row_id = savings_header_row, MATCH(savings_min_row, $C:$C, 0), "" ) ) ), "" )} | N56: {=IF( is_cat, IF( header_row_id = income_header_row, MATCH(income_max_row, $C:$C, 0), IF( header_row_id = expenses_header_row, MATCH(expenses_max_row, $C:$C, 0), IF( header_row_id = savings_header_row, MATCH(savings_max_row, $C:$C, 0), "" ) ) ), "" )} | O56: =IF(is_cat, ADDRESS(sort_min_row, COLUMN(tracked)) &":" & ADDRESS(sort_max_row, COLUMN(tracked)), "") | P56: =IF(is_cat, RANK(tracked, INDIRECT(tracked_range), 0), "") | Q56: =IF(is_cat, ADDRESS(sort_min_row, COLUMN(budget)) &":" & ADDRESS(sort_max_row, COLUMN(budget)), "") | R56: =IF(is_cat, RANK(budget, INDIRECT(budget_range), 0), "") | S56: =IF(is_cat, _xlfn.NUMBERVALUE(tracked_rank & budget_rank), "") | T56: =IF(is_cat, ADDRESS(sort_min_row, COLUMN(comb_rank)) &":" & ADDRESS(sort_max_row, COLUMN(comb_rank)), "") | U56: =IF(is_cat,RANK(comb_rank,INDIRECT(comb_rank_range),1),"") | V56: =IF(is_cat, ADDRESS(sort_min_row, COLUMN(comb_rank_norm)) &":" & ADDRESS(ROW(), COLUMN(comb_rank_norm)), "") | W56: =IF(is_cat, comb_rank_norm + COUNTIF(INDIRECT(comb_rank_norm_run_range), comb_rank_norm)-1, "") | X56: =IF(is_cat, header_row_id + comb_rank_unique, row_id) -> -1 | Y56: =IF(is_empty, "", INDEX($J:$J, MATCH(row_id, $X:$X, 0))) | Z56: =IF(is_empty, "", IF(is_header, "Tracked", INDEX($K:$K, MATCH(row_id, $X:$X, 0)))) | AA56: =IF(is_empty, "", IF(is_header, "Budget", INDEX($L:$L, MATCH(row_id, $X:$X, 0)))) | AB56: =IF(is_empty, "", IF(is_header, "% Compl.", IFERROR(out_tracked / out_budget, "-"))) | AC56: =IF(is_empty, "", IF(is_header, "Remaining", IF(out_budget - out_tracked > 0, out_budget - out_tracked, 0))) | AD56: =IF(is_empty, "", IF(is_header, "Excess", IF(out_budget - out_tracked < 0, out_tracked - out_budget, 0)))
C57: {=IF(C56=-1,-1, IF(C56<income_max_row, C56+1, IF(C56=income_max_row, income_total_row, IF(C56=income_total_row, "/1", IF(C56="/1", expenses_header_row, IF(C56<expenses_max_row, C56+1, IF(C56=expenses_max_row, expenses_total_row, IF(C56=expenses_total_row, "/2", IF(C56="/2", savings_header_row, IF(C56<savings_max_row, C56+1, IF(C56=savings_max_row, savings_total_row, -1)))))))))))} -> -1 | D57: =IF(is_header,row_id, IF(NOT(is_empty),D56,-1)) -> -1 | E57: {=1*OR(row_id=income_header_row, row_id=expenses_header_row, row_id=savings_header_row)} -> 0 | F57: =1*NOT(OR(is_header, is_total, is_empty)) -> 0 | G57: {=1*OR(row_id=income_total_row, row_id=expenses_total_row, row_id=savings_total_row)} -> 0 | H57: =1*OR(row_id="/1", row_id="/2", row_id=-1) -> 1 | I57: {=IFERROR(INDEX('Budget Planning'!$C:$C, header_row_id),"")} | J57: {=IFERROR(INDEX('Budget Planning'!$C:$C, row_id), "")} | K57: {=IF( OR(is_header, is_empty, selected_period=""), "", IF( is_total, IF( selected_period="Total Year", SUMPRODUCT( Tracking[Amount] * (Tracking[Type]=type) * (YEAR(Tracking[Effective Date])=selected_year) ), SUMPRODUCT( Tracking[Amount] * (Tracking[Type]=type) * (YEAR(Tracking[Effective Date])=selected_year) * (MONTH(Tracking[Effective Date])=selected_period) ) ), IF( selected_period="Total Year", SUMPRODUCT( Tracking[Amount] * (Tracking[Type]=type) * (Tracking[Category]=item) * (YEAR(Tracking[Effective Date])=selected_year) ), SUMPRODUCT( Tracking[Amount] * (Tracking[Type]=type) * (Tracking[Category]=item) * (YEAR(Tracking[Effective Date])=selected_year) * (MONTH(Tracking[Effective Date])=selected_period) ) ) ) )} | L57: {=IF( OR(is_header, is_empty), "", INDEX( 'Budget Planning'!$E:$FA, row_id, MATCH( IF( selected_period = "Total Year", selected_year, DATE(selected_year, selected_period, 1) ), 'Budget Planning'!$E$10:$FA$10, 0 ) ) )} | M57: {=IF( is_cat, IF( header_row_id = income_header_row, MATCH(income_min_row, $C:$C, 0), IF( header_row_id = expenses_header_row, MATCH(expenses_min_row, $C:$C, 0), IF( header_row_id = savings_header_row, MATCH(savings_min_row, $C:$C, 0), "" ) ) ), "" )} | N57: {=IF( is_cat, IF( header_row_id = income_header_row, MATCH(income_max_row, $C:$C, 0), IF( header_row_id = expenses_header_row, MATCH(expenses_max_row, $C:$C, 0), IF( header_row_id = savings_header_row, MATCH(savings_max_row, $C:$C, 0), "" ) ) ), "" )} | O57: =IF(is_cat, ADDRESS(sort_min_row, COLUMN(tracked)) &":" & ADDRESS(sort_max_row, COLUMN(tracked)), "") | P57: =IF(is_cat, RANK(tracked, INDIRECT(tracked_range), 0), "") | Q57: =IF(is_cat, ADDRESS(sort_min_row, COLUMN(budget)) &":" & ADDRESS(sort_max_row, COLUMN(budget)), "") | R57: =IF(is_cat, RANK(budget, INDIRECT(budget_range), 0), "") | S57: =IF(is_cat, _xlfn.NUMBERVALUE(tracked_rank & budget_rank), "") | T57: =IF(is_cat, ADDRESS(sort_min_row, COLUMN(comb_rank)) &":" & ADDRESS(sort_max_row, COLUMN(comb_rank)), "") | U57: =IF(is_cat,RANK(comb_rank,INDIRECT(comb_rank_range),1),"") | V57: =IF(is_cat, ADDRESS(sort_min_row, COLUMN(comb_rank_norm)) &":" & ADDRESS(ROW(), COLUMN(comb_rank_norm)), "") | W57: =IF(is_cat, comb_rank_norm + COUNTIF(INDIRECT(comb_rank_norm_run_range), comb_rank_norm)-1, "") | X57: =IF(is_cat, header_row_id + comb_rank_unique, row_id) -> -1 | Y57: =IF(is_empty, "", INDEX($J:$J, MATCH(row_id, $X:$X, 0))) | Z57: =IF(is_empty, "", IF(is_header, "Tracked", INDEX($K:$K, MATCH(row_id, $X:$X, 0)))) | AA57: =IF(is_empty, "", IF(is_header, "Budget", INDEX($L:$L, MATCH(row_id, $X:$X, 0)))) | AB57: =IF(is_empty, "", IF(is_header, "% Compl.", IFERROR(out_tracked / out_budget, "-"))) | AC57: =IF(is_empty, "", IF(is_header, "Remaining", IF(out_budget - out_tracked > 0, out_budget - out_tracked, 0))) | AD57: =IF(is_empty, "", IF(is_header, "Excess", IF(out_budget - out_tracked < 0, out_tracked - out_budget, 0)))
C58: {=IF(C57=-1,-1, IF(C57<income_max_row, C57+1, IF(C57=income_max_row, income_total_row, IF(C57=income_total_row, "/1", IF(C57="/1", expenses_header_row, IF(C57<expenses_max_row, C57+1, IF(C57=expenses_max_row, expenses_total_row, IF(C57=expenses_total_row, "/2", IF(C57="/2", savings_header_row, IF(C57<savings_max_row, C57+1, IF(C57=savings_max_row, savings_total_row, -1)))))))))))} -> -1 | D58: =IF(is_header,row_id, IF(NOT(is_empty),D57,-1)) -> -1 | E58: {=1*OR(row_id=income_header_row, row_id=expenses_header_row, row_id=savings_header_row)} -> 0 | F58: =1*NOT(OR(is_header, is_total, is_empty)) -> 0 | G58: {=1*OR(row_id=income_total_row, row_id=expenses_total_row, row_id=savings_total_row)} -> 0 | H58: =1*OR(row_id="/1", row_id="/2", row_id=-1) -> 1 | I58: {=IFERROR(INDEX('Budget Planning'!$C:$C, header_row_id),"")} | J58: {=IFERROR(INDEX('Budget Planning'!$C:$C, row_id), "")} | K58: {=IF( OR(is_header, is_empty, selected_period=""), "", IF( is_total, IF( selected_period="Total Year", SUMPRODUCT( Tracking[Amount] * (Tracking[Type]=type) * (YEAR(Tracking[Effective Date])=selected_year) ), SUMPRODUCT( Tracking[Amount] * (Tracking[Type]=type) * (YEAR(Tracking[Effective Date])=selected_year) * (MONTH(Tracking[Effective Date])=selected_period) ) ), IF( selected_period="Total Year", SUMPRODUCT( Tracking[Amount] * (Tracking[Type]=type) * (Tracking[Category]=item) * (YEAR(Tracking[Effective Date])=selected_year) ), SUMPRODUCT( Tracking[Amount] * (Tracking[Type]=type) * (Tracking[Category]=item) * (YEAR(Tracking[Effective Date])=selected_year) * (MONTH(Tracking[Effective Date])=selected_period) ) ) ) )} | L58: {=IF( OR(is_header, is_empty), "", INDEX( 'Budget Planning'!$E:$FA, row_id, MATCH( IF( selected_period = "Total Year", selected_year, DATE(selected_year, selected_period, 1) ), 'Budget Planning'!$E$10:$FA$10, 0 ) ) )} | M58: {=IF( is_cat, IF( header_row_id = income_header_row, MATCH(income_min_row, $C:$C, 0), IF( header_row_id = expenses_header_row, MATCH(expenses_min_row, $C:$C, 0), IF( header_row_id = savings_header_row, MATCH(savings_min_row, $C:$C, 0), "" ) ) ), "" )} | N58: {=IF( is_cat, IF( header_row_id = income_header_row, MATCH(income_max_row, $C:$C, 0), IF( header_row_id = expenses_header_row, MATCH(expenses_max_row, $C:$C, 0), IF( header_row_id = savings_header_row, MATCH(savings_max_row, $C:$C, 0), "" ) ) ), "" )} | O58: =IF(is_cat, ADDRESS(sort_min_row, COLUMN(tracked)) &":" & ADDRESS(sort_max_row, COLUMN(tracked)), "") | P58: =IF(is_cat, RANK(tracked, INDIRECT(tracked_range), 0), "") | Q58: =IF(is_cat, ADDRESS(sort_min_row, COLUMN(budget)) &":" & ADDRESS(sort_max_row, COLUMN(budget)), "") | R58: =IF(is_cat, RANK(budget, INDIRECT(budget_range), 0), "") | S58: =IF(is_cat, _xlfn.NUMBERVALUE(tracked_rank & budget_rank), "") | T58: =IF(is_cat, ADDRESS(sort_min_row, COLUMN(comb_rank)) &":" & ADDRESS(sort_max_row, COLUMN(comb_rank)), "") | U58: =IF(is_cat,RANK(comb_rank,INDIRECT(comb_rank_range),1),"") | V58: =IF(is_cat, ADDRESS(sort_min_row, COLUMN(comb_rank_norm)) &":" & ADDRESS(ROW(), COLUMN(comb_rank_norm)), "") | W58: =IF(is_cat, comb_rank_norm + COUNTIF(INDIRECT(comb_rank_norm_run_range), comb_rank_norm)-1, "") | X58: =IF(is_cat, header_row_id + comb_rank_unique, row_id) -> -1 | Y58: =IF(is_empty, "", INDEX($J:$J, MATCH(row_id, $X:$X, 0))) | Z58: =IF(is_empty, "", IF(is_header, "Tracked", INDEX($K:$K, MATCH(row_id, $X:$X, 0)))) | AA58: =IF(is_empty, "", IF(is_header, "Budget", INDEX($L:$L, MATCH(row_id, $X:$X, 0)))) | AB58: =IF(is_empty, "", IF(is_header, "% Compl.", IFERROR(out_tracked / out_budget, "-"))) | AC58: =IF(is_empty, "", IF(is_header, "Remaining", IF(out_budget - out_tracked > 0, out_budget - out_tracked, 0))) | AD58: =IF(is_empty, "", IF(is_header, "Excess", IF(out_budget - out_tracked < 0, out_tracked - out_budget, 0)))
C59: {=IF(C58=-1,-1, IF(C58<income_max_row, C58+1, IF(C58=income_max_row, income_total_row, IF(C58=income_total_row, "/1", IF(C58="/1", expenses_header_row, IF(C58<expenses_max_row, C58+1, IF(C58=expenses_max_row, expenses_total_row, IF(C58=expenses_total_row, "/2", IF(C58="/2", savings_header_row, IF(C58<savings_max_row, C58+1, IF(C58=savings_max_row, savings_total_row, -1)))))))))))} -> -1 | D59: =IF(is_header,row_id, IF(NOT(is_empty),D58,-1)) -> -1 | E59: {=1*OR(row_id=income_header_row, row_id=expenses_header_row, row_id=savings_header_row)} -> 0 | F59: =1*NOT(OR(is_header, is_total, is_empty)) -> 0 | G59: {=1*OR(row_id=income_total_row, row_id=expenses_total_row, row_id=savings_total_row)} -> 0 | H59: =1*OR(row_id="/1", row_id="/2", row_id=-1) -> 1 | I59: {=IFERROR(INDEX('Budget Planning'!$C:$C, header_row_id),"")} | J59: {=IFERROR(INDEX('Budget Planning'!$C:$C, row_id), "")} | K59: {=IF( OR(is_header, is_empty, selected_period=""), "", IF( is_total, IF( selected_period="Total Year", SUMPRODUCT( Tracking[Amount] * (Tracking[Type]=type) * (YEAR(Tracking[Effective Date])=selected_year) ), SUMPRODUCT( Tracking[Amount] * (Tracking[Type]=type) * (YEAR(Tracking[Effective Date])=selected_year) * (MONTH(Tracking[Effective Date])=selected_period) ) ), IF( selected_period="Total Year", SUMPRODUCT( Tracking[Amount] * (Tracking[Type]=type) * (Tracking[Category]=item) * (YEAR(Tracking[Effective Date])=selected_year) ), SUMPRODUCT( Tracking[Amount] * (Tracking[Type]=type) * (Tracking[Category]=item) * (YEAR(Tracking[Effective Date])=selected_year) * (MONTH(Tracking[Effective Date])=selected_period) ) ) ) )} | L59: {=IF( OR(is_header, is_empty), "", INDEX( 'Budget Planning'!$E:$FA, row_id, MATCH( IF( selected_period = "Total Year", selected_year, DATE(selected_year, selected_period, 1) ), 'Budget Planning'!$E$10:$FA$10, 0 ) ) )} | M59: {=IF( is_cat, IF( header_row_id = income_header_row, MATCH(income_min_row, $C:$C, 0), IF( header_row_id = expenses_header_row, MATCH(expenses_min_row, $C:$C, 0), IF( header_row_id = savings_header_row, MATCH(savings_min_row, $C:$C, 0), "" ) ) ), "" )} | N59: {=IF( is_cat, IF( header_row_id = income_header_row, MATCH(income_max_row, $C:$C, 0), IF( header_row_id = expenses_header_row, MATCH(expenses_max_row, $C:$C, 0), IF( header_row_id = savings_header_row, MATCH(savings_max_row, $C:$C, 0), "" ) ) ), "" )} | O59: =IF(is_cat, ADDRESS(sort_min_row, COLUMN(tracked)) &":" & ADDRESS(sort_max_row, COLUMN(tracked)), "") | P59: =IF(is_cat, RANK(tracked, INDIRECT(tracked_range), 0), "") | Q59: =IF(is_cat, ADDRESS(sort_min_row, COLUMN(budget)) &":" & ADDRESS(sort_max_row, COLUMN(budget)), "") | R59: =IF(is_cat, RANK(budget, INDIRECT(budget_range), 0), "") | S59: =IF(is_cat, _xlfn.NUMBERVALUE(tracked_rank & budget_rank), "") | T59: =IF(is_cat, ADDRESS(sort_min_row, COLUMN(comb_rank)) &":" & ADDRESS(sort_max_row, COLUMN(comb_rank)), "") | U59: =IF(is_cat,RANK(comb_rank,INDIRECT(comb_rank_range),1),"") | V59: =IF(is_cat, ADDRESS(sort_min_row, COLUMN(comb_rank_norm)) &":" & ADDRESS(ROW(), COLUMN(comb_rank_norm)), "") | W59: =IF(is_cat, comb_rank_norm + COUNTIF(INDIRECT(comb_rank_norm_run_range), comb_rank_norm)-1, "") | X59: =IF(is_cat, header_row_id + comb_rank_unique, row_id) -> -1 | Y59: =IF(is_empty, "", INDEX($J:$J, MATCH(row_id, $X:$X, 0))) | Z59: =IF(is_empty, "", IF(is_header, "Tracked", INDEX($K:$K, MATCH(row_id, $X:$X, 0)))) | AA59: =IF(is_empty, "", IF(is_header, "Budget", INDEX($L:$L, MATCH(row_id, $X:$X, 0)))) | AB59: =IF(is_empty, "", IF(is_header, "% Compl.", IFERROR(out_tracked / out_budget, "-"))) | AC59: =IF(is_empty, "", IF(is_header, "Remaining", IF(out_budget - out_tracked > 0, out_budget - out_tracked, 0))) | AD59: =IF(is_empty, "", IF(is_header, "Excess", IF(out_budget - out_tracked < 0, out_tracked - out_budget, 0)))
C60: {=IF(C59=-1,-1, IF(C59<income_max_row, C59+1, IF(C59=income_max_row, income_total_row, IF(C59=income_total_row, "/1", IF(C59="/1", expenses_header_row, IF(C59<expenses_max_row, C59+1, IF(C59=expenses_max_row, expenses_total_row, IF(C59=expenses_total_row, "/2", IF(C59="/2", savings_header_row, IF(C59<savings_max_row, C59+1, IF(C59=savings_max_row, savings_total_row, -1)))))))))))} -> -1 | D60: =IF(is_header,row_id, IF(NOT(is_empty),D59,-1)) -> -1 | E60: {=1*OR(row_id=income_header_row, row_id=expenses_header_row, row_id=savings_header_row)} -> 0 | F60: =1*NOT(OR(is_header, is_total, is_empty)) -> 0 | G60: {=1*OR(row_id=income_total_row, row_id=expenses_total_row, row_id=savings_total_row)} -> 0 | H60: =1*OR(row_id="/1", row_id="/2", row_id=-1) -> 1 | I60: {=IFERROR(INDEX('Budget Planning'!$C:$C, header_row_id),"")} | J60: {=IFERROR(INDEX('Budget Planning'!$C:$C, row_id), "")} | K60: {=IF( OR(is_header, is_empty, selected_period=""), "", IF( is_total, IF( selected_period="Total Year", SUMPRODUCT( Tracking[Amount] * (Tracking[Type]=type) * (YEAR(Tracking[Effective Date])=selected_year) ), SUMPRODUCT( Tracking[Amount] * (Tracking[Type]=type) * (YEAR(Tracking[Effective Date])=selected_year) * (MONTH(Tracking[Effective Date])=selected_period) ) ), IF( selected_period="Total Year", SUMPRODUCT( Tracking[Amount] * (Tracking[Type]=type) * (Tracking[Category]=item) * (YEAR(Tracking[Effective Date])=selected_year) ), SUMPRODUCT( Tracking[Amount] * (Tracking[Type]=type) * (Tracking[Category]=item) * (YEAR(Tracking[Effective Date])=selected_year) * (MONTH(Tracking[Effective Date])=selected_period) ) ) ) )} | L60: {=IF( OR(is_header, is_empty), "", INDEX( 'Budget Planning'!$E:$FA, row_id, MATCH( IF( selected_period = "Total Year", selected_year, DATE(selected_year, selected_period, 1) ), 'Budget Planning'!$E$10:$FA$10, 0 ) ) )} | M60: {=IF( is_cat, IF( header_row_id = income_header_row, MATCH(income_min_row, $C:$C, 0), IF( header_row_id = expenses_header_row, MATCH(expenses_min_row, $C:$C, 0), IF( header_row_id = savings_header_row, MATCH(savings_min_row, $C:$C, 0), "" ) ) ), "" )} | N60: {=IF( is_cat, IF( header_row_id = income_header_row, MATCH(income_max_row, $C:$C, 0), IF( header_row_id = expenses_header_row, MATCH(expenses_max_row, $C:$C, 0), IF( header_row_id = savings_header_row, MATCH(savings_max_row, $C:$C, 0), "" ) ) ), "" )} | O60: =IF(is_cat, ADDRESS(sort_min_row, COLUMN(tracked)) &":" & ADDRESS(sort_max_row, COLUMN(tracked)), "") | P60: =IF(is_cat, RANK(tracked, INDIRECT(tracked_range), 0), "") | Q60: =IF(is_cat, ADDRESS(sort_min_row, COLUMN(budget)) &":" & ADDRESS(sort_max_row, COLUMN(budget)), "") | R60: =IF(is_cat, RANK(budget, INDIRECT(budget_range), 0), "") | S60: =IF(is_cat, _xlfn.NUMBERVALUE(tracked_rank & budget_rank), "") | T60: =IF(is_cat, ADDRESS(sort_min_row, COLUMN(comb_rank)) &":" & ADDRESS(sort_max_row, COLUMN(comb_rank)), "") | U60: =IF(is_cat,RANK(comb_rank,INDIRECT(comb_rank_range),1),"") | V60: =IF(is_cat, ADDRESS(sort_min_row, COLUMN(comb_rank_norm)) &":" & ADDRESS(ROW(), COLUMN(comb_rank_norm)), "") | W60: =IF(is_cat, comb_rank_norm + COUNTIF(INDIRECT(comb_rank_norm_run_range), comb_rank_norm)-1, "") | X60: =IF(is_cat, header_row_id + comb_rank_unique, row_id) -> -1 | Y60: =IF(is_empty, "", INDEX($J:$J, MATCH(row_id, $X:$X, 0))) | Z60: =IF(is_empty, "", IF(is_header, "Tracked", INDEX($K:$K, MATCH(row_id, $X:$X, 0)))) | AA60: =IF(is_empty, "", IF(is_header, "Budget", INDEX($L:$L, MATCH(row_id, $X:$X, 0)))) | AB60: =IF(is_empty, "", IF(is_header, "% Compl.", IFERROR(out_tracked / out_budget, "-"))) | AC60: =IF(is_empty, "", IF(is_header, "Remaining", IF(out_budget - out_tracked > 0, out_budget - out_tracked, 0))) | AD60: =IF(is_empty, "", IF(is_header, "Excess", IF(out_budget - out_tracked < 0, out_tracked - out_budget, 0)))
C61: {=IF(C60=-1,-1, IF(C60<income_max_row, C60+1, IF(C60=income_max_row, income_total_row, IF(C60=income_total_row, "/1", IF(C60="/1", expenses_header_row, IF(C60<expenses_max_row, C60+1, IF(C60=expenses_max_row, expenses_total_row, IF(C60=expenses_total_row, "/2", IF(C60="/2", savings_header_row, IF(C60<savings_max_row, C60+1, IF(C60=savings_max_row, savings_total_row, -1)))))))))))} -> -1 | D61: =IF(is_header,row_id, IF(NOT(is_empty),D60,-1)) -> -1 | E61: {=1*OR(row_id=income_header_row, row_id=expenses_header_row, row_id=savings_header_row)} -> 0 | F61: =1*NOT(OR(is_header, is_total, is_empty)) -> 0 | G61: {=1*OR(row_id=income_total_row, row_id=expenses_total_row, row_id=savings_total_row)} -> 0 | H61: =1*OR(row_id="/1", row_id="/2", row_id=-1) -> 1 | I61: {=IFERROR(INDEX('Budget Planning'!$C:$C, header_row_id),"")} | J61: {=IFERROR(INDEX('Budget Planning'!$C:$C, row_id), "")} | K61: {=IF( OR(is_header, is_empty, selected_period=""), "", IF( is_total, IF( selected_period="Total Year", SUMPRODUCT( Tracking[Amount] * (Tracking[Type]=type) * (YEAR(Tracking[Effective Date])=selected_year) ), SUMPRODUCT( Tracking[Amount] * (Tracking[Type]=type) * (YEAR(Tracking[Effective Date])=selected_year) * (MONTH(Tracking[Effective Date])=selected_period) ) ), IF( selected_period="Total Year", SUMPRODUCT( Tracking[Amount] * (Tracking[Type]=type) * (Tracking[Category]=item) * (YEAR(Tracking[Effective Date])=selected_year) ), SUMPRODUCT( Tracking[Amount] * (Tracking[Type]=type) * (Tracking[Category]=item) * (YEAR(Tracking[Effective Date])=selected_year) * (MONTH(Tracking[Effective Date])=selected_period) ) ) ) )} | L61: {=IF( OR(is_header, is_empty), "", INDEX( 'Budget Planning'!$E:$FA, row_id, MATCH( IF( selected_period = "Total Year", selected_year, DATE(selected_year, selected_period, 1) ), 'Budget Planning'!$E$10:$FA$10, 0 ) ) )} | M61: {=IF( is_cat, IF( header_row_id = income_header_row, MATCH(income_min_row, $C:$C, 0), IF( header_row_id = expenses_header_row, MATCH(expenses_min_row, $C:$C, 0), IF( header_row_id = savings_header_row, MATCH(savings_min_row, $C:$C, 0), "" ) ) ), "" )} | N61: {=IF( is_cat, IF( header_row_id = income_header_row, MATCH(income_max_row, $C:$C, 0), IF( header_row_id = expenses_header_row, MATCH(expenses_max_row, $C:$C, 0), IF( header_row_id = savings_header_row, MATCH(savings_max_row, $C:$C, 0), "" ) ) ), "" )} | O61: =IF(is_cat, ADDRESS(sort_min_row, COLUMN(tracked)) &":" & ADDRESS(sort_max_row, COLUMN(tracked)), "") | P61: =IF(is_cat, RANK(tracked, INDIRECT(tracked_range), 0), "") | Q61: =IF(is_cat, ADDRESS(sort_min_row, COLUMN(budget)) &":" & ADDRESS(sort_max_row, COLUMN(budget)), "") | R61: =IF(is_cat, RANK(budget, INDIRECT(budget_range), 0), "") | S61: =IF(is_cat, _xlfn.NUMBERVALUE(tracked_rank & budget_rank), "") | T61: =IF(is_cat, ADDRESS(sort_min_row, COLUMN(comb_rank)) &":" & ADDRESS(sort_max_row, COLUMN(comb_rank)), "") | U61: =IF(is_cat,RANK(comb_rank,INDIRECT(comb_rank_range),1),"") | V61: =IF(is_cat, ADDRESS(sort_min_row, COLUMN(comb_rank_norm)) &":" & ADDRESS(ROW(), COLUMN(comb_rank_norm)), "") | W61: =IF(is_cat, comb_rank_norm + COUNTIF(INDIRECT(comb_rank_norm_run_range), comb_rank_norm)-1, "") | X61: =IF(is_cat, header_row_id + comb_rank_unique, row_id) -> -1 | Y61: =IF(is_empty, "", INDEX($J:$J, MATCH(row_id, $X:$X, 0))) | Z61: =IF(is_empty, "", IF(is_header, "Tracked", INDEX($K:$K, MATCH(row_id, $X:$X, 0)))) | AA61: =IF(is_empty, "", IF(is_header, "Budget", INDEX($L:$L, MATCH(row_id, $X:$X, 0)))) | AB61: =IF(is_empty, "", IF(is_header, "% Compl.", IFERROR(out_tracked / out_budget, "-"))) | AC61: =IF(is_empty, "", IF(is_header, "Remaining", IF(out_budget - out_tracked > 0, out_budget - out_tracked, 0))) | AD61: =IF(is_empty, "", IF(is_header, "Excess", IF(out_budget - out_tracked < 0, out_tracked - out_budget, 0)))
C62: {=IF(C61=-1,-1, IF(C61<income_max_row, C61+1, IF(C61=income_max_row, income_total_row, IF(C61=income_total_row, "/1", IF(C61="/1", expenses_header_row, IF(C61<expenses_max_row, C61+1, IF(C61=expenses_max_row, expenses_total_row, IF(C61=expenses_total_row, "/2", IF(C61="/2", savings_header_row, IF(C61<savings_max_row, C61+1, IF(C61=savings_max_row, savings_total_row, -1)))))))))))} -> -1 | D62: =IF(is_header,row_id, IF(NOT(is_empty),D61,-1)) -> -1 | E62: {=1*OR(row_id=income_header_row, row_id=expenses_header_row, row_id=savings_header_row)} -> 0 | F62: =1*NOT(OR(is_header, is_total, is_empty)) -> 0 | G62: {=1*OR(row_id=income_total_row, row_id=expenses_total_row, row_id=savings_total_row)} -> 0 | H62: =1*OR(row_id="/1", row_id="/2", row_id=-1) -> 1 | I62: {=IFERROR(INDEX('Budget Planning'!$C:$C, header_row_id),"")} | J62: {=IFERROR(INDEX('Budget Planning'!$C:$C, row_id), "")} | K62: {=IF( OR(is_header, is_empty, selected_period=""), "", IF( is_total, IF( selected_period="Total Year", SUMPRODUCT( Tracking[Amount] * (Tracking[Type]=type) * (YEAR(Tracking[Effective Date])=selected_year) ), SUMPRODUCT( Tracking[Amount] * (Tracking[Type]=type) * (YEAR(Tracking[Effective Date])=selected_year) * (MONTH(Tracking[Effective Date])=selected_period) ) ), IF( selected_period="Total Year", SUMPRODUCT( Tracking[Amount] * (Tracking[Type]=type) * (Tracking[Category]=item) * (YEAR(Tracking[Effective Date])=selected_year) ), SUMPRODUCT( Tracking[Amount] * (Tracking[Type]=type) * (Tracking[Category]=item) * (YEAR(Tracking[Effective Date])=selected_year) * (MONTH(Tracking[Effective Date])=selected_period) ) ) ) )} | L62: {=IF( OR(is_header, is_empty), "", INDEX( 'Budget Planning'!$E:$FA, row_id, MATCH( IF( selected_period = "Total Year", selected_year, DATE(selected_year, selected_period, 1) ), 'Budget Planning'!$E$10:$FA$10, 0 ) ) )} | M62: {=IF( is_cat, IF( header_row_id = income_header_row, MATCH(income_min_row, $C:$C, 0), IF( header_row_id = expenses_header_row, MATCH(expenses_min_row, $C:$C, 0), IF( header_row_id = savings_header_row, MATCH(savings_min_row, $C:$C, 0), "" ) ) ), "" )} | N62: {=IF( is_cat, IF( header_row_id = income_header_row, MATCH(income_max_row, $C:$C, 0), IF( header_row_id = expenses_header_row, MATCH(expenses_max_row, $C:$C, 0), IF( header_row_id = savings_header_row, MATCH(savings_max_row, $C:$C, 0), "" ) ) ), "" )} | O62: =IF(is_cat, ADDRESS(sort_min_row, COLUMN(tracked)) &":" & ADDRESS(sort_max_row, COLUMN(tracked)), "") | P62: =IF(is_cat, RANK(tracked, INDIRECT(tracked_range), 0), "") | Q62: =IF(is_cat, ADDRESS(sort_min_row, COLUMN(budget)) &":" & ADDRESS(sort_max_row, COLUMN(budget)), "") | R62: =IF(is_cat, RANK(budget, INDIRECT(budget_range), 0), "") | S62: =IF(is_cat, _xlfn.NUMBERVALUE(tracked_rank & budget_rank), "") | T62: =IF(is_cat, ADDRESS(sort_min_row, COLUMN(comb_rank)) &":" & ADDRESS(sort_max_row, COLUMN(comb_rank)), "") | U62: =IF(is_cat,RANK(comb_rank,INDIRECT(comb_rank_range),1),"") | V62: =IF(is_cat, ADDRESS(sort_min_row, COLUMN(comb_rank_norm)) &":" & ADDRESS(ROW(), COLUMN(comb_rank_norm)), "") | W62: =IF(is_cat, comb_rank_norm + COUNTIF(INDIRECT(comb_rank_norm_run_range), comb_rank_norm)-1, "") | X62: =IF(is_cat, header_row_id + comb_rank_unique, row_id) -> -1 | Y62: =IF(is_empty, "", INDEX($J:$J, MATCH(row_id, $X:$X, 0))) | Z62: =IF(is_empty, "", IF(is_header, "Tracked", INDEX($K:$K, MATCH(row_id, $X:$X, 0)))) | AA62: =IF(is_empty, "", IF(is_header, "Budget", INDEX($L:$L, MATCH(row_id, $X:$X, 0)))) | AB62: =IF(is_empty, "", IF(is_header, "% Compl.", IFERROR(out_tracked / out_budget, "-"))) | AC62: =IF(is_empty, "", IF(is_header, "Remaining", IF(out_budget - out_tracked > 0, out_budget - out_tracked, 0))) | AD62: =IF(is_empty, "", IF(is_header, "Excess", IF(out_budget - out_tracked < 0, out_tracked - out_budget, 0)))
